Workbook

Sheet Reserves
A1: Year | B1: 2025 | C1: 2026 | D1: 2027 | E1: 2028 | F1: 2029 | G1: 2030 | H1: 2031 | I1: 2032 | J1: 2033 | K1: 2034 | L1: 2035 | M1: 2036 | N1: 2037 | O1: 2038 | P1: 2039 | Q1: 2040 | R1: 2041 | S1: 2042 | T1: 2043 | U1: 2044 | V1: 2045 | W1: 2046 | X1: 2047 | Y1: 2048 | Z1: 2049 | AA1: 2050 | AB1: 2051 | AC1: 2052 | AD1: 2053 | AE1: 2054 | AF1: 2055 | AG1: 2056
A2: RESERVES (Cash Surplus Yr-End) | B2: ='30 Year'!M47 -> 528488.74 | C2: ='30 Year'!AC47 -> 268775.72 | D2: ='30 Year'!AS47 -> 228405.76 | E2: ='30 Year'!BG47 -> 350309.58 | F2: ='30 Year'!BU47 -> 527869.51 | G2: ='30 Year'!BX47 -> 686202.63 | H2: ='30 Year'!BY47 -> 951900.25 | I2: ='30 Year'!BZ47 -> 1077903.8 | J2: ='30 Year'!CA47 -> 1309219.9 | K2: ='30 Year'!CB47 -> 1522556 | L2: ='30 Year'!CC47 -> 1163888.6 | M2: ='30 Year'!CD47 -> 927245.83 | N2: ='30 Year'!CE47 -> 762843.22 | ... AG2: ='30 Year'!CX47 -> 1884857.2
A3: Minimum Year-End Reserve Start 2030 | C3: 450000 | D3: =C3*(1+Inflation!$J$13) -> 465444.83 | E3: =D3*(1+Inflation!$J$13) -> 481419.75 | F3: =E3*(1+Inflation!$J$13) -> 497942.97 | G3: =F3*(1+Inflation!$J$13) -> 515033.29 | H3: =G3*(1+Inflation!$J$13) -> 532710.18 | I3: =H3*(1+Inflation!$J$13) -> 550993.77 | J3: =I3*(1+Inflation!$J$13) -> 569904.89 | K3: =J3*(1+Inflation!$J$13) -> 589465.08 | ... AG3: =AF3*(1+Inflation!$J$13) -> 1238464
A4: Monthly Cash-In / Unit | B4: =sum('30 Year'!B48:B49) -> 800 | C4: =SUM('30 Year'!R48:R49) -> 425 | D4: =SUM('30 Year'!AH48:AH49) -> 425 | E4: =SUM('30 Year'!AV48:AV49) -> 475 | F4: =SUM('30 Year'!BJ48:BJ49) -> 425 | G4: =SUM('30 Year'!BX48:BX49) -> 425 | H4: =SUM('30 Year'!BY48:BY49) -> 500 | I4: =SUM('30 Year'!BZ48:BZ49) -> 500 | J4: =SUM('30 Year'!CA48:CA49) -> 500 | K4: =SUM('30 Year'!CB48:CB49) -> 500 | L4: =SUM('30 Year'!CC48:CC49) -> 500 | M4: =SUM('30 Year'!CD48:CD49) -> 575 | N4: =SUM('30 Year'!CE48:CE49) -> 575 | ... AG4: =SUM('30 Year'!CX48:CX49) -> 850
B5: THIS CASH PROJECTION REPRESENTS THE BEST ESTIMATE OF THE FINANCIAL OUTLOOK. THE RIDGE PARK BOARD MAY CHANGE IT AT ANYTIME.
A6: Inflation Rate Sources: Federal Reserve Bank of St. Louis Producer Price Index by Industry for Building Maintenance, New Construction, and General Inflation.
A7: Ridge Park Property Data Sources: square footages, linear feet, and other dimensions measured and estimated from Ridge Park blue prints.
A8: Financial Data Sources: Bank Statements, Financial Statements from Accoutant, Ridge Park Annual Budget, Max Property Insurance Deductible, and cost estimates from Budget and Maintenance Committees.
A9: Assumptions: All Projects in each Annual Budget are completed. Current Inflation Rates are used for all future years.
C11: CLICK CHART AND HOVER CURSOR OVER BAR TO DISPLAY RESERVE BALANCE
A46: FOR DETAILS ON HOW THIS CHART WAS BUILT CLICK THIS LINK AND REQUEST ACCESS | G46: Ridge Park Budget Projection
A49: STANDARD FORMULA FOR FUTURE VALUES:
A51: FV = PV x (1 + r)^n
A52: PV = Present Value
A53: r = Interest or Inflation Rate (Annual %)
A54: n = Number of Compounding Periods (Years)

Sheet 30 Year
A1: FUNDING PLAN | B1: 1 | C1: 2 | D1: 3 | E1: 4 | F1: 5 | G1: 6 | H1: 7 | I1: 8 | J1: 9 | K1: 10 | L1: 11 | M1: 12 | Q1: FUNDING PLAN | R1: 1 | S1: 2 | T1: 3 | U1: 4 | V1: 5 | W1: 6 | X1: 7 | Y1: 8 | Z1: 9 | AA1: 10 | AB1: 11 | AC1: 12 | AG1: FUNDING PLAN | AU1: FUNDING PLAN | BI1: FUNDING PLAN | BW1: FUNDING PLAN
A2: 2025 Budget Projection GREEN = Bank Record or Check Register BLUE = Budgeted Averages & Estimates, Bids, BLACK = Formula Results | B2: Jan | C2: Feb | D2: Mar | E2: Apr | F2: May | G2: Jun | H2: July | I2: Aug | J2: Sep | K2: Oct | L2: Nov | M2: Dec | N2: Projected Total | O2: Budgeted Total | P2: Projected Over (+) Under (-) Budget | Q2: 2026 Budget Projection GREEN = Bank Record Numbers BLUE = Budget Number/Averages & Bids BLACK = Other Formula Results | R2: Jan | S2: Feb | T2: Mar | U2: Apr | V2: May | W2: Jun | X2: July | Y2: Aug | Z2: Sep | AA2: Oct | AB2: Nov | AC2: Dec | AD2: Projected Total | AE2: Budgeted Total | AF2: Projected Over (+) Under (-) Budget | AG2: PROJECTED Operating & Reserves Account Balances | AH2: Jan | AI2: Feb | AJ2: Mar | AK2: Apr | AL2: May | AM2: Jun | AN2: July | AO2: Aug | AP2: Sep | AQ2: Oct | AR2: Nov | AS2: Dec | AT2: Total 2027 | AU2: PROJECTED Operating & Reserves Account Balances | AV2: Jan | AW2: Feb | AX2: Mar | AY2: Apr | AZ2: May | BA2: Jun | BB2: July | BC2: Aug | BD2: Sep | BE2: Oct | BF2: Nov | BG2: Dec | BH2: Total 2028 | BI2: PROJECTED Operating & Reserves Account Balances | BJ2: Jan | BK2: Feb | BL2: Mar | BM2: Apr | BN2: May | BO2: Jun | BP2: July | BQ2: Aug | BR2: Sep | BS2: Oct | BT2: Nov | BU2: Dec | BV2: Total 2029 | BW2: PROJECTED Operating & Reserves Account Balances
B3: 2025 | C3: 2025 | D3: 2025 | E3: 2025 | F3: 2025 | G3: 2025 | H3: 2025 | I3: 2025 | J3: 2025 | K3: 2025 | L3: 2025 | M3: 2025 | N3: 2025 | O3: 2025 | P3: 2025 | R3: 2026 | S3: 2026 | T3: 2026 | U3: 2026 | V3: 2026 | W3: 2026 | X3: 2026 | Y3: 2026 | Z3: 2026 | AA3: 2026 | AB3: 2026 | AC3: 2026 | AD3: 2026 | AE3: 2026 | AH3: 2027 | AI3: 2027 | AJ3: 2027 | AK3: 2027 | AL3: 2027 | AM3: 2027 | AN3: 2027 | AO3: 2027 | AP3: 2027 | AQ3: 2027 | AR3: 2027 | AS3: 2027 | AT3: 2027 | AV3: 2028 | AW3: 2028 | AX3: 2028 | AY3: 2028 | AZ3: 2028 | BA3: 2028 | BB3: 2028 | BC3: 2028 | BD3: 2028 | BE3: 2028 | BF3: 2028 | BG3: 2028 | BH3: 2028 | BJ3: 2029 | BK3: 2029 | BL3: 2029 | BM3: 2029 | BN3: 2029 | BO3: 2029 | BP3: 2029 | BQ3: 2029 | BR3: 2029 | BS3: 2029 | BT3: 2029 | BU3: 2029 | BV3: 2029 | BX3: 2030 | BY3: 2031 | BZ3: 2032 | CA3: 2033 | CB3: 2034 | CC3: 2035 | CD3: 2036 | CE3: 2037 | CF3: 2038 | CG3: 2039 | CH3: 2040 | CI3: 2041 | CJ3: 2042 | CK3: 2043 | CL3: 2044 | CM3: 2045 | CN3: 2046 | CO3: 2047 | CP3: 2048 | CQ3: 2049 | CR3: 2050 | CS3: 2051 | CT3: 2052 | CU3: 2053 | CV3: 2054 | CW3: 2055 | CX3: 2056
A4: Operating Account (checking) | B4: 122944 | C4: 297940 | D4: 116875 | E4: 92821 | F4: 99109 | G4: 158512 | H4: 202997 | I4: 65081 | J4: 36737 | K4: =sum(J4+J16-J46-J5+J6+J48) -> 75293 | L4: 39900 | M4: 86497 | Q4: Operating Account (checking) | R4: 77854.91 | S4: 124896.59 | T4: 152070 | U4: =sum(T4+T16-T46-T5+T6) -> 161117.56 | V4: 113551 | W4: =sum(V4+V16-V46-V5+V6) -> 117195.81 | X4: =sum(W4+W16-W46-W5+W6) -> 89614.617 | Y4: =sum(X4+X16-X46-X5+X6) -> 68275.782 | Z4: =sum(Y4+Y16-Y46-Y5+Y6) -> 89345.03 | AA4: =sum(Z4+Z16-Z46-Z5+Z6) -> 85909.493 | AB4: =sum(AA4+AA16-AA46-AA5+AA6) -> 79319.85 | AC4: =sum(AB4+AB16-AB46-AB5+AB6) -> 47177.158 | AG4: Operating Account (checking) | AH4: =sum(AC4+AC16-AC46-AC5+AC6) -> 58224.717 | AI4: =sum(AH4+AH16-AH46-AH5+AH6) -> 69625.346 | AJ4: =sum(AI4+AI16-AI46-AI5+AI6) -> 81946.025 | AK4: =sum(AJ4+AJ16-AJ46-AJ5+AJ6) -> 92283.927 | AL4: =sum(AK4+AK16-AK46-AK5+AK6) -> 81780.094 | AM4: =sum(AL4+AL16-AL46-AL5+AL6) -> 63988.109 | AN4: =sum(AM4+AM16-AM46-AM5+AM6) -> 22255.729 | AO4: =sum(AN4+AN16-AN46-AN5+AN6) -> 39333.95 | AP4: =sum(AO4+AO16-AO46-AO5+AO6) -> 48412.17 | ... AS4: =sum(AR4+AR16-AR46-AR5+AR6) -> 80466.862 | AU4: Operating Account (checking) | AV4: =sum(AS4+AS16-AS46-AS5+AS6) -> 82854.764 | AW4: =sum(AV4+AV16-AV46-AV5+AV6) -> 99428.736 | AX4: =sum(AW4+AW16-AW46-AW5+AW6) -> 116920.76 | AY4: =sum(AX4+AX16-AX46-AX5+AX6) -> 132380.44 | AZ4: =sum(AY4+AY16-AY46-AY5+AY6) -> 139302.84 | BA4: =sum(AZ4+AZ16-AZ46-AZ5+AZ6) -> 87831.745 | BB4: =sum(BA4+BA16-BA46-BA5+BA6) -> 108437.31 | BC4: =sum(BB4+BB16-BB46-BB5+BB6) -> 129042.88 | BD4: =sum(BC4+BC16-BC46-BC5+BC6) -> 149020.35 | ... BG4: =sum(BF4+BF16-BF46-BF5+BF6) -> 192197.65 | BI4: Operating Account (checking) | BJ4: =sum(BG4+BG16-BG46-BG5+BG6) -> 209758.58 | BK4: =sum(BJ4+BJ16-BJ46-BJ5+BJ6) -> 217640.65 | BL4: =sum(BK4+BK16-BK46-BK5+BK6) -> 226438.72 | BM4: =sum(BL4+BL16-BL46-BL5+BL6) -> 233153.63 | BN4: =sum(BM4+BM16-BM46-BM5+BM6) -> 231301.36 | BO4: =sum(BN4+BN16-BN46-BN5+BN6) -> 243580.64 | BP4: =sum(BO4+BO16-BO46-BO5+BO6) -> 255859.91 | BQ4: =sum(BP4+BP16-BP46-BP5+BP6) -> 268139.18 | BR4: =sum(BQ4+BQ16-BQ46-BQ5+BQ6) -> 279767.83 | ... BU4: =sum(BT4+BT16-BT46-BT5+BT6) -> 318449.82 | BW4: Operating Account (checking) | BX4: =sum(BU4+BU16-BU46-BU5+BU6) -> 327318.51 | BY4: =sum(BX4+BX16-BX46-BX5+BX6) -> 555651.63 | BZ4: =sum(BY4+BY16-BY46-BY5+BY6) -> 761349.25 | CA4: =sum(BZ4+BZ16-BZ46-BZ5+BZ6) -> 827352.78 | CB4: =sum(CA4+CA16-CA46-CA5+CA6) -> 998668.91 | CC4: =sum(CB4+CB16-CB46-CB5+CB6) -> 1152005 | CD4: =sum(CC4+CC16-CC46-CC5+CC6) -> 733337.59 | CE4: =sum(CD4+CD16-CD46-CD5+CD6) -> 536694.83 | CF4: =sum(CE4+CE16-CE46-CE5+CE6) -> 312292.22 | ... CX4: =sum(CW4+CW16-CW46-CW5+CW6) -> 130610.03
A5: Auto Transfer to Reserves | B5: 5000 | C5: 256000 | D5: 55000 | E5: 56000 | F5: 5000 | G5: 5000 | H5: 5000 | I5: 5000 | J5: 5000 | K5: 5000 | L5: 5000 | M5: 5000 | N5: =SUM(B5:M5) -> 412000 | O5: 170000 | P5: =N5-O5 -> 242000 | Q5: Auto Transfer to Reserves | R5: 5000 | S5: 5000 | T5: 5000 | U5: 5000 | V5: 5000 | W5: 5000 | X5: 5000 | Y5: 5000 | Z5: 5000 | AA5: 5000 | AB5: 5000 | AC5: 5000 | AG5: Auto Transfer to Reserves | AH5: 5000 | AI5: 5000 | AJ5: 5000 | AK5: 5000 | AL5: 5000 | AM5: 5000 | AN5: 5000 | AO5: 5000 | AP5: 5000 | AQ5: 10000 | AR5: 15000 | AS5: 15000 | AU5: Auto Transfer to Reserves | AV5: 5000 | AW5: 5000 | AX5: 5000 | AY5: 5000 | AZ5: 5000 | BA5: 5000 | BB5: 5000 | BC5: 5000 | BD5: 10000 | BE5: 10000 | BF5: 10000 | BG5: 5000 | BI5: Auto Transfer to Reserves | BJ5: 5000 | BK5: 5000 | BL5: 5000 | BM5: 5000 | BN5: 5000 | BO5: 5000 | BP5: 5000 | BQ5: 5000 | BR5: 5000 | BS5: 5000 | BT5: 5000 | BU5: 5000 | BW5: Auto Transfer to Reserves | BX5: 60000 | BY5: 60000 | BZ5: 60000 | CA5: 60000 | CB5: 60000 | CC5: 60000 | CD5: 60000 | CE5: 60000 | CF5: 60000 | CG5: 60000 | CH5: 60000 | CI5: 60000 | CJ5: 60000 | CK5: 60000 | CL5: 60000 | CM5: 60000 | CN5: 60000 | CO5: 60000 | CP5: 60000 | CQ5: 60000 | CR5: 60000 | CS5: 60000 | CT5: 60000 | CU5: 60000 | CV5: 60000 | CW5: 60000 | CX5: 60000
A6: Transfer to Operating | K6: 200000 | M6: 50000 | Q6: Transfer to Operating | W6: 150000 | X6: 80000 | Y6: 80000 | Z6: 80000 | AA6: 90000 | AG6: Transfer to Operating | AM6: 100000 | AN6: 50000 | AU6: Transfer to Operating | AZ6: 80000 | BI6: Transfer to Operating | BW6: Transfer to Operating | BX6: 130000 | CD6: 100000
A7: Reserves Account (savings) | B7: 227639 | C7: 232649 | D7: 488667 | E7: =sum(D7+D5-D6) -> 543667 | F7: =sum(E7+E5-E6) -> 599667 | G7: =sum(F7+F5-F6) -> 604667 | H7: 635609 | I7: 516305 | J7: 521158 | K7: =sum(J7+J5-J6) -> 526158 | L7: 533568 | M7: 399381 | Q7: Reserves Account (Money Mkt Accts #3731 & #0598) | R7: 405061 | S7: 410716 | T7: 416309 | U7: =sum(T7+T5-T6) -> 421309 | V7: 522040 | W7: =sum(V7+V5-V6) -> 527040 | X7: =sum(W7+W5-W6) -> 382040 | Y7: =sum(X7+X5-X6) -> 307040 | Z7: =sum(Y7+Y5-Y6) -> 232040 | AA7: =sum(Z7+Z5-Z6) -> 157040 | AB7: =sum(AA7+AA5-AA6) -> 72040 | AC7: =sum(AB7+AB5-AB6) -> 77040 | AG7: Reserves Account (savings) | AH7: =sum(AC7+AC5-AC6) -> 82040 | AI7: =sum(AH7+AH5-AH6) -> 87040 | AJ7: =sum(AI7+AI5+AI8-AI6) -> 220551 | AK7: =sum(AJ7+AJ5-AJ6) -> 225551 | AL7: =sum(AK7+AK5-AK6) -> 230551 | AM7: =sum(AL7+AL5-AL6) -> 235551 | AN7: =sum(AM7+AM5-AM6) -> 140551 | AO7: =sum(AN7+AN5-AN6) -> 95551 | AP7: =sum(AO7+AO5-AO6) -> 100551 | AQ7: =sum(AP7+AP5-AP6) -> 105551 | AR7: =sum(AQ7+AQ5-AQ6) -> 115551 | AS7: =sum(AR7+AR5-AR6) -> 130551 | AU7: Reserves Account (savings) | AV7: =sum(AS7+AS5-AS6) -> 145551 | AW7: =sum(AV7+AV5-AV6) -> 150551 | AX7: =sum(AW7+AW5-AW6) -> 155551 | AY7: =sum(AX7+AX5-AX6) -> 160551 | AZ7: =sum(AY7+AY5-AY6) -> 165551 | BA7: =sum(AZ7+AZ5-AZ6) -> 90551 | BB7: =sum(BA7+BA5-BA6) -> 95551 | BC7: =sum(BB7+BB5-BB6) -> 100551 | BD7: =sum(BC7+BC5-BC6) -> 105551 | ... BG7: =sum(BF7+BF5-BF6) -> 135551 | BI7: Reserves Account (savings) | BJ7: =sum(BG7+BG5-BG6) -> 140551 | BK7: =sum(BJ7+BJ5-BJ6) -> 145551 | BL7: =sum(BK7+BK5-BK6) -> 150551 | BM7: =sum(BL7+BL5-BL6) -> 155551 | BN7: =sum(BM7+BM5-BM6) -> 160551 | BO7: =sum(BN7+BN5-BN6) -> 165551 | BP7: =sum(BO7+BO5-BO6) -> 170551 | BQ7: =sum(BP7+BP5-BP6) -> 175551 | BR7: =sum(BQ7+BQ5-BQ6) -> 180551 | ... BU7: =sum(BT7+BT5-BT6) -> 195551 | BW7: Reserves Account (savings) | BX7: =sum(BU7+BU5-BU6) -> 200551 | BY7: =sum(BX7+BX5-BX6) -> 130551 | BZ7: =sum(BY7+BY5-BY6) -> 190551 | CA7: =sum(BZ7+BZ5-BZ6) -> 250551 | CB7: =sum(CA7+CA5-CA6) -> 310551 | CC7: =sum(CB7+CB5-CB6) -> 370551 | CD7: =sum(CC7+CC5-CC6) -> 430551 | CE7: =sum(CD7+CD5-CD6) -> 390551 | CF7: =sum(CE7+CE5-CE6) -> 450551 | ... CX7: =sum(CW7+CW5-CW6) -> 1530551
A8: Investment Account (CD) | B8: 13231 | C8: 13231 | D8: 13231 | E8: 13231 | F8: =E8+((E8*Inflation!$E$11)/12) -> 13255.808 | G8: =F8+((F8*Inflation!$E$11)/12) -> 13280.663 | H8: 125000 | I8: =H8 -> 125000 | J8: =I8 -> 125000 | K8: =J8 -> 125000 | L8: =K8 -> 125000 | M8: =L8 -> 125000 | Q8: Investment Account (Cert of Deposit) | R8: =M8 -> 125000 | S8: =R8 -> 125000 | T8: =S8 -> 125000 | U8: 128511 | V8: 128511 | W8: =V8 -> 128511 | X8: =W8 -> 128511 | Y8: =X8 -> 128511 | Z8: =Y8 -> 128511 | AA8: =Z8 -> 128511 | AB8: =AA8 -> 128511 | AC8: =AB8 -> 128511 | AG8: Investment Account | AH8: =AC8 -> 128511 | AI8: =AH8 -> 128511 | AJ8: 0 | AK8: 0 | AL8: 0 | AM8: 0 | AN8: 0 | AO8: 0 | AP8: 0 | AQ8: 0 | AR8: 0 | AS8: 0 | AU8: Investment Account | AV8: =AS8 -> 0 | AW8: =AV8 -> 0 | AX8: =AW8+((AW8*Inflation!$E$11)/12) -> 0 | AY8: =AX8 -> 0 | AZ8: =AY8 -> 0 | BA8: =AZ8 -> 0 | BB8: =BA8 -> 0 | BC8: =BB8 -> 0 | BD8: =BC8 -> 0 | BE8: =BD8 -> 0 | BF8: =BE8 -> 0 | BG8: =BF8 -> 0 | BI8: Investment Account | BJ8: =BG8 -> 0 | BK8: =BJ8 -> 0 | BL8: =BK8+((BK8*Inflation!$E$11)/12) -> 0 | BM8: =BL8 -> 0 | BN8: =BM8 -> 0 | BO8: =BN8 -> 0 | BP8: =BO8 -> 0 | BQ8: =BP8 -> 0 | BR8: =BQ8 -> 0 | BS8: =BR8 -> 0 | BT8: =BS8 -> 0 | BU8: =BT8 -> 0 | BW8: Investment Account | BX8: =BU8+(BU8*Inflation!$E$11) -> 0 | BY8: =BX8+((BX8*Inflation!$E$11)) -> 0 | BZ8: =BY8+((BY8*Inflation!$E$11)) -> 0 | CA8: =BZ8+((BZ8*Inflation!$E$11)) -> 0 | CB8: =CA8+((CA8*Inflation!$E$11)) -> 0 | CC8: =CB8+((CB8*Inflation!$E$11)) -> 0 | CD8: =CC8+((CC8*Inflation!$E$11)) -> 0 | CE8: =CD8+((CD8*Inflation!$E$11)) -> 0 | CF8: =CE8+((CE8*Inflation!$E$11)) -> 0 | ... CX8: =CW8+((CW8*Inflation!$E$11)) -> 0
A9: Starting Balance (Current Reserves) | B9: =sum(B4,B7,B8) -> 363814 | C9: =sum(C4,C7,C8) -> 543820 | D9: =sum(D4,D7,D8) -> 618773 | E9: =sum(E4,E7,E8) -> 649719 | F9: =sum(F4,F7,F8) -> 712031.81 | G9: =sum(G4,G7,G8) -> 776459.66 | H9: =sum(H4,H7,H8) -> 963606 | I9: =sum(I4,I7,I8) -> 706386 | ... M9: =sum(M4,M7,M8) -> 610878 | Q9: Starting Balance (Current Reserves) | R9: =sum(R4,R7,R8) -> 607915.91 | S9: =sum(S4,S7,S8) -> 660612.59 | T9: =sum(T4,T7,T8) -> 693379 | U9: =sum(U4,U7,U8) -> 710937.56 | V9: =sum(V4,V7,V8) -> 764102 | W9: =sum(W4,W7,W8) -> 772746.81 | X9: =sum(X4,X7,X8) -> 600165.62 | Y9: =sum(Y4,Y7,Y8) -> 503826.78 | ... AC9: =sum(AC4,AC7,AC8) -> 252728.16 | AG9: Starting Balance (Current Reserves) | AH9: =sum(AH4,AH7,AH8) -> 268775.72 | AI9: =sum(AI4,AI7,AI8) -> 285176.35 | AJ9: =sum(AJ4,AJ7,AJ8) -> 302497.02 | AK9: =sum(AK4,AK7,AK8) -> 317834.93 | AL9: =sum(AL4,AL7,AL8) -> 312331.09 | AM9: =sum(AM4,AM7,AM8) -> 299539.11 | AN9: =sum(AN4,AN7,AN8) -> 162806.73 | AO9: =sum(AO4,AO7,AO8) -> 134884.95 | ... AS9: =sum(AS4,AS7,AS8) -> 211017.86 | AU9: Starting Balance (Current Reserves) | AV9: =sum(AV4,AV7,AV8) -> 228405.76 | AW9: =sum(AW4,AW7,AW8) -> 249979.74 | AX9: =sum(AX4,AX7,AX8) -> 272471.76 | AY9: =sum(AY4,AY7,AY8) -> 292931.44 | AZ9: =sum(AZ4,AZ7,AZ8) -> 304853.84 | BA9: =sum(BA4,BA7,BA8) -> 178382.75 | BB9: =sum(BB4,BB7,BB8) -> 203988.31 | BC9: =sum(BC4,BC7,BC8) -> 229593.88 | ... BG9: =sum(BG4,BG7,BG8) -> 327748.65 | BI9: Starting Balance (Current Reserves) | BJ9: =sum(BJ4,BJ7,BJ8) -> 350309.58 | BK9: =sum(BK4,BK7,BK8) -> 363191.65 | BL9: =sum(BL4,BL7,BL8) -> 376989.72 | BM9: =sum(BM4,BM7,BM8) -> 388704.63 | BN9: =sum(BN4,BN7,BN8) -> 391852.36 | BO9: =sum(BO4,BO7,BO8) -> 409131.64 | BP9: =sum(BP4,BP7,BP8) -> 426410.91 | BQ9: =sum(BQ4,BQ7,BQ8) -> 443690.18 | ... BU9: =sum(BU4,BU7,BU8) -> 514000.82 | BW9: Starting Balance (Current Reserves) | BX9: =sum(BX4,BX7,BX8) -> 527869.51 | BY9: =sum(BY4,BY7,BY8) -> 686202.63 | BZ9: =sum(BZ4,BZ7,BZ8) -> 951900.25 | CA9: =sum(CA4,CA7,CA8) -> 1077903.8 | CB9: =sum(CB4,CB7,CB8) -> 1309219.9 | CC9: =sum(CC4,CC7,CC8) -> 1522556 | CD9: =sum(CD4,CD7,CD8) -> 1163888.6 | CE9: =sum(CE4,CE7,CE8) -> 927245.83 | ... CX9: =sum(CX4,CX7,CX8) -> 1661161
A10: CASH IN | Q10: CASH IN | AG10: CASH IN | AU10: CASH IN | BI10: CASH IN | BW10: CASH IN
A11: Interest Income | B11: 10 | C11: 18 | D11: 23 | E11: 25 | F11: 26 | G11: 24 | H11: 686 | I11: =I7*(Inflation!$E$11)/12 -> 968.07187 | J11: 1119 | K11: 637 | L11: 814 | M11: =M7*(Inflation!$E$11)/12 -> 748.83938 | N11: =SUM(B11:M11) -> 5098.9113 | O11: 4008 | P11: =N11-O11 -> 1090.9113 | Q11: Interest Income | R11: 655 | S11: 592 | T11: =(T7*(Inflation!$F$11)/12)+3751 -> 4444.8483 | U11: =U7*(Inflation!$F$11)/12 -> 702.18167 | V11: =V7*(Inflation!$F$11)/12 -> 870.06667 | W11: =W7*(Inflation!$F$11)/12 -> 878.4 | X11: =X7*(Inflation!$F$11)/12 -> 636.73333 | Y11: =Y7*(Inflation!$F$11)/12 -> 511.73333 | Z11: =Z7*(Inflation!$F$11)/12 -> 386.73333 | AA11: =AA7*(Inflation!$F$11)/12 -> 261.73333 | AB11: =AB7*(Inflation!$F$11)/12 -> 120.06667 | AC11: =AC7*(Inflation!$F$11)/12 -> 128.4 | AD11: =SUM(R11:AC11) -> 10187.897 | AE11: 5300 | AF11: =AD11-AE11 -> 4887.8967 | AG11: Interest Income | AH11: =AH7*(Inflation!$F$11)/12 -> 136.73333 | AI11: =AI7*(Inflation!$F$11)/12 -> 145.06667 | AJ11: =AJ7*(Inflation!$G$11)/12 -> 367.585 | AK11: =AK7*(Inflation!$G$11)/12 -> 375.91833 | AL11: =AL7*(Inflation!$G$11)/12 -> 384.25167 | AM11: =AM7*(Inflation!$G$11)/12 -> 392.585 | AN11: =AN7*(Inflation!$G$11)/12 -> 234.25167 | AO11: =AO7*(Inflation!$G$11)/12 -> 159.25167 | AP11: =AP7*(Inflation!$G$11)/12 -> 167.585 | AQ11: =AQ7*(Inflation!$G$11)/12 -> 175.91833 | ... AS11: =AS7*(Inflation!$G$11)/12 -> 217.585 | AT11: =SUM(AH11:AS11) -> 2949.3167 | AU11: Interest Income | AV11: =AV7*(Inflation!$G$11)/12 -> 242.585 | AW11: =AW7*(Inflation!$G$11)/12 -> 250.91833 | AX11: =AX7*(Inflation!$H$11)/12 -> 259.25167 | AY11: =AY7*(Inflation!$H$11)/12 -> 267.585 | AZ11: =AZ7*(Inflation!$H$11)/12 -> 275.91833 | BA11: =BA7*(Inflation!$H$11)/12 -> 150.91833 | BB11: =BB7*(Inflation!$H$11)/12 -> 159.25167 | BC11: =BC7*(Inflation!$H$11)/12 -> 167.585 | BD11: =BD7*(Inflation!$H$11)/12 -> 175.91833 | BE11: =BE7*(Inflation!$H$11)/12 -> 192.585 | ... BG11: =BG7*(Inflation!$H$11)/12 -> 225.91833 | BH11: =SUM(AV11:BG11) -> 2577.6867 | BI11: Interest Income | BJ11: =BJ7*(Inflation!$H$11)/12 -> 234.25167 | BK11: =BK7*(Inflation!$H$11)/12 -> 242.585 | BL11: =BL7*(Inflation!$I$11)/12 -> 250.91833 | BM11: =BM7*(Inflation!$I$11)/12 -> 259.25167 | BN11: =BN7*(Inflation!$I$11)/12 -> 267.585 | BO11: =BO7*(Inflation!$I$11)/12 -> 275.91833 | BP11: =BP7*(Inflation!$I$11)/12 -> 284.25167 | BQ11: =BQ7*(Inflation!$I$11)/12 -> 292.585 | BR11: =BR7*(Inflation!$I$11)/12 -> 300.91833 | BS11: =BS7*(Inflation!$I$11)/12 -> 309.25167 | ... BU11: =BU7*(Inflation!$I$11)/12 -> 325.91833 | BV11: =SUM(BJ11:BU11) -> 3361.02 | BW11: Interest Income | BX11: =BX7*(Inflation!$J$11)/12 -> 334.25167 | BY11: =BY7*(Inflation!$J$11)/12 -> 217.585 | BZ11: =BZ7*(Inflation!$J$11)/12 -> 317.585 | CA11: =CA7*(Inflation!$J$11)/12 -> 417.585 | CB11: =CB7*(Inflation!$J$11)/12 -> 517.585 | CC11: =CC7*(Inflation!$J$11)/12 -> 617.585 | CD11: =CD7*(Inflation!$J$11)/12 -> 717.585 | CE11: =CE7*(Inflation!$J$11)/12 -> 650.91833 | ... CX11: =CX7*(Inflation!$J$11)/12 -> 2550.9183
A12: Income from Owner Assessments | B12: 254010 | C12: 98880 | D12: 101008 | E12: 92733 | F12: 83435 | G12: 88100 | H12: 85296 | I12: 86668 | J12: 81555 | K12: 97010 | L12: 84290 | M12: 86668 | N12: =SUM(B12:M12) -> 1239653 | O12: 1324800 | P12: =60000+N12-O12 -> -25147 | Q12: Income from Owner Assessments | R12: 78325 | S12: 65716 | T12: =($AE$12-($R12+$S12))/($AC$1-$S1) -> 55975.9 | U12: =($AE$12-($R12+$S12))/($AC$1-$S1) -> 55975.9 | V12: =($AE$12-($R12+$S12))/($AC$1-$S1) -> 55975.9 | W12: =($AE$12-($R12+$S12))/($AC$1-$S1) -> 55975.9 | X12: =($AE$12-($R12+$S12))/($AC$1-$S1) -> 55975.9 | Y12: =($AE$12-($R12+$S12))/($AC$1-$S1) -> 55975.9 | Z12: =($AE$12-($R12+$S12))/($AC$1-$S1) -> 55975.9 | AA12: =($AE$12-($R12+$S12))/($AC$1-$S1) -> 55975.9 | ... AC12: =($AE$12-($R12+$S12))/($AC$1-$S1) -> 55975.9 | AD12: =SUM(R12:AC12) -> 703800 | AE12: 703800 | AF12: =AD12-AE12 -> 1.1641532e-10 | AG12: Income from Owner Assessments | AH12: =138*(AH49+AH48) -> 58650 | AI12: =138*(AI49+AI48) -> 58650 | AJ12: =138*(AJ49+AJ48) -> 58650 | AK12: =138*(AK49+AK48) -> 58650 | AL12: =138*(AL49+AL48) -> 58650 | AM12: =138*(AM49+AM48) -> 58650 | AN12: =138*(AN49+AN48) -> 58650 | AO12: =138*(AO49+AO48) -> 58650 | ... AS12: =138*(AS49+AS48) -> 58650 | AT12: =SUM(AH12:AS12) -> 703800 | AU12: Income from Owner Assessments | AV12: =138*(AV49+AV48) -> 65550 | AW12: =138*(AW49+AW48) -> 65550 | AX12: =138*(AX49+AX48) -> 65550 | AY12: =138*(AY49+AY48) -> 65550 | AZ12: =138*(AZ49+AZ48) -> 65550 | BA12: =138*(BA49+BA48) -> 65550 | BB12: =138*(BB49+BB48) -> 65550 | BC12: =138*(BC49+BC48) -> 65550 | ... BG12: =138*(BG49+BG48) -> 65550 | BH12: =SUM(AV12:BG12) -> 786600 | BI12: Income from Owner Assessments | BJ12: =138*(BJ49+BJ48) -> 58650 | BK12: =138*(BK49+BK48) -> 58650 | BL12: =138*(BL49+BL48) -> 58650 | BM12: =138*(BM49+BM48) -> 58650 | BN12: =138*(BN49+BN48) -> 58650 | BO12: =138*(BO49+BO48) -> 58650 | BP12: =138*(BP49+BP48) -> 58650 | BQ12: =138*(BQ49+BQ48) -> 58650 | ... BU12: =138*(BU49+BU48) -> 58650 | BV12: =SUM(BJ12:BU12) -> 703800 | BW12: Income from Owner Assessments | BX12: =138*(BX48+BX49)*12 -> 703800 | BY12: =138*(BY48+BY49)*12 -> 828000 | BZ12: =138*(BZ48+BZ49)*12 -> 828000 | CA12: =138*(CA48+CA49)*12 -> 828000 | CB12: =138*(CB48+CB49)*12 -> 828000 | CC12: =138*(CC48+CC49)*12 -> 828000 | CD12: =138*(CD48+CD49)*12 -> 952200 | CE12: =138*(CE48+CE49)*12 -> 952200 | ... CX12: =138*(CX48+CX49)*12 -> 1407600
A13: Other Income Apt Rent | B13: 0 | C13: 0 | D13: 2500 | E13: 2500 | F13: 2500 | G13: 2500 | H13: 2500 | I13: 2500 | J13: 2500 | K13: 2500 | L13: 2500 | M13: 2500 | N13: =SUM(B13:M13) -> 25000 | O13: 30000 | P13: =N13-O13 -> -5000 | Q13: Other Income Apt Rent | R13: 2500 | S13: =R13 -> 2500 | T13: =S13 -> 2500 | U13: =T13 -> 2500 | V13: =U13 -> 2500 | W13: =V13 -> 2500 | X13: =W13 -> 2500 | Y13: =X13 -> 2500 | Z13: =Y13 -> 2500 | ... AC13: =AB13 -> 2500 | AD13: =SUM(R13:AC13) -> 30000 | AE13: 30000 | AF13: =AD13-AE13 -> 0 | AG13: Other Income Apt Rent | AH13: =AC13*(1+(Inflation!$F$6)) -> 2562.5 | AI13: =AH13 -> 2562.5 | AJ13: =AI13 -> 2562.5 | AK13: =AJ13 -> 2562.5 | AL13: =AK13 -> 2562.5 | AM13: =AL13 -> 2562.5 | AN13: =AM13 -> 2562.5 | AO13: =AN13 -> 2562.5 | AP13: =AO13 -> 2562.5 | ... AS13: =AR13 -> 2562.5 | AT13: =SUM(AH13:AS13) -> 30750 | AU13: Other Income Apt Rent | AV13: =AS13*(1+(Inflation!$F$6)) -> 2626.5625 | AW13: =AV13 -> 2626.5625 | AX13: =AW13 -> 2626.5625 | AY13: =AX13 -> 2626.5625 | AZ13: =AY13 -> 2626.5625 | BA13: =AZ13 -> 2626.5625 | BB13: =BA13 -> 2626.5625 | BC13: =BB13 -> 2626.5625 | BD13: =BC13 -> 2626.5625 | ... BG13: =BF13 -> 2626.5625 | BH13: =SUM(AV13:BG13) -> 31518.75 | BI13: Other Income Apt Rent | BJ13: =BG13*(1+(Inflation!$F$6)) -> 2692.2266 | BK13: =BJ13 -> 2692.2266 | BL13: =BK13 -> 2692.2266 | BM13: =BL13 -> 2692.2266 | BN13: =BM13 -> 2692.2266 | BO13: =BN13 -> 2692.2266 | BP13: =BO13 -> 2692.2266 | BQ13: =BP13 -> 2692.2266 | BR13: =BQ13 -> 2692.2266 | ... BU13: =BT13 -> 2692.2266 | BV13: =SUM(BJ13:BU13) -> 32306.719 | BW13: Other Income Apt Rent | BX13: =BV13*(1+Inflation!$I$5) -> 33114.387 | BY13: =BX13*(1+Inflation!$I$5) -> 33942.246 | BZ13: =BY13*(1+Inflation!$I$5) -> 34790.803 | CA13: =BZ13*(1+Inflation!$I$5) -> 35660.573 | CB13: =CA13*(1+Inflation!$I$5) -> 36552.087 | CC13: =CB13*(1+Inflation!$I$5) -> 37465.889 | CD13: =CC13*(1+Inflation!$I$5) -> 38402.536 | CE13: =CD13*(1+Inflation!$I$5) -> 39362.6 | CF13: =CE13*(1+Inflation!$I$5) -> 40346.665 | ... CX13: =CW13*(1+Inflation!$I$5) -> 62927.027
A14: RV Park Fees | B14: 0 | C14: 0 | D14: 0 | E14: 0 | F14: 0 | G14: 0 | H14: 0 | I14: 0 | J14: 0 | K14: 0 | L14: 0 | M14: 0 | N14: =SUM(B14:M14) -> 0 | O14: 2100 | P14: =N14-O14 -> -2100 | Q14: RV Park Fees | R14: 175 | S14: =R14 -> 175 | T14: =S14 -> 175 | U14: =T14 -> 175 | V14: =U14 -> 175 | W14: =V14 -> 175 | X14: =W14 -> 175 | Y14: =X14 -> 175 | Z14: =Y14 -> 175 | ... AC14: =AB14 -> 175 | AD14: =SUM(R14:AC14) -> 2100 | AE14: 2100 | AF14: =AD14-AE14 -> 0 | AG14: RV Park Fees | AH14: =AC14*(1+(Inflation!$F$6)) -> 179.375 | AI14: =AH14 -> 179.375 | AJ14: =AI14 -> 179.375 | AK14: =AJ14 -> 179.375 | AL14: =AK14 -> 179.375 | AM14: =AL14 -> 179.375 | AN14: =AM14 -> 179.375 | AO14: =AN14 -> 179.375 | AP14: =AO14 -> 179.375 | ... AS14: =AR14 -> 179.375 | AT14: =SUM(AH14:AS14) -> 2152.5 | AU14: RV Park Fees | AV14: =AS14*(1+(Inflation!$F$6)) -> 183.85938 | AW14: =AV14 -> 183.85938 | AX14: =AW14 -> 183.85938 | AY14: =AX14 -> 183.85938 | AZ14: =AY14 -> 183.85938 | BA14: =AZ14 -> 183.85938 | BB14: =BA14 -> 183.85938 | BC14: =BB14 -> 183.85938 | BD14: =BC14 -> 183.85938 | ... BG14: =BF14 -> 183.85938 | BH14: =SUM(AV14:BG14) -> 2206.3125 | BI14: RV Park Fees | BJ14: =BG14*(1+(Inflation!$F$6)) -> 188.45586 | BK14: =BJ14 -> 188.45586 | BL14: =BK14 -> 188.45586 | BM14: =BL14 -> 188.45586 | BN14: =BM14 -> 188.45586 | BO14: =BN14 -> 188.45586 | BP14: =BO14 -> 188.45586 | BQ14: =BP14 -> 188.45586 | BR14: =BQ14 -> 188.45586 | ... BU14: =BT14 -> 188.45586 | BV14: =SUM(BJ14:BU14) -> 2261.4703 | BW14: RV Park Fees | BX14: =BV14*(1+Inflation!$I$5) -> 2318.0071 | BY14: =BX14*(1+Inflation!$I$5) -> 2375.9572 | BZ14: =BY14*(1+Inflation!$I$5) -> 2435.3562 | CA14: =BZ14*(1+Inflation!$I$5) -> 2496.2401 | CB14: =CA14*(1+Inflation!$I$5) -> 2558.6461 | CC14: =CB14*(1+Inflation!$I$5) -> 2622.6122 | CD14: =CC14*(1+Inflation!$I$5) -> 2688.1775 | CE14: =CD14*(1+Inflation!$I$5) -> 2755.382 | CF14: =CE14*(1+Inflation!$I$5) -> 2824.2665 | ... CX14: =CW14*(1+Inflation!$I$5) -> 4404.8919
A15: Late Fees, Resale Certificates | B15: 0 | C15: 0 | D15: 0 | E15: 0 | F15: 0 | G15: 0 | H15: 71 | I15: 0 | J15: 0 | K15: 0 | L15: 0 | M15: 0 | N15: =SUM(B15:M15) -> 71 | P15: =N15-O15 -> 71 | Q15: Late Fees, Resale Certificates | R15: =M15*(1+(Inflation!$F$6)) -> 0 | S15: =R15 -> 0 | T15: =S15 -> 0 | U15: =T15 -> 0 | V15: =U15 -> 0 | W15: =V15 -> 0 | X15: =W15 -> 0 | Y15: =X15 -> 0 | Z15: =Y15 -> 0 | ... AB15: =AA15 -> 0 | AC15: 0 | AD15: =SUM(R15:AC15) -> 0 | AE15: 0 | AF15: =AD15-AE15 -> 0 | AG15: Late Fees, Resale Certificates | AH15: =AC15*(1+(Inflation!$F$6)) -> 0 | AI15: =AH15 -> 0 | AT15: =SUM(AH15:AS15) -> 0 | AU15: Late Fees, Resale Certificates | AV15: =AS15*(1+(Inflation!$F$6)) -> 0 | AW15: =AV15 -> 0 | AX15: =AW15 -> 0 | AY15: =AX15 -> 0 | AZ15: =AY15 -> 0 | BA15: =AZ15 -> 0 | BB15: =BA15 -> 0 | BC15: =BB15 -> 0 | BD15: =BC15 -> 0 | ... BG15: =BF15 -> 0 | BH15: =SUM(AV15:BG15) -> 0 | BI15: Late Fees, Resale Certificates | BJ15: =BG15*(1+(Inflation!$F$6)) -> 0 | BK15: =BJ15 -> 0 | BL15: =BK15 -> 0 | BM15: =BL15 -> 0 | BN15: =BM15 -> 0 | BO15: =BN15 -> 0 | BP15: =BO15 -> 0 | BQ15: =BP15 -> 0 | BR15: =BQ15 -> 0 | ... BU15: =BT15 -> 0 | BV15: =SUM(BJ15:BU15) -> 0 | BW15: Late Fees, Resale Certificates | BX15: =BV15*(1+Inflation!$I$5) -> 0 | BY15: =BX15*(1+Inflation!$I$5) -> 0 | BZ15: =BY15*(1+Inflation!$I$5) -> 0 | CA15: =BZ15*(1+Inflation!$I$5) -> 0 | CB15: =CA15*(1+Inflation!$I$5) -> 0 | CC15: =CB15*(1+Inflation!$I$5) -> 0 | CD15: =CC15*(1+Inflation!$I$5) -> 0 | CE15: =CD15*(1+Inflation!$I$5) -> 0 | CF15: =CE15*(1+Inflation!$I$5) -> 0 | ... CX15: =CW15*(1+Inflation!$I$5) -> 0
A16: TOTAL CASH IN | B16: =SUM(B11:B15) -> 254020 | C16: =SUM(C11:C15) -> 98898 | D16: =SUM(D11:D15) -> 103531 | E16: =SUM(E11:E15) -> 95258 | F16: =SUM(F11:F15) -> 85961 | G16: =SUM(G11:G15) -> 90624 | H16: =SUM(H11:H15) -> 88553 | I16: =SUM(I11:I15) -> 90136.072 | ... M16: =SUM(M11:M15) -> 89916.839 | N16: =SUM(B16:M16) -> 1269822.9 | O16: =SUM(O11:O15) -> 1360908 | P16: =SUM(P12:P15) -> -32176 | Q16: TOTAL CASH IN | R16: =SUM(R11:R15)-R11 -> 81000 | S16: =SUM(S11:S15)-S11 -> 68391 | T16: =SUM(T11:T15)-T11 -> 58650.9 | U16: =SUM(U11:U15)-U11 -> 58650.9 | V16: =SUM(V11:V15)-V11 -> 58650.9 | W16: =SUM(W11:W15)-W11 -> 58650.9 | X16: =SUM(X11:X15)-X11 -> 58650.9 | Y16: =SUM(Y11:Y15)-Y11 -> 58650.9 | ... AC16: =SUM(AC11:AC15)-AC11 -> 58650.9 | AD16: =SUM(R16:AC16) -> 735900 | AE16: =SUM(AE11:AE15) -> 741200 | AG16: TOTAL CASH IN | AH16: =SUM(AH11:AH15)-AH11 -> 61391.875 | AI16: =SUM(AI11:AI15)-AI11 -> 61391.875 | AJ16: =SUM(AJ11:AJ15)-AJ11 -> 61391.875 | AK16: =SUM(AK11:AK15)-AK11 -> 61391.875 | AL16: =SUM(AL11:AL15)-AL11 -> 61391.875 | AM16: =SUM(AM11:AM15)-AM11 -> 61391.875 | AN16: =SUM(AN11:AN15)-AN11 -> 61391.875 | AO16: =SUM(AO11:AO15)-AO11 -> 61391.875 | ... AS16: =SUM(AS11:AS15)-AS11 -> 61391.875 | AT16: =SUM(AH16:AS16) -> 736702.5 | AU16: TOTAL CASH IN | AV16: =SUM(AV11:AV15)-AV11 -> 68360.422 | AW16: =SUM(AW11:AW15)-AW11 -> 68360.422 | AX16: =SUM(AX11:AX15)-AX11 -> 68360.422 | AY16: =SUM(AY11:AY15)-AY11 -> 68360.422 | AZ16: =SUM(AZ11:AZ15)-AZ11 -> 68360.422 | BA16: =SUM(BA11:BA15)-BA11 -> 68360.422 | BB16: =SUM(BB11:BB15)-BB11 -> 68360.422 | BC16: =SUM(BC11:BC15)-BC11 -> 68360.422 | ... BG16: =SUM(BG11:BG15)-BG11 -> 68360.422 | BH16: =SUM(AV16:BG16) -> 820325.06 | BI16: TOTAL CASH IN | BJ16: =SUM(BJ11:BJ15)-BJ11 -> 61530.682 | BK16: =SUM(BK11:BK15)-BK11 -> 61530.682 | BL16: =SUM(BL11:BL15)-BL11 -> 61530.682 | BM16: =SUM(BM11:BM15)-BM11 -> 61530.682 | BN16: =SUM(BN11:BN15)-BN11 -> 61530.682 | BO16: =SUM(BO11:BO15)-BO11 -> 61530.682 | BP16: =SUM(BP11:BP15)-BP11 -> 61530.682 | BQ16: =SUM(BQ11:BQ15)-BQ11 -> 61530.682 | ... BU16: =SUM(BU11:BU15)-BU11 -> 61530.682 | BV16: =SUM(BJ16:BU16) -> 738368.19 | BW16: TOTAL CASH IN | BX16: =SUM(BX11:BX15)-BX11 -> 739232.39 | BY16: =SUM(BY11:BY15)-BY11 -> 864318.2 | BZ16: =SUM(BZ11:BZ15)-BZ11 -> 865226.16 | CA16: =SUM(CA11:CA15)-CA11 -> 866156.81 | CB16: =SUM(CB11:CB15)-CB11 -> 867110.73 | CC16: =SUM(CC11:CC15)-CC11 -> 868088.5 | CD16: =SUM(CD11:CD15)-CD11 -> 993290.71 | CE16: =SUM(CE11:CE15)-CE11 -> 994317.98 | ... CX16: =SUM(CX11:CX15)-CX11 -> 1474931.9
A17: CASH OUT | Q17: CASH OUT | AG17: CASH OUT | AU17: CASH OUT | BI17: CASH OUT | BW17: CASH OUT
A18: Financial Management | Q18: Financial Management | AG18: Financial Management | AU18: Financial Management | BI18: Financial Management | BW18: Financial Management
A19: Accounting | B19: 402 | C19: 402 | D19: 1602 | E19: 0 | F19: 402 | G19: 402 | H19: 402 | I19: 401 | J19: 535 | K19: 535 | L19: 703 | M19: 704 | N19: =SUM(B19:M19) -> 6490 | O19: 8437 | P19: =N19-O19 -> -1947 | Q19: Accounting + PayHOA Svc | R19: 0 | S19: 142 | T19: 554 | U19: =T19 -> 554 | V19: =U19 -> 554 | W19: =V19 -> 554 | X19: =W19 -> 554 | Y19: =X19 -> 554 | Z19: =Y19 -> 554 | AA19: =Z19 -> 554 | AB19: =AA19 -> 554 | AC19: =AB19 -> 554 | AD19: =SUM(R19:AC19) -> 5682 | AE19: 6824 | AF19: =AD19-AE19 -> -1142 | AG19: Accounting | AH19: =(AD19/12)*(1+(Inflation!$G$6)) -> 485.3375 | AI19: =AH19 -> 485.3375 | AJ19: =AI19 -> 485.3375 | AK19: =AJ19 -> 485.3375 | AL19: =AK19 -> 485.3375 | AM19: =AL19 -> 485.3375 | AN19: =AM19 -> 485.3375 | AO19: =AN19 -> 485.3375 | AP19: =AO19 -> 485.3375 | ... AS19: =AR19 -> 485.3375 | AT19: =SUM(AH19:AS19) -> 5824.05 | AU19: Accounting | AV19: =(AT19/12)*(1+(Inflation!$H$6)) -> 497.47094 | AW19: =AV19 -> 497.47094 | AX19: =AW19 -> 497.47094 | AY19: =AX19 -> 497.47094 | AZ19: =AY19 -> 497.47094 | BA19: =AZ19 -> 497.47094 | BB19: =BA19 -> 497.47094 | BC19: =BB19 -> 497.47094 | BD19: =BC19 -> 497.47094 | ... BG19: =BF19 -> 497.47094 | BH19: =SUM(AV19:BG19) -> 5969.6512 | BI19: Accounting | BJ19: =(BH19/12)*(1+(Inflation!$I$6)) -> 509.90771 | BK19: =BJ19 -> 509.90771 | BL19: =BK19 -> 509.90771 | BM19: =BL19 -> 509.90771 | BN19: =BM19 -> 509.90771 | BO19: =BN19 -> 509.90771 | BP19: =BO19 -> 509.90771 | BQ19: =BP19 -> 509.90771 | BR19: =BQ19 -> 509.90771 | ... BU19: =BT19 -> 509.90771 | BV19: =SUM(BJ19:BU19) -> 6118.8925 | BW19: Accounting | BX19: =BV19*(1+Inflation!$J$5) -> 6271.8648 | BY19: =BX19*(1+Inflation!$J$5) -> 6428.6615 | BZ19: =BY19*(1+Inflation!$J$5) -> 6589.378 | CA19: =BZ19*(1+Inflation!$J$5) -> 6754.1125 | CB19: =CA19*(1+Inflation!$J$5) -> 6922.9653 | CC19: =CB19*(1+Inflation!$J$5) -> 7096.0394 | CD19: =CC19*(1+Inflation!$J$5) -> 7273.4404 | CE19: =CD19*(1+Inflation!$J$5) -> 7455.2764 | CF19: =CE19*(1+Inflation!$J$5) -> 7641.6583 | ... CX19: =CW19*(1+Inflation!$J$5) -> 11918.379
A20: Insurance | B20: 4877 | C20: 4877 | D20: 6940 | E20: 4875 | F20: 6977 | G20: 6977 | H20: 6977 | I20: 7430 | J20: 7939 | K20: 7430 | L20: 7458 | M20: 7458 | N20: =SUM(B20:M20) -> 80215 | O20: 66163 | P20: =N20-O20 -> 14052 | Q20: Insurance | R20: 7458 | S20: =R20 -> 7458 | T20: =S20+2000 -> 9458 | U20: =S20 -> 7458 | V20: =U20 -> 7458 | W20: =V20 -> 7458 | X20: =W20 -> 7458 | Y20: =X20 -> 7458 | Z20: =Y20 -> 7458 | AA20: =Z20 -> 7458 | AB20: =AA20 -> 7458 | AC20: =AB20 -> 7458 | AD20: =SUM(R20:AC20) -> 91496 | AE20: 95097 | AF20: =AD20-AE20 -> -3601 | AG20: Insurance | AH20: =AC20*(1+(Inflation!$F$6)) -> 7644.45 | AI20: =AH20 -> 7644.45 | AJ20: =(T20*(1+(Inflation!$F$6))) -> 9694.45 | AK20: =AI20 -> 7644.45 | AL20: =AK20 -> 7644.45 | AM20: =AL20 -> 7644.45 | AN20: =AM20 -> 7644.45 | AO20: =AN20 -> 7644.45 | AP20: =AO20 -> 7644.45 | AQ20: =AP20 -> 7644.45 | AR20: =AQ20 -> 7644.45 | AS20: =AR20 -> 7644.45 | AT20: =SUM(AH20:AS20) -> 93783.4 | AU20: Insurance | AV20: =AS20*(1+(Inflation!$F$6)) -> 7835.5612 | AW20: =AV20 -> 7835.5612 | AX20: =(AJ20*(1+(Inflation!$G$6))) -> 9936.8113 | AY20: =AW20 -> 7835.5612 | AZ20: =AY20 -> 7835.5612 | BA20: =AZ20 -> 7835.5612 | BB20: =BA20 -> 7835.5612 | BC20: =BB20 -> 7835.5612 | BD20: =BC20 -> 7835.5612 | BE20: =BD20 -> 7835.5612 | BF20: =BE20 -> 7835.5612 | BG20: =BF20 -> 7835.5612 | BH20: =SUM(AV20:BG20) -> 96127.985 | BI20: Insurance | BJ20: =BG20*(1+(Inflation!$F$6)) -> 8031.4503 | BK20: =BJ20 -> 8031.4503 | BL20: =(AX20*(1+(Inflation!$H$6))) -> 10185.232 | BM20: =BK20 -> 8031.4503 | BN20: =BM20 -> 8031.4503 | BO20: =BN20 -> 8031.4503 | BP20: =BO20 -> 8031.4503 | BQ20: =BP20 -> 8031.4503 | BR20: =BQ20 -> 8031.4503 | BS20: =BR20 -> 8031.4503 | BT20: =BS20 -> 8031.4503 | BU20: =BT20 -> 8031.4503 | BV20: =SUM(BJ20:BU20) -> 98531.185 | BW20: Insurance | BX20: =BV20*(1+Inflation!$J$5) -> 100994.46 | BY20: =BX20*(1+Inflation!$J$5) -> 103519.33 | BZ20: =BY20*(1+Inflation!$J$5) -> 106107.31 | CA20: =BZ20*(1+Inflation!$J$5) -> 108759.99 | CB20: =CA20*(1+Inflation!$J$5) -> 111478.99 | CC20: =CB20*(1+Inflation!$J$5) -> 114265.97 | CD20: =CC20*(1+Inflation!$J$5) -> 117122.62 | CE20: =CD20*(1+Inflation!$J$5) -> 120050.68 | CF20: =CE20*(1+Inflation!$J$5) -> 123051.95 | ... CX20: =CW20*(1+Inflation!$J$5) -> 191919.04
A21: Legal/Professional Services | B21: 54 | C21: 0 | D21: 0 | E21: 0 | F21: 12 | G21: 0 | H21: 0 | I21: 0 | J21: 0 | K21: 568 | L21: 833 | M21: 837 | N21: =SUM(B21:M21) -> 2304 | O21: 10000 | P21: =N21-O21 -> -7696 | Q21: Legal/Professional Services | R21: =M21*(1+(Inflation!$F$6)) -> 857.925 | S21: =R21 -> 857.925 | T21: =S21 -> 857.925 | U21: =T21 -> 857.925 | V21: =U21 -> 857.925 | W21: =V21 -> 857.925 | X21: =W21 -> 857.925 | Y21: =X21 -> 857.925 | Z21: =Y21 -> 857.925 | ... AC21: =AB21 -> 857.925 | AD21: =SUM(R21:AC21) -> 10295.1 | AE21: 10295 | AF21: =AD21-AE21 -> 0.1 | AG21: Legal/Professional Services | AH21: =R21*(1+(Inflation!$G$6)) -> 879.37312 | AI21: =S21*(1+(Inflation!$G$6)) -> 879.37312 | AJ21: =T21*(1+(Inflation!$G$6)) -> 879.37312 | AK21: =U21*(1+(Inflation!$G$6)) -> 879.37312 | AL21: =V21*(1+(Inflation!$G$6)) -> 879.37312 | AM21: =W21*(1+(Inflation!$G$6)) -> 879.37312 | AN21: =X21*(1+(Inflation!$G$6)) -> 879.37312 | AO21: =Y21*(1+(Inflation!$G$6)) -> 879.37312 | ... AS21: =AC21*(1+(Inflation!$G$6)) -> 879.37312 | AT21: =SUM(AH21:AS21) -> 10552.478 | AU21: Legal/Professional Services | AV21: =AH21*(1+(Inflation!$H$6)) -> 901.35745 | AW21: =AI21*(1+(Inflation!$G$6)) -> 901.35745 | AX21: =AJ21*(1+(Inflation!$H$6)) -> 901.35745 | AY21: =AK21*(1+(Inflation!$G$6)) -> 901.35745 | AZ21: =AL21*(1+(Inflation!$G$6)) -> 901.35745 | BA21: =AM21*(1+(Inflation!$H$6)) -> 901.35745 | BB21: =AN21*(1+(Inflation!$G$6)) -> 901.35745 | BC21: =AO21*(1+(Inflation!$G$6)) -> 901.35745 | BD21: =AP21*(1+(Inflation!$H$6)) -> 901.35745 | BE21: =AQ21*(1+(Inflation!$G$6)) -> 901.35745 | BF21: =AR21*(1+(Inflation!$G$6)) -> 901.35745 | BG21: =AS21*(1+(Inflation!$G$6)) -> 901.35745 | BH21: =SUM(AV21:BG21) -> 10816.289 | BI21: Legal/Professional Services | BJ21: =AV21*(1+(Inflation!$I$6)) -> 923.89139 | BK21: =AW21*(1+(Inflation!$G$6)) -> 923.89139 | BL21: =AX21*(1+(Inflation!$H$6)) -> 923.89139 | BM21: =AY21*(1+(Inflation!$G$6)) -> 923.89139 | BN21: =AZ21*(1+(Inflation!$G$6)) -> 923.89139 | BO21: =BA21*(1+(Inflation!$H$6)) -> 923.89139 | BP21: =BB21*(1+(Inflation!$G$6)) -> 923.89139 | BQ21: =BC21*(1+(Inflation!$G$6)) -> 923.89139 | BR21: =BD21*(1+(Inflation!$H$6)) -> 923.89139 | BS21: =BE21*(1+(Inflation!$G$6)) -> 923.89139 | BT21: =BF21*(1+(Inflation!$G$6)) -> 923.89139 | BU21: =BG21*(1+(Inflation!$G$6)) -> 923.89139 | BV21: =SUM(BJ21:BU21) -> 11086.697 | BW21: Legal/Professional Services | BX21: =BV21*(1+Inflation!$J$5) -> 11363.864 | BY21: =BX21*(1+Inflation!$J$5) -> 11647.961 | BZ21: =BY21*(1+Inflation!$J$5) -> 11939.16 | CA21: =BZ21*(1+Inflation!$J$5) -> 12237.639 | CB21: =CA21*(1+Inflation!$J$5) -> 12543.58 | CC21: =CB21*(1+Inflation!$J$5) -> 12857.169 | CD21: =CC21*(1+Inflation!$J$5) -> 13178.598 | CE21: =CD21*(1+Inflation!$J$5) -> 13508.063 | CF21: =CE21*(1+Inflation!$J$5) -> 13845.765 | ... CX21: =CW21*(1+Inflation!$J$5) -> 21594.668
A22: Subtotal | B22: =SUM(B19:B21) -> 5333 | C22: =SUM(C19:C21) -> 5279 | D22: =SUM(D19:D21) -> 8542 | E22: =SUM(E19:E21) -> 4875 | F22: =SUM(F19:F21) -> 7391 | G22: =SUM(G19:G21) -> 7379 | H22: =SUM(H19:H21) -> 7379 | I22: =SUM(I19:I21) -> 7831 | ... M22: =SUM(M19:M21) -> 8999 | N22: =SUM(B22:M22) -> 89009 | O22: =SUM(O19:O21) -> 84600 | P22: =N22-O22 -> 4409 | Q22: Subtotal | R22: =SUM(R19:R21) -> 8315.925 | S22: =SUM(S19:S21) -> 8457.925 | T22: =SUM(T19:T21) -> 10869.925 | U22: =SUM(U19:U21) -> 8869.925 | V22: =SUM(V19:V21) -> 8869.925 | W22: =SUM(W19:W21) -> 8869.925 | X22: =SUM(X19:X21) -> 8869.925 | Y22: =SUM(Y19:Y21) -> 8869.925 | ... AC22: =SUM(AC19:AC21) -> 8869.925 | AD22: =SUM(R22:AC22) -> 107473.1 | AE22: =SUM(AE19:AE21) -> 112216 | AF22: =AD22-AE22 -> -4742.9 | AG22: Subtotal | AH22: =SUM(AH19:AH21) -> 9009.1606 | AI22: =SUM(AI19:AI21) -> 9009.1606 | AJ22: =SUM(AJ19:AJ21) -> 11059.161 | AK22: =SUM(AK19:AK21) -> 9009.1606 | AL22: =SUM(AL19:AL21) -> 9009.1606 | AM22: =SUM(AM19:AM21) -> 9009.1606 | AN22: =SUM(AN19:AN21) -> 9009.1606 | AO22: =SUM(AO19:AO21) -> 9009.1606 | ... AS22: =SUM(AS19:AS21) -> 9009.1606 | AT22: =SUM(AH22:AS22) -> 110159.93 | AU22: Subtotal | AV22: =SUM(AV19:AV21) -> 9234.3896 | AW22: =SUM(AW19:AW21) -> 9234.3896 | AX22: =SUM(AX19:AX21) -> 11335.64 | AY22: =SUM(AY19:AY21) -> 9234.3896 | AZ22: =SUM(AZ19:AZ21) -> 9234.3896 | BA22: =SUM(BA19:BA21) -> 9234.3896 | BB22: =SUM(BB19:BB21) -> 9234.3896 | BC22: =SUM(BC19:BC21) -> 9234.3896 | ... BG22: =SUM(BG19:BG21) -> 9234.3896 | BH22: =SUM(AV22:BG22) -> 112913.93 | BI22: Subtotal | BJ22: =SUM(BJ19:BJ21) -> 9465.2494 | BK22: =SUM(BK19:BK21) -> 9465.2494 | BL22: =SUM(BL19:BL21) -> 11619.031 | BM22: =SUM(BM19:BM21) -> 9465.2494 | BN22: =SUM(BN19:BN21) -> 9465.2494 | BO22: =SUM(BO19:BO21) -> 9465.2494 | BP22: =SUM(BP19:BP21) -> 9465.2494 | BQ22: =SUM(BQ19:BQ21) -> 9465.2494 | ... BU22: =SUM(BU19:BU21) -> 9465.2494 | BV22: =SUM(BJ22:BU22) -> 115736.77 | BW22: Subtotal | BX22: =SUM(BX19:BX21) -> 118630.19 | BY22: =SUM(BY19:BY21) -> 121595.95 | BZ22: =SUM(BZ19:BZ21) -> 124635.85 | CA22: =SUM(CA19:CA21) -> 127751.74 | CB22: =SUM(CB19:CB21) -> 130945.54 | CC22: =SUM(CC19:CC21) -> 134219.17 | CD22: =SUM(CD19:CD21) -> 137574.65 | CE22: =SUM(CE19:CE21) -> 141014.02 | ... CX22: =SUM(CX19:CX21) -> 225432.09
A23: Maintenance and Repairs | Q23: Maintenance and Repairs | AG23: Maintenance and Repairs | AU23: Maintenance and Repairs | BI23: Maintenance and Repairs | BW23: Maintenance and Repairs | BX23: =BV23
A24: Equipment Repairs (and purchases) | B24: 0 | C24: 0 | D24: 0 | E24: 636 | F24: 0 | G24: 32 | H24: 190 | I24: 528 | J24: 105 | K24: 863 | L24: 105 | M24: 110 | N24: =SUM(B24:M24) -> 2569 | O24: 1265 | P24: =N24-O24 -> 1304 | Q24: Equipment Repairs (and purchases) | R24: =(AE24/12) -> 164.08333 | S24: =R24 -> 164.08333 | T24: =S24 -> 164.08333 | U24: =T24 -> 164.08333 | V24: =U24 -> 164.08333 | W24: =V24 -> 164.08333 | X24: =W24 -> 164.08333 | Y24: =X24 -> 164.08333 | Z24: =Y24 -> 164.08333 | ... AC24: =AB24 -> 164.08333 | AD24: =SUM(R24:AC24) -> 1969 | AE24: 1969 | AF24: =AD24-AE24 -> 0 | AG24: Equipment Repairs | AH24: =R24*(1+(Inflation!$G$6)) -> 168.18542 | AI24: =S24*(1+(Inflation!$G$6)) -> 168.18542 | AJ24: =T24*(1+(Inflation!$G$6)) -> 168.18542 | AK24: =U24*(1+(Inflation!$G$6)) -> 168.18542 | AL24: =V24*(1+(Inflation!$G$6)) -> 168.18542 | AM24: =W24*(1+(Inflation!$G$6)) -> 168.18542 | AN24: =X24*(1+(Inflation!$G$6)) -> 168.18542 | AO24: =Y24*(1+(Inflation!$G$6)) -> 168.18542 | ... AS24: =AC24*(1+(Inflation!$G$6)) -> 168.18542 | AT24: =SUM(AH24:AS24) -> 2018.225 | AU24: Equipment Repairs | AV24: =AH24*(1+(Inflation!$H$6)) -> 172.39005 | AW24: =AI24*(1+(Inflation!$H$6)) -> 172.39005 | AX24: =AJ24*(1+(Inflation!$H$6)) -> 172.39005 | AY24: =AK24*(1+(Inflation!$H$6)) -> 172.39005 | AZ24: =AL24*(1+(Inflation!$H$6)) -> 172.39005 | BA24: =AM24*(1+(Inflation!$H$6)) -> 172.39005 | BB24: =AN24*(1+(Inflation!$H$6)) -> 172.39005 | BC24: =AO24*(1+(Inflation!$H$6)) -> 172.39005 | ... BG24: =AS24*(1+(Inflation!$H$6)) -> 172.39005 | BH24: =SUM(AV24:BG24) -> 2068.6806 | BI24: Equipment Repairs | BJ24: =AV24*(1+(Inflation!$I$6)) -> 176.6998 | BK24: =AW24*(1+(Inflation!$H$6)) -> 176.6998 | BL24: =AX24*(1+(Inflation!$H$6)) -> 176.6998 | BM24: =AY24*(1+(Inflation!$H$6)) -> 176.6998 | BN24: =AZ24*(1+(Inflation!$H$6)) -> 176.6998 | BO24: =BA24*(1+(Inflation!$H$6)) -> 176.6998 | BP24: =BB24*(1+(Inflation!$H$6)) -> 176.6998 | BQ24: =BC24*(1+(Inflation!$H$6)) -> 176.6998 | BR24: =BD24*(1+(Inflation!$H$6)) -> 176.6998 | ... BU24: =BG24*(1+(Inflation!$H$6)) -> 176.6998 | BV24: =SUM(BJ24:BU24) -> 2120.3976 | BW24: Equipment Repairs | BX24: =BV24*(1+Inflation!$J$4) -> 2188.2504 | BY24: =BX24*(1+Inflation!$J$4) -> 2258.2744 | BZ24: =BY24*(1+Inflation!$J$4) -> 2330.5392 | CA24: =BZ24*(1+Inflation!$J$4) -> 2405.1164 | CB24: =CA24*(1+Inflation!$J$4) -> 2482.0801 | CC24: =CB24*(1+Inflation!$J$4) -> 2561.5067 | CD24: =CC24*(1+Inflation!$J$4) -> 2643.4749 | CE24: =CD24*(1+Inflation!$J$4) -> 2728.0661 | CF24: =CE24*(1+Inflation!$J$4) -> 2815.3642 | ... CX24: =CW24*(1+Inflation!$J$4) -> 4963.2841
A25: Grounds Maintenance (Jaquez Contract) | B25: 0 | C25: 3756 | D25: 11268 | E25: 3756 | F25: 0 | G25: 7541 | H25: 12187 | I25: 5634 | J25: 1199 | K25: 19060 | L25: 3748 | M25: 3748 | N25: =SUM(B25:M25) -> 71897 | O25: 65000 | P25: =N25-O25 -> 6897 | Q25: Grounds Maintenance | R25: =(AE25/12) -> 5156.1667 | S25: =R25 -> 5156.1667 | T25: =S25 -> 5156.1667 | U25: =T25 -> 5156.1667 | V25: =U25 -> 5156.1667 | W25: =V25 -> 5156.1667 | X25: =W25 -> 5156.1667 | Y25: =X25 -> 5156.1667 | Z25: =Y25 -> 5156.1667 | ... AC25: =AB25 -> 5156.1667 | AD25: =SUM(R25:AC25) -> 61874 | AE25: 61874 | AF25: =AD25-AE25 -> 0 | AG25: Grounds Maintenance | AH25: =(AD25/12)*(1+(Inflation!$F$5)) -> 5285.0708 | AI25: =AH25 -> 5285.0708 | AJ25: =AI25 -> 5285.0708 | AK25: =AJ25 -> 5285.0708 | AL25: =AK25 -> 5285.0708 | AM25: =AL25 -> 5285.0708 | AN25: =AM25 -> 5285.0708 | AO25: =AN25 -> 5285.0708 | AP25: =AO25 -> 5285.0708 | ... AS25: =AR25 -> 5285.0708 | AT25: =SUM(AH25:AS25) -> 63420.85 | AU25: Grounds Maintenance | AV25: =(AT25/12)*(1+(Inflation!$F$5)) -> 5417.1976 | AW25: =AV25 -> 5417.1976 | AX25: =AW25 -> 5417.1976 | AY25: =AX25 -> 5417.1976 | AZ25: =AY25 -> 5417.1976 | BA25: =AZ25 -> 5417.1976 | BB25: =BA25 -> 5417.1976 | BC25: =BB25 -> 5417.1976 | BD25: =BC25 -> 5417.1976 | ... BG25: =BF25 -> 5417.1976 | BH25: =SUM(AV25:BG25) -> 65006.371 | BI25: Grounds Maintenance | BJ25: =(BH25/12)*(1+(Inflation!$F$5)) -> 5552.6275 | BK25: =BJ25 -> 5552.6275 | BL25: =BK25 -> 5552.6275 | BM25: =BL25 -> 5552.6275 | BN25: =BM25 -> 5552.6275 | BO25: =BN25 -> 5552.6275 | BP25: =BO25 -> 5552.6275 | BQ25: =BP25 -> 5552.6275 | BR25: =BQ25 -> 5552.6275 | ... BU25: =BT25 -> 5552.6275 | BV25: =SUM(BJ25:BU25) -> 66631.531 | BW25: Grounds Maintenance | BX25: =BV25*(1+Inflation!$J$5) -> 68297.319 | BY25: =BX25*(1+Inflation!$J$5) -> 70004.752 | BZ25: =BY25*(1+Inflation!$J$5) -> 71754.871 | CA25: =BZ25*(1+Inflation!$J$5) -> 73548.742 | CB25: =CA25*(1+Inflation!$J$5) -> 75387.461 | CC25: =CB25*(1+Inflation!$J$5) -> 77272.147 | CD25: =CC25*(1+Inflation!$J$5) -> 79203.951 | CE25: =CD25*(1+Inflation!$J$5) -> 81184.05 | CF25: =CE25*(1+Inflation!$J$5) -> 83213.651 | ... CX25: =CW25*(1+Inflation!$J$5) -> 129784.9
A26: Facility Maintenance (Misc Repairs) | B26: 19878 | C26: 256 | D26: 7540 | E26: 366 | F26: 365 | G26: 139 | H26: 12669 | I26: 2939 | J26: 13845 | K26: 14929 | L26: 0 | M26: =(sum($C26:$H26)/6) -> 3555.8333 | N26: =SUM(B26:M26) -> 76481.833 | O26: 60820 | P26: =N26-O26 -> 15661.833 | Q26: Facility Maintenance (Misc Repairs) | R26: 5991 | S26: =R26 -> 5991 | T26: =S26 -> 5991 | U26: =T26 -> 5991 | V26: =U26 -> 5991 | W26: =V26 -> 5991 | X26: =W26 -> 5991 | Y26: =X26 -> 5991 | Z26: =Y26 -> 5991 | ... AC26: =AB26 -> 5991 | AD26: =SUM(R26:AC26) -> 71892 | AE26: 71892 | AF26: =AD26-AE26 -> 0 | AG26: Facility Maintenance (Misc Repairs) | AH26: =(AC26)*(1+(Inflation!$F$2)) -> 6212.667 | AI26: =AH26 -> 6212.667 | AJ26: =AI26 -> 6212.667 | AK26: =AJ26 -> 6212.667 | AL26: =AK26 -> 6212.667 | AM26: =AL26 -> 6212.667 | AN26: =AM26 -> 6212.667 | AO26: =AN26 -> 6212.667 | AP26: =AO26 -> 6212.667 | ... AS26: =AR26 -> 6212.667 | AT26: =SUM(AH26:AS26) -> 74552.004 | AU26: Facility Maintenance (Misc Repairs) | AV26: =(AS26)*(1+(Inflation!$F$2)) -> 6442.5357 | AW26: =AV26 -> 6442.5357 | AX26: =AW26 -> 6442.5357 | AY26: =AX26 -> 6442.5357 | AZ26: =AY26 -> 6442.5357 | BA26: =AZ26 -> 6442.5357 | BB26: =BA26 -> 6442.5357 | BC26: =BB26 -> 6442.5357 | BD26: =BC26 -> 6442.5357 | ... BG26: =BF26 -> 6442.5357 | BH26: =SUM(AV26:BG26) -> 77310.428 | BI26: Facility Maintenance (Misc Repairs) | BJ26: =(BG26)*(1+(Inflation!$F$2)) -> 6680.9095 | BK26: =BJ26 -> 6680.9095 | BL26: =BK26 -> 6680.9095 | BM26: =BL26 -> 6680.9095 | BN26: =BM26 -> 6680.9095 | BO26: =BN26 -> 6680.9095 | BP26: =BO26 -> 6680.9095 | BQ26: =BP26 -> 6680.9095 | BR26: =BQ26 -> 6680.9095 | ... BU26: =BT26 -> 6680.9095 | BV26: =SUM(BJ26:BU26) -> 80170.914 | BW26: Facility Maintenance (Misc Repairs) | BX26: =BV26*(1+(Inflation!$F$2)) -> 83137.238 | BY26: =BX26*(1+(Inflation!$F$2)) -> 86213.316 | BZ26: =BY26*(1+Inflation!$J$4) -> 88972.142 | CA26: =BZ26*(1+Inflation!$J$4) -> 91819.25 | CB26: =CA26*(1+Inflation!$J$4) -> 94757.466 | CC26: =CB26*(1+Inflation!$J$4) -> 97789.705 | CD26: =CC26*(1+Inflation!$J$4) -> 100918.98 | CE26: =CD26*(1+Inflation!$J$4) -> 104148.38 | CF26: =CE26*(1+Inflation!$J$4) -> 107481.13 | CG26: =CF26*(1+Inflation!$J$4) -> 110920.53 | ... CX26: =CW26*(1+Inflation!$J$4) -> 189481.49
A27: Facilities Maintenance (Detail in Line 51): | B27: =B82 -> 27685 | C27: =C82 -> 0 | D27: =D82 -> 25659.5 | E27: =E82 -> 0 | F27: =F82 -> 0 | G27: =G82 -> 10000 | H27: =H82 -> 170108 | I27: =I82 -> 90246 | ... M27: =M82 -> 134702.27 | N27: =SUM(B27:M27) -> 636583.77 | O27: 807000 | P27: =N27-O27 -> -170416.23 | Q27: Facilities Maintenance (Detail in Line 52): | R27: =R82 -> 0 | S27: =S82 -> 0 | T27: =T82 -> 0 | U27: =U82 -> 0 | V27: =V82 -> 10000 | W27: =W82 -> 191226 | X27: =X82 -> 114983.64 | Y27: =Y82 -> 72575.56 | ... AC27: =AC82 -> 0 | AD27: =SUM(R27:AC27) -> 648525 | AE27: 566158 | AF27: =AD27-AE27 -> 82367 | AG27: Facilities Maintenance (Detail in Line 52): | AH27: =AH82 -> 0 | AI27: =AI82 -> 0 | AJ27: =AJ82 -> 0 | AK27: =AK82 -> 27855.397 | AL27: =AL82 -> 32870.206 | AM27: =AM82 -> 156810.6 | AN27: =AN82 -> 48000 | AO27: =AO82 -> 6000 | ... AS27: =AS82 -> 0 | AT27: =SUM(AH27:AS27) -> 276536.2 | AU27: Facilities Maintenance (Detail in Line 52): | AV27: =AV82 -> 0 | AW27: =AW82 -> 0 | AX27: =AX82 -> 0 | AY27: =AY82 -> 16019.026 | AZ27: =AZ82 -> 152076.66 | BA27: =BA82 -> 0 | BB27: =BB82 -> 0 | BC27: =BC82 -> 628.09583 | ... BG27: =BG82 -> 0 | BH27: =SUM(AV27:BG27) -> 179370.75 | BI27: Facilities Maintenance (Detail in Line 52): | BJ27: =BJ82 -> 0 | BK27: =BK82 -> 0 | BL27: =BL82 -> 0 | BM27: =BM82 -> 16531.635 | BN27: =BN82 -> 0 | BO27: =BO82 -> 0 | BP27: =BP82 -> 0 | BQ27: =BQ82 -> 650.62547 | ... BU27: =BU82 -> 0 | BV27: =SUM(BJ27:BU27) -> 22538.385 | BW27: Facilities Maintenance (Detail in Line 52): | BX27: =BX82 -> 23606.178 | BY27: =BY82 -> 24386.905 | BZ27: =BZ82 -> 147954.68 | CA27: =CA82 -> 26026.896 | CB27: =CB82 -> 26887.911 | CC27: =CC82 -> 581253.15 | CD27: =CD82 -> 565255.06 | CE27: =CE82 -> 474289.91 | ... CX27: =CX82 -> 55059.731
A28: Pool Maintenance | F28: 1900 | G28: 1581 | H28: 1746 | I28: 2500 | J28: 886 | L28: 711 | N28: =SUM(B28:M28) -> 9324 | O28: 10000 | P28: =N28-O28 -> -676 | Q28: Pool Maintenance | V28: =(AE28/4) -> 2212.5 | W28: =V28 -> 2212.5 | X28: =W28 -> 2212.5 | Y28: =X28 -> 2212.5 | AD28: =SUM(R28:AC28) -> 8850 | AE28: 8850 | AF28: =AD28-AE28 -> 0 | AG28: Pool Maintenance | AL28: =(AD28/4)*(1+Inflation!$D$4) -> 2273.3438 | AM28: =AL28 -> 2273.3438 | AN28: =AM28 -> 2273.3438 | AO28: =AN28 -> 2273.3438 | AT28: =SUM(AH28:AS28) -> 9093.375 | AU28: Pool Maintenance | AZ28: =(AT28/4)*(1+Inflation!$D$4) -> 2335.8607 | BA28: =AZ28 -> 2335.8607 | BB28: =BA28 -> 2335.8607 | BC28: =BB28 -> 2335.8607 | BH28: =SUM(AV28:BG28) -> 9343.4428 | BI28: Pool Maintenance | BN28: =(BH28/4)*(1+Inflation!$D$4) -> 2400.0969 | BO28: =BN28 -> 2400.0969 | BP28: =BO28 -> 2400.0969 | BQ28: =BP28 -> 2400.0969 | BV28: =SUM(BJ28:BU28) -> 9600.3875 | BW28: Pool Maintenance | BX28: =BV28*(1+Inflation!$J$4) -> 9907.5999 | BY28: =BX28*(1+Inflation!$J$4) -> 10224.643 | BZ28: =BY28*(1+Inflation!$J$4) -> 10551.832 | CA28: =BZ28*(1+Inflation!$J$4) -> 10889.49 | CB28: =CA28*(1+Inflation!$J$4) -> 11237.954 | CC28: =CB28*(1+Inflation!$J$4) -> 11597.568 | CD28: =CC28*(1+Inflation!$J$4) -> 11968.691 | CE28: =CD28*(1+Inflation!$J$4) -> 12351.689 | CF28: =CE28*(1+Inflation!$J$4) -> 12746.943 | ... CX28: =CW28*(1+Inflation!$J$4) -> 22471.941
A29: Rental Unit Maintenance | B29: 5798 | C29: 1438 | D29: 288 | E29: 0 | F29: 125 | G29: 0 | H29: 71 | I29: 125 | J29: 0 | K29: 125 | L29: 0 | M29: 125 | N29: =SUM(B29:M29) -> 8095 | O29: 1500 | P29: =N29-O29 -> 6595 | Q29: Rental Unit Maintenance | R29: =AE29/12 -> 128.16667 | S29: =R29 -> 128.16667 | T29: =S29 -> 128.16667 | U29: =T29 -> 128.16667 | V29: =U29 -> 128.16667 | W29: =V29 -> 128.16667 | X29: =W29 -> 128.16667 | Y29: =X29 -> 128.16667 | Z29: =Y29 -> 128.16667 | ... AC29: =AB29 -> 128.16667 | AD29: =SUM(R29:AC29) -> 1538 | AE29: 1538 | AF29: =AD29-AE29 -> 0 | AG29: Rental Unit Maintenance | AH29: =AC29*(1+(Inflation!$F$6)) -> 131.37083 | AI29: =AH29 -> 131.37083 | AJ29: =AI29 -> 131.37083 | AK29: =AJ29 -> 131.37083 | AL29: =AK29 -> 131.37083 | AM29: =AL29 -> 131.37083 | AN29: =AM29 -> 131.37083 | AO29: =AN29 -> 131.37083 | AP29: =AO29 -> 131.37083 | ... AS29: =AR29 -> 131.37083 | AT29: =SUM(AH29:AS29) -> 1576.45 | AU29: Rental Unit Maintenance | AV29: =AS29*(1+(Inflation!$F$6)) -> 134.6551 | AW29: =AV29 -> 134.6551 | AX29: =AW29 -> 134.6551 | AY29: =AX29 -> 134.6551 | AZ29: =AY29 -> 134.6551 | BA29: =AZ29 -> 134.6551 | BB29: =BA29 -> 134.6551 | BC29: =BB29 -> 134.6551 | BD29: =BC29 -> 134.6551 | ... BG29: =BF29 -> 134.6551 | BH29: =SUM(AV29:BG29) -> 1615.8612 | BI29: Rental Unit Maintenance | BJ29: =BG29*(1+(Inflation!$F$6)) -> 138.02148 | BK29: =BJ29 -> 138.02148 | BL29: =BK29 -> 138.02148 | BM29: =BL29 -> 138.02148 | BN29: =BM29 -> 138.02148 | BO29: =BN29 -> 138.02148 | BP29: =BO29 -> 138.02148 | BQ29: =BP29 -> 138.02148 | BR29: =BQ29 -> 138.02148 | ... BU29: =BT29 -> 138.02148 | BV29: =SUM(BJ29:BU29) -> 1656.2578 | BW29: Rental Unit Maintenance | BX29: =BV29*(1+Inflation!$J$4) -> 1709.258 | BY29: =BX29*(1+Inflation!$J$4) -> 1763.9543 | BZ29: =BY29*(1+Inflation!$J$4) -> 1820.4008 | CA29: =BZ29*(1+Inflation!$J$4) -> 1878.6537 | CB29: =CA29*(1+Inflation!$J$4) -> 1938.7706 | CC29: =CB29*(1+Inflation!$J$4) -> 2000.8112 | CD29: =CC29*(1+Inflation!$J$4) -> 2064.8372 | CE29: =CD29*(1+Inflation!$J$4) -> 2130.912 | CF29: =CE29*(1+Inflation!$J$4) -> 2199.1012 | ... CX29: =CW29*(1+Inflation!$J$4) -> 3876.8568
A30: Snow Removal & Purchase Snow-Melt | B30: 0 | C30: 0 | D30: 2802 | E30: 10276 | M30: 4595 | N30: =SUM(B30:M30) -> 17673 | O30: 18380 | P30: =N30-O30 -> -707 | Q30: Snow Removal & Purchase Snow-Melt | R30: =(AE30/4) -> 4809.75 | S30: =R30 -> 4809.75 | T30: =S30 -> 4809.75 | AC30: =T30 -> 4809.75 | AD30: =SUM(R30:AC30) -> 19239 | AE30: 19239 | AF30: =AD30-AE30 -> 0 | AG30: Snow Removal & Purchase Snow-Melt | AH30: =(AD30/4)*(1+Inflation!$G$4)+1000 -> 5963.662 | AI30: =(AD30/4)*(1+Inflation!$G$4) -> 4963.662 | AJ30: =AI30 -> 4963.662 | AS30: =AJ30 -> 4963.662 | AT30: =SUM(AH30:AS30) -> 20854.648 | AU30: Snow Removal & Purchase Snow-Melt | AV30: =(AT30/4)*(1+Inflation!$H$4)+1000 -> 6380.4992 | AW30: =(AT30/4)*(1+Inflation!$H$4) -> 5380.4992 | AX30: =AW30 -> 5380.4992 | BG30: =AX30 -> 5380.4992 | BH30: =SUM(AV30:BG30) -> 22521.997 | BI30: Snow Removal & Purchase Snow-Melt | BJ30: =(BH30/4)*(1+Inflation!$I$4)+1000 -> 6810.6752 | BK30: =(BH30/4)*(1+Inflation!$H$4) -> 5810.6752 | BL30: =BK30 -> 5810.6752 | BU30: =BL30 -> 5810.6752 | BV30: =SUM(BJ30:BU30) -> 24242.701 | BW30: Snow Removal & Purchase Snow-Melt | BX30: =BV30*(1+Inflation!$J$4) -> 25018.467 | BY30: =BX30*(1+Inflation!$J$4) -> 25819.058 | BZ30: =BY30*(1+Inflation!$J$4) -> 26645.268 | CA30: =BZ30*(1+Inflation!$J$4) -> 27497.916 | CB30: =CA30*(1+Inflation!$J$4) -> 28377.85 | CC30: =CB30*(1+Inflation!$J$4) -> 29285.941 | CD30: =CC30*(1+Inflation!$J$4) -> 30223.091 | CE30: =CD30*(1+Inflation!$J$4) -> 31190.23 | CF30: =CE30*(1+Inflation!$J$4) -> 32188.317 | ... CX30: =CW30*(1+Inflation!$J$4) -> 56745.683
A31: Subtotal | B31: =SUM(B24:B30) -> 53361 | C31: =SUM(C24:C30) -> 5450 | D31: =SUM(D24:D30) -> 47557.5 | E31: =SUM(E24:E30) -> 15034 | F31: =SUM(F24:F30) -> 2390 | G31: =SUM(G24:G30) -> 19293 | H31: =SUM(H24:H30) -> 196971 | I31: =SUM(I24:I30) -> 101972 | ... M31: =SUM(M24:M30) -> 146836.1 | N31: =SUM(B31:M31) -> 822623.6 | O31: =SUM(O24:O30) -> 963965 | P31: =N31-O31 -> -141341.4 | Q31: Subtotal | R31: =SUM(R24:R30) -> 16249.167 | S31: =SUM(S24:S30) -> 16249.167 | T31: =SUM(T24:T30) -> 16249.167 | U31: =SUM(U24:U30) -> 11439.417 | V31: =SUM(V24:V30) -> 23651.917 | W31: =SUM(W24:W30) -> 204877.92 | X31: =SUM(X24:X30) -> 128635.56 | Y31: =SUM(Y24:Y30) -> 86227.477 | ... AC31: =SUM(AC24:AC30) -> 16249.167 | AD31: =SUM(R31:AC31) -> 813887 | AE31: =SUM(AE24:AE30) -> 731520 | AF31: =AD31-AE31 -> 82367 | AG31: Subtotal | AH31: =SUM(AH24:AH30) -> 17760.956 | AI31: =SUM(AI24:AI30) -> 16760.956 | AJ31: =SUM(AJ24:AJ30) -> 16760.956 | AK31: =SUM(AK24:AK30) -> 39652.691 | AL31: =SUM(AL24:AL30) -> 46940.844 | AM31: =SUM(AM24:AM30) -> 170881.24 | AN31: =SUM(AN24:AN30) -> 62070.638 | AO31: =SUM(AO24:AO30) -> 20070.638 | ... AS31: =SUM(AS24:AS30) -> 16760.956 | AT31: =SUM(AH31:AS31) -> 448051.75 | AU31: Subtotal | AV31: =SUM(AV24:AV30) -> 18547.278 | AW31: =SUM(AW24:AW30) -> 17547.278 | AX31: =SUM(AX24:AX30) -> 17547.278 | AY31: =SUM(AY24:AY30) -> 28185.804 | AZ31: =SUM(AZ24:AZ30) -> 166579.3 | BA31: =SUM(BA24:BA30) -> 14502.639 | BB31: =SUM(BB24:BB30) -> 14502.639 | BC31: =SUM(BC24:BC30) -> 15130.735 | ... BG31: =SUM(BG24:BG30) -> 17547.278 | BH31: =SUM(AV31:BG31) -> 357237.53 | BI31: Subtotal | BJ31: =SUM(BJ24:BJ30) -> 19358.933 | BK31: =SUM(BK24:BK30) -> 18358.933 | BL31: =SUM(BL24:BL30) -> 18358.933 | BM31: =SUM(BM24:BM30) -> 29079.893 | BN31: =SUM(BN24:BN30) -> 14948.355 | BO31: =SUM(BO24:BO30) -> 14948.355 | BP31: =SUM(BP24:BP30) -> 14948.355 | BQ31: =SUM(BQ24:BQ30) -> 15598.981 | ... BU31: =SUM(BU24:BU30) -> 18358.933 | BV31: =SUM(BJ31:BU31) -> 206960.57 | BW31: Subtotal | BX31: =SUM(BX24:BX30) -> 213864.31 | BY31: =SUM(BY24:BY30) -> 220670.9 | BZ31: =SUM(BZ24:BZ30) -> 350029.74 | CA31: =SUM(CA24:CA30) -> 234066.07 | CB31: =SUM(CB24:CB30) -> 241069.49 | CC31: =SUM(CC24:CC30) -> 801760.83 | CD31: =SUM(CD24:CD30) -> 792278.08 | CE31: =SUM(CE24:CE30) -> 708023.24 | ... CX31: =SUM(CX24:CX30) -> 462383.88
A32: Office Salary Expenses | Q32: Office Salary Expenses | AG32: Office Salary Expenses | AU32: Office Salary Expenses | BI32: Office Salary Expenses | BW32: Office Salary Expenses
A33: Business Office Salary | B33: 2131 | C33: 1227 | D33: 4727 | E33: 996 | F33: 1942 | G33: 2508 | H33: 8824 | I33: 3121 | J33: 3121 | K33: 3121 | L33: 3193 | M33: 3193 | N33: =SUM(B33:M33) -> 38104 | O33: 37447 | P33: =N33-O33 -> 657 | Q33: Business Office Salary | R33: =AE33/12 -> 4116.6667 | S33: =R33 -> 4116.6667 | T33: =S33 -> 4116.6667 | U33: =T33 -> 4116.6667 | V33: =U33 -> 4116.6667 | W33: =V33 -> 4116.6667 | X33: =W33 -> 4116.6667 | Y33: =X33 -> 4116.6667 | Z33: =Y33 -> 4116.6667 | ... AC33: =AB33 -> 4116.6667 | AD33: =SUM(R33:AC33) -> 49400 | AE33: 49400 | AF33: =AD33-AE33 -> 0 | AG33: Business Office Salary | AH33: =AC33*(1+(Inflation!$G$6)) -> 4219.5833 | AI33: =AH33 -> 4219.5833 | AJ33: =AI33 -> 4219.5833 | AK33: =AJ33 -> 4219.5833 | AL33: =AK33 -> 4219.5833 | AM33: =AL33 -> 4219.5833 | AN33: =AM33 -> 4219.5833 | AO33: =AN33 -> 4219.5833 | AP33: =AO33 -> 4219.5833 | ... AS33: =AR33 -> 4219.5833 | AT33: =SUM(AH33:AS33) -> 50635 | AU33: Business Office Salary | AV33: =AS33*(1+(Inflation!$H$6)) -> 4325.0729 | AW33: =AV33 -> 4325.0729 | AX33: =AW33 -> 4325.0729 | AY33: =AX33 -> 4325.0729 | AZ33: =AY33 -> 4325.0729 | BA33: =AZ33 -> 4325.0729 | BB33: =BA33 -> 4325.0729 | BC33: =BB33 -> 4325.0729 | BD33: =BC33 -> 4325.0729 | ... BG33: =BF33 -> 4325.0729 | BH33: =SUM(AV33:BG33) -> 51900.875 | BI33: Business Office Salary | BJ33: =BG33*(1+(Inflation!$I$6)) -> 4433.1997 | BK33: =BJ33 -> 4433.1997 | BL33: =BK33 -> 4433.1997 | BM33: =BL33 -> 4433.1997 | BN33: =BM33 -> 4433.1997 | BO33: =BN33 -> 4433.1997 | BP33: =BO33 -> 4433.1997 | BQ33: =BP33 -> 4433.1997 | BR33: =BQ33 -> 4433.1997 | ... BU33: =BT33 -> 4433.1997 | BV33: =SUM(BJ33:BU33) -> 53198.397 | BW33: Business Office Salary | BX33: =BV33*(1+Inflation!$J$5) -> 54528.357 | BY33: =BX33*(1+Inflation!$J$4) -> 56273.264 | BZ33: =BY33*(1+Inflation!$J$4) -> 58074.009 | CA33: =BZ33*(1+Inflation!$J$4) -> 59932.377 | CB33: =CA33*(1+Inflation!$J$4) -> 61850.213 | CC33: =CB33*(1+Inflation!$J$4) -> 63829.42 | CD33: =CC33*(1+Inflation!$J$4) -> 65871.961 | CE33: =CD33*(1+Inflation!$J$4) -> 67979.864 | CF33: =CE33*(1+Inflation!$J$4) -> 70155.22 | ... CX33: =CW33*(1+Inflation!$J$4) -> 123678.59
A34: Unallocated expenses (includes DDA) | B34: 0 | C34: 0 | D34: 0 | E34: 0 | F34: 0 | G34: 0 | H34: 1037 | I34: 0 | J34: 0 | K34: 0 | L34: 0 | M34: 0 | N34: =SUM(B34:M34) -> 1037 | P34: =N34-O34 -> 1037 | Q34: Unallocated expenses (includes DDA) | R34: =M34*(1+(Inflation!$F$6)) -> 0 | S34: =R34 -> 0 | T34: =S34 -> 0 | U34: =T34 -> 0 | V34: =U34 -> 0 | W34: =V34 -> 0 | X34: =W34 -> 0 | Y34: =X34 -> 0 | Z34: =Y34 -> 0 | ... AC34: =AB34 -> 0 | AD34: =SUM(R34:AC34) -> 0 | AE34: 0 | AF34: =AD34-AE34 -> 0 | AG34: Unallocated expenses (includes DDA) | AH34: =AC34*(1+(Inflation!$G$6)) -> 0 | AI34: =AH34 -> 0 | AJ34: =AI34 -> 0 | AK34: =AJ34 -> 0 | AL34: =AK34 -> 0 | AM34: =AL34 -> 0 | AN34: =AM34 -> 0 | AO34: =AN34 -> 0 | AP34: =AO34 -> 0 | ... AS34: =AR34 -> 0 | AT34: =SUM(AH34:AS34) -> 0 | AU34: Unallocated expenses (includes DDA) | AV34: =AS34*(1+(Inflation!$H$6)) -> 0 | AW34: =AV34 -> 0 | AX34: =AW34 -> 0 | AY34: =AX34 -> 0 | AZ34: =AY34 -> 0 | BA34: =AZ34 -> 0 | BB34: =BA34 -> 0 | BC34: =BB34 -> 0 | BD34: =BC34 -> 0 | ... BG34: =BF34 -> 0 | BH34: =SUM(AV34:BG34) -> 0 | BI34: Unallocated expenses (includes DDA) | BJ34: =BG34*(1+(Inflation!$I$6)) -> 0 | BK34: =BJ34 -> 0 | BL34: =BK34 -> 0 | BM34: =BL34 -> 0 | BN34: =BM34 -> 0 | BO34: =BN34 -> 0 | BP34: =BO34 -> 0 | BQ34: =BP34 -> 0 | BR34: =BQ34 -> 0 | ... BU34: =BT34 -> 0 | BV34: =SUM(BJ34:BU34) -> 0 | BW34: Unallocated expenses (includes DDA) | BX34: =BV34*(1+Inflation!$J$5) -> 0 | BY34: =BX34*(1+Inflation!$J$4) -> 0 | BZ34: =BY34*(1+Inflation!$J$4) -> 0 | CA34: =BZ34*(1+Inflation!$J$4) -> 0 | CB34: =CA34*(1+Inflation!$J$4) -> 0 | CC34: =CB34*(1+Inflation!$J$4) -> 0 | CD34: =CC34*(1+Inflation!$J$4) -> 0 | CE34: =CD34*(1+Inflation!$J$4) -> 0 | CF34: =CE34*(1+Inflation!$J$4) -> 0 | ... CX34: =CW34*(1+Inflation!$J$4) -> 0
A35: Payroll Taxes & other taxes | B35: 711 | C35: 686 | D35: 546 | E35: 861 | F35: 274 | G35: 788 | H35: 951 | I35: 271 | J35: 993 | K35: 271 | L35: 271 | M35: 649 | N35: =SUM(B35:M35) -> 7272 | O35: 3250 | P35: =N35-O35 -> 4022 | Q35: Payroll Taxes | R35: 1240 | S35: 880 | T35: =AE35/12 -> 354.83333 | U35: =T35 -> 354.83333 | V35: =U35 -> 354.83333 | W35: =V35 -> 354.83333 | X35: =W35 -> 354.83333 | Y35: =X35 -> 354.83333 | Z35: =Y35 -> 354.83333 | AA35: =Z35 -> 354.83333 | AB35: =AA35 -> 354.83333 | AC35: =AB35 -> 354.83333 | AD35: =SUM(R35:AC35) -> 5668.3333 | AE35: 4258 | AF35: =AD35-AE35 -> 1410.3333 | AG35: Payroll Taxes | AH35: =AC35*(1+(Inflation!$G$6)) -> 363.70417 | AI35: =AH35 -> 363.70417 | AJ35: =AI35 -> 363.70417 | AK35: =AJ35 -> 363.70417 | AL35: =AK35 -> 363.70417 | AM35: =AL35 -> 363.70417 | AN35: =AM35 -> 363.70417 | AO35: =AN35 -> 363.70417 | AP35: =AO35 -> 363.70417 | ... AS35: =AR35 -> 363.70417 | AT35: =SUM(AH35:AS35) -> 4364.45 | AU35: Payroll Taxes | AV35: =AS35*(1+(Inflation!$H$6)) -> 372.79677 | AW35: =AV35 -> 372.79677 | AX35: =AW35 -> 372.79677 | AY35: =AX35 -> 372.79677 | AZ35: =AY35 -> 372.79677 | BA35: =AZ35 -> 372.79677 | BB35: =BA35 -> 372.79677 | BC35: =BB35 -> 372.79677 | BD35: =BC35 -> 372.79677 | ... BG35: =BF35 -> 372.79677 | BH35: =SUM(AV35:BG35) -> 4473.5612 | BI35: Payroll Taxes | BJ35: =BG35*(1+(Inflation!$I$6)) -> 382.11669 | BK35: =BJ35 -> 382.11669 | BL35: =BK35 -> 382.11669 | BM35: =BL35 -> 382.11669 | BN35: =BM35 -> 382.11669 | BO35: =BN35 -> 382.11669 | BP35: =BO35 -> 382.11669 | BQ35: =BP35 -> 382.11669 | BR35: =BQ35 -> 382.11669 | ... BU35: =BT35 -> 382.11669 | BV35: =SUM(BJ35:BU35) -> 4585.4003 | BW35: Payroll Taxes | BX35: =BV35*(1+Inflation!$J$5) -> 4700.0353 | BY35: =BX35*(1+Inflation!$J$4) -> 4850.4364 | BZ35: =BY35*(1+Inflation!$J$4) -> 5005.6504 | CA35: =BZ35*(1+Inflation!$J$4) -> 5165.8312 | CB35: =CA35*(1+Inflation!$J$4) -> 5331.1378 | CC35: =CB35*(1+Inflation!$J$4) -> 5501.7342 | CD35: =CC35*(1+Inflation!$J$4) -> 5677.7897 | CE35: =CD35*(1+Inflation!$J$4) -> 5859.479 | CF35: =CE35*(1+Inflation!$J$4) -> 6046.9823 | ... CX35: =CW35*(1+Inflation!$J$4) -> 10660.394
A36: Subtotal | B36: =SUM(B33:B35) -> 2842 | C36: =SUM(C33:C35) -> 1913 | D36: =SUM(D33:D35) -> 5273 | E36: =SUM(E33:E35) -> 1857 | F36: =SUM(F33:F35) -> 2216 | G36: =SUM(G33:G35) -> 3296 | H36: =SUM(H33:H35) -> 10812 | I36: =SUM(I33:I35) -> 3392 | ... M36: =SUM(M33:M35) -> 3842 | N36: =SUM(B36:M36) -> 46413 | O36: =SUM(O33:O35) -> 40697 | P36: =N36-O36 -> 5716 | Q36: Subtotal | R36: =SUM(R33:R35) -> 5356.6667 | S36: =SUM(S33:S35) -> 4996.6667 | T36: =SUM(T33:T35) -> 4471.5 | U36: =SUM(U33:U35) -> 4471.5 | V36: =SUM(V33:V35) -> 4471.5 | W36: =SUM(W33:W35) -> 4471.5 | X36: =SUM(X33:X35) -> 4471.5 | Y36: =SUM(Y33:Y35) -> 4471.5 | ... AC36: =SUM(AC33:AC35) -> 4471.5 | AD36: =SUM(R36:AC36) -> 55068.333 | AE36: =SUM(AE33:AE35) -> 53658 | AF36: =AD36-AE36 -> 1410.3333 | AG36: Subtotal | AH36: =SUM(AH33:AH35) -> 4583.2875 | AI36: =SUM(AI33:AI35) -> 4583.2875 | AJ36: =SUM(AJ33:AJ35) -> 4583.2875 | AK36: =SUM(AK33:AK35) -> 4583.2875 | AL36: =SUM(AL33:AL35) -> 4583.2875 | AM36: =SUM(AM33:AM35) -> 4583.2875 | AN36: =SUM(AN33:AN35) -> 4583.2875 | AO36: =SUM(AO33:AO35) -> 4583.2875 | ... AS36: =SUM(AS33:AS35) -> 4583.2875 | AT36: =SUM(AH36:AS36) -> 54999.45 | AU36: Subtotal | AV36: =SUM(AV33:AV35) -> 4697.8697 | AW36: =SUM(AW33:AW35) -> 4697.8697 | AX36: =SUM(AX33:AX35) -> 4697.8697 | AY36: =SUM(AY33:AY35) -> 4697.8697 | AZ36: =SUM(AZ33:AZ35) -> 4697.8697 | BA36: =SUM(BA33:BA35) -> 4697.8697 | BB36: =SUM(BB33:BB35) -> 4697.8697 | BC36: =SUM(BC33:BC35) -> 4697.8697 | ... BG36: =SUM(BG33:BG35) -> 4697.8697 | BH36: =SUM(AV36:BG36) -> 56374.436 | BI36: Subtotal | BJ36: =SUM(BJ33:BJ35) -> 4815.3164 | BK36: =SUM(BK33:BK35) -> 4815.3164 | BL36: =SUM(BL33:BL35) -> 4815.3164 | BM36: =SUM(BM33:BM35) -> 4815.3164 | BN36: =SUM(BN33:BN35) -> 4815.3164 | BO36: =SUM(BO33:BO35) -> 4815.3164 | BP36: =SUM(BP33:BP35) -> 4815.3164 | BQ36: =SUM(BQ33:BQ35) -> 4815.3164 | ... BU36: =SUM(BU33:BU35) -> 4815.3164 | BV36: =SUM(BJ36:BU36) -> 57783.797 | BW36: Subtotal | BX36: =SUM(BX33:BX35) -> 59228.392 | BY36: =SUM(BY33:BY35) -> 61123.701 | BZ36: =SUM(BZ33:BZ35) -> 63079.659 | CA36: =SUM(CA33:CA35) -> 65098.208 | CB36: =SUM(CB33:CB35) -> 67181.351 | CC36: =SUM(CC33:CC35) -> 69331.154 | CD36: =SUM(CD33:CD35) -> 71549.751 | CE36: =SUM(CE33:CE35) -> 73839.343 | ... CX36: =SUM(CX33:CX35) -> 134338.99
A37: Office Expenses | Q37: Office Expenses | AG37: Office Expenses | AU37: Office Expenses | BI37: Office Expenses | BW37: Office Expenses
A38: Supplies | B38: 174 | C38: 259 | D38: 204 | E38: 0 | F38: 0 | G38: 163 | H38: 83 | I38: 43 | J38: 95 | K38: 83 | L38: 83 | M38: 87 | N38: =SUM(B38:M38) -> 1274 | O38: 1000 | P38: =N38-O38 -> 274 | Q38: Supplies | R38: =AE38/12 -> 108.83333 | S38: =R38 -> 108.83333 | T38: =S38 -> 108.83333 | U38: =T38 -> 108.83333 | V38: =U38 -> 108.83333 | W38: =V38 -> 108.83333 | X38: =W38 -> 108.83333 | Y38: =X38 -> 108.83333 | Z38: =Y38 -> 108.83333 | ... AC38: =AB38 -> 108.83333 | AD38: =SUM(R38:AC38) -> 1306 | AE38: 1306 | AF38: =AD38-AE38 -> 0 | AG38: Supplies | AH38: =R38*(1+Inflation!$G$6) -> 111.55417 | AI38: =S38*(1+Inflation!$G$6) -> 111.55417 | AJ38: =T38*(1+Inflation!$G$6) -> 111.55417 | AK38: =U38*(1+Inflation!$G$6) -> 111.55417 | AL38: =V38*(1+Inflation!$G$6) -> 111.55417 | AM38: =W38*(1+Inflation!$G$6) -> 111.55417 | AN38: =X38*(1+Inflation!$G$6) -> 111.55417 | AO38: =Y38*(1+Inflation!$G$6) -> 111.55417 | ... AS38: =AC38*(1+Inflation!$G$6) -> 111.55417 | AT38: =SUM(AH38:AS38) -> 1338.65 | AU38: Supplies | AV38: =AH38*(1+Inflation!$H$6) -> 114.34302 | AW38: =AI38*(1+Inflation!$H$6) -> 114.34302 | AX38: =AJ38*(1+Inflation!$H$6) -> 114.34302 | AY38: =AK38*(1+Inflation!$H$6) -> 114.34302 | AZ38: =AL38*(1+Inflation!$H$6) -> 114.34302 | BA38: =AM38*(1+Inflation!$H$6) -> 114.34302 | BB38: =AN38*(1+Inflation!$H$6) -> 114.34302 | BC38: =AO38*(1+Inflation!$H$6) -> 114.34302 | ... BG38: =AS38*(1+Inflation!$H$6) -> 114.34302 | BH38: =SUM(AV38:BG38) -> 1372.1163 | BI38: Supplies | BJ38: =AV38*(1+Inflation!$I$6) -> 117.2016 | BK38: =AW38*(1+Inflation!$H$6) -> 117.2016 | BL38: =AX38*(1+Inflation!$H$6) -> 117.2016 | BM38: =AY38*(1+Inflation!$H$6) -> 117.2016 | BN38: =AZ38*(1+Inflation!$H$6) -> 117.2016 | BO38: =BA38*(1+Inflation!$H$6) -> 117.2016 | BP38: =BB38*(1+Inflation!$H$6) -> 117.2016 | BQ38: =BC38*(1+Inflation!$H$6) -> 117.2016 | BR38: =BD38*(1+Inflation!$H$6) -> 117.2016 | ... BU38: =BG38*(1+Inflation!$H$6) -> 117.2016 | BV38: =SUM(BJ38:BU38) -> 1406.4192 | BW38: Supplies | BX38: =BV38*(1+Inflation!$J$5) -> 1441.5796 | BY38: =BX38*(1+Inflation!$J$4) -> 1487.7102 | BZ38: =BY38*(1+Inflation!$J$4) -> 1535.3169 | CA38: =BZ38*(1+Inflation!$J$4) -> 1584.447 | CB38: =CA38*(1+Inflation!$J$4) -> 1635.1494 | CC38: =CB38*(1+Inflation!$J$4) -> 1687.4741 | CD38: =CC38*(1+Inflation!$J$4) -> 1741.4733 | CE38: =CD38*(1+Inflation!$J$4) -> 1797.2005 | CF38: =CE38*(1+Inflation!$J$4) -> 1854.7109 | ... CX38: =CW38*(1+Inflation!$J$4) -> 3269.7215
A39: Postage and Freight | B39: 0 | C39: 0 | D39: 0 | E39: 0 | F39: 0 | G39: 0 | H39: 0 | I39: 29 | J39: 29 | K39: 29 | L39: 29 | M39: 29 | N39: =SUM(B39:M39) -> 145 | O39: 348 | P39: =N39-O39 -> -203 | Q39: Postage and Freight | R39: =B39*(1+Inflation!$F$6) -> 0 | S39: 78 | T39: =AE39/12 -> 12.416667 | U39: =T39 -> 12.416667 | V39: =U39 -> 12.416667 | W39: =V39 -> 12.416667 | X39: =W39 -> 12.416667 | Y39: =X39 -> 12.416667 | Z39: =Y39 -> 12.416667 | AA39: =Z39 -> 12.416667 | AB39: =AA39 -> 12.416667 | AC39: =AB39 -> 12.416667 | AD39: =SUM(R39:AC39) -> 202.16667 | AE39: 149 | AF39: =AD39-AE39 -> 53.166667 | AG39: Postage and Freight | AH39: =R39*(1+Inflation!$G$6) -> 0 | AI39: =S39*(1+Inflation!$G$6) -> 79.95 | AJ39: =T39*(1+Inflation!$G$6) -> 12.727083 | AK39: =U39*(1+Inflation!$G$6) -> 12.727083 | AL39: =V39*(1+Inflation!$G$6) -> 12.727083 | AM39: =W39*(1+Inflation!$G$6) -> 12.727083 | AN39: =X39*(1+Inflation!$G$6) -> 12.727083 | AO39: =Y39*(1+Inflation!$G$6) -> 12.727083 | ... AS39: =AC39*(1+Inflation!$G$6) -> 12.727083 | AT39: =SUM(AH39:AS39) -> 207.22083 | AU39: Postage and Freight | AV39: =AH39*(1+Inflation!$H$6) -> 0 | AW39: =AI39*(1+Inflation!$H$6) -> 81.94875 | AX39: =AJ39*(1+Inflation!$H$6) -> 13.04526 | AY39: =AK39*(1+Inflation!$H$6) -> 13.04526 | AZ39: =AL39*(1+Inflation!$H$6) -> 13.04526 | BA39: =AM39*(1+Inflation!$H$6) -> 13.04526 | BB39: =AN39*(1+Inflation!$H$6) -> 13.04526 | BC39: =AO39*(1+Inflation!$H$6) -> 13.04526 | ... BG39: =AS39*(1+Inflation!$H$6) -> 13.04526 | BH39: =SUM(AV39:BG39) -> 212.40135 | BI39: Postage and Freight | BJ39: =AV39*(1+Inflation!$H$6) -> 0 | BK39: =AW39*(1+Inflation!$H$6) -> 83.997469 | BL39: =AX39*(1+Inflation!$H$6) -> 13.371392 | BM39: =AY39*(1+Inflation!$H$6) -> 13.371392 | BN39: =AZ39*(1+Inflation!$H$6) -> 13.371392 | BO39: =BA39*(1+Inflation!$H$6) -> 13.371392 | BP39: =BB39*(1+Inflation!$H$6) -> 13.371392 | BQ39: =BC39*(1+Inflation!$H$6) -> 13.371392 | ... BU39: =BG39*(1+Inflation!$H$6) -> 13.371392 | BV39: =SUM(BJ39:BU39) -> 217.71139 | BW39: Postage and Freight | BX39: =BV39*(1+Inflation!$J$5) -> 223.15417 | BY39: =BX39*(1+Inflation!$J$4) -> 230.29511 | BZ39: =BY39*(1+Inflation!$J$4) -> 237.66455 | CA39: =BZ39*(1+Inflation!$J$4) -> 245.26982 | CB39: =CA39*(1+Inflation!$J$4) -> 253.11845 | CC39: =CB39*(1+Inflation!$J$4) -> 261.21824 | CD39: =CC39*(1+Inflation!$J$4) -> 269.57722 | CE39: =CD39*(1+Inflation!$J$4) -> 278.20369 | CF39: =CE39*(1+Inflation!$J$4) -> 287.10621 | ... CX39: =CW39*(1+Inflation!$J$4) -> 506.14755
A40: Travel/Mileage Reimbursement | B40: 0 | C40: 0 | D40: 0 | E40: 0 | F40: 0 | G40: 0 | H40: 0 | I40: 16 | J40: 16 | K40: 16 | L40: 16 | M40: 19 | N40: =SUM(B40:M40) -> 83 | O40: 195 | P40: =N40-O40 -> -112 | Q40: Travel/Mileage Reimbursement | R40: =AE40/12 -> 7.0833333 | S40: =R40 -> 7.0833333 | T40: =S40 -> 7.0833333 | U40: =T40 -> 7.0833333 | V40: =U40 -> 7.0833333 | W40: =V40 -> 7.0833333 | X40: =W40 -> 7.0833333 | Y40: =X40 -> 7.0833333 | Z40: =Y40 -> 7.0833333 | ... AC40: =AB40 -> 7.0833333 | AD40: =SUM(R40:AC40) -> 85 | AE40: 85 | AF40: =AD40-AE40 -> 0 | AG40: Travel/Mileage Reimbursement | AH40: =R40*(1+Inflation!$G$6) -> 7.2604167 | AI40: =S40*(1+Inflation!$G$6) -> 7.2604167 | AJ40: =T40*(1+Inflation!$G$6) -> 7.2604167 | AK40: =U40*(1+Inflation!$G$6) -> 7.2604167 | AL40: =V40*(1+Inflation!$G$6) -> 7.2604167 | AM40: =W40*(1+Inflation!$G$6) -> 7.2604167 | AN40: =X40*(1+Inflation!$G$6) -> 7.2604167 | AO40: =Y40*(1+Inflation!$G$6) -> 7.2604167 | ... AS40: =AC40*(1+Inflation!$G$6) -> 7.2604167 | AT40: =SUM(AH40:AS40) -> 87.125 | AU40: Travel/Mileage Reimbursement | AV40: =AH40*(1+Inflation!$H$6) -> 7.4419271 | AW40: =AI40*(1+Inflation!$H$6) -> 7.4419271 | AX40: =AJ40*(1+Inflation!$H$6) -> 7.4419271 | AY40: =AK40*(1+Inflation!$H$6) -> 7.4419271 | AZ40: =AL40*(1+Inflation!$H$6) -> 7.4419271 | BA40: =AM40*(1+Inflation!$H$6) -> 7.4419271 | BB40: =AN40*(1+Inflation!$H$6) -> 7.4419271 | BC40: =AO40*(1+Inflation!$H$6) -> 7.4419271 | ... BG40: =AS40*(1+Inflation!$H$6) -> 7.4419271 | BH40: =SUM(AV40:BG40) -> 89.303125 | BI40: Travel/Mileage Reimbursement | BJ40: =AV40*(1+Inflation!$I$6) -> 7.6279753 | BK40: =AW40*(1+Inflation!$H$6) -> 7.6279753 | BL40: =AX40*(1+Inflation!$H$6) -> 7.6279753 | BM40: =AY40*(1+Inflation!$H$6) -> 7.6279753 | BN40: =AZ40*(1+Inflation!$H$6) -> 7.6279753 | BO40: =BA40*(1+Inflation!$H$6) -> 7.6279753 | BP40: =BB40*(1+Inflation!$H$6) -> 7.6279753 | BQ40: =BC40*(1+Inflation!$H$6) -> 7.6279753 | BR40: =BD40*(1+Inflation!$H$6) -> 7.6279753 | ... BU40: =BG40*(1+Inflation!$H$6) -> 7.6279753 | BV40: =SUM(BJ40:BU40) -> 91.535703 | BW40: Travel/Mileage Reimbursement | BX40: =BV40*(1+Inflation!$J$5) -> 93.824096 | BY40: =BX40*(1+Inflation!$J$4) -> 96.826467 | BZ40: =BY40*(1+Inflation!$J$4) -> 99.924914 | CA40: =BZ40*(1+Inflation!$J$4) -> 103.12251 | CB40: =CA40*(1+Inflation!$J$4) -> 106.42243 | CC40: =CB40*(1+Inflation!$J$4) -> 109.82795 | CD40: =CC40*(1+Inflation!$J$4) -> 113.34244 | CE40: =CD40*(1+Inflation!$J$4) -> 116.9694 | CF40: =CE40*(1+Inflation!$J$4) -> 120.71242 | ... CX40: =CW40*(1+Inflation!$J$4) -> 212.8073
A41: Subtotal | B41: =SUM(B38:B40) -> 174 | C41: =SUM(C38:C40) -> 259 | D41: =SUM(D38:D40) -> 204 | E41: =SUM(E38:E40) -> 0 | F41: =SUM(F38:F40) -> 0 | G41: =SUM(G38:G40) -> 163 | H41: =SUM(H38:H40) -> 83 | I41: =SUM(I38:I40) -> 88 | ... M41: =SUM(M38:M40) -> 135 | N41: =SUM(B41:M41) -> 1502 | O41: =SUM(O38:O40) -> 1543 | P41: =N41-O41 -> -41 | Q41: Subtotal | R41: =SUM(R38:R40) -> 115.91667 | S41: =SUM(S38:S40) -> 193.91667 | T41: =SUM(T38:T40) -> 128.33333 | U41: =SUM(U38:U40) -> 128.33333 | V41: =SUM(V38:V40) -> 128.33333 | W41: =SUM(W38:W40) -> 128.33333 | X41: =SUM(X38:X40) -> 128.33333 | Y41: =SUM(Y38:Y40) -> 128.33333 | ... AC41: =SUM(AC38:AC40) -> 128.33333 | AD41: =SUM(R41:AC41) -> 1593.1667 | AE41: =SUM(AE38:AE40) -> 1540 | AF41: =AD41-AE41 -> 53.166667 | AG41: Subtotal | AH41: =SUM(AH38:AH40) -> 118.81458 | AI41: =SUM(AI38:AI40) -> 198.76458 | AJ41: =SUM(AJ38:AJ40) -> 131.54167 | AK41: =SUM(AK38:AK40) -> 131.54167 | AL41: =SUM(AL38:AL40) -> 131.54167 | AM41: =SUM(AM38:AM40) -> 131.54167 | AN41: =SUM(AN38:AN40) -> 131.54167 | AO41: =SUM(AO38:AO40) -> 131.54167 | ... AS41: =SUM(AS38:AS40) -> 131.54167 | AT41: =SUM(AH41:AS41) -> 1632.9958 | AU41: Subtotal | AV41: =SUM(AV38:AV40) -> 121.78495 | AW41: =SUM(AW38:AW40) -> 203.7337 | AX41: =SUM(AX38:AX40) -> 134.83021 | AY41: =SUM(AY38:AY40) -> 134.83021 | AZ41: =SUM(AZ38:AZ40) -> 134.83021 | BA41: =SUM(BA38:BA40) -> 134.83021 | BB41: =SUM(BB38:BB40) -> 134.83021 | BC41: =SUM(BC38:BC40) -> 134.83021 | ... BG41: =SUM(BG38:BG40) -> 134.83021 | BH41: =SUM(AV41:BG41) -> 1673.8207 | BI41: Subtotal | BJ41: =SUM(BJ38:BJ40) -> 124.82957 | BK41: =SUM(BK38:BK40) -> 208.82704 | BL41: =SUM(BL38:BL40) -> 138.20096 | BM41: =SUM(BM38:BM40) -> 138.20096 | BN41: =SUM(BN38:BN40) -> 138.20096 | BO41: =SUM(BO38:BO40) -> 138.20096 | BP41: =SUM(BP38:BP40) -> 138.20096 | BQ41: =SUM(BQ38:BQ40) -> 138.20096 | ... BU41: =SUM(BU38:BU40) -> 138.20096 | BV41: =SUM(BJ41:BU41) -> 1715.6662 | BW41: Subtotal | BX41: =SUM(BX38:BX40) -> 1758.5579 | BY41: =SUM(BY38:BY40) -> 1814.8318 | BZ41: =SUM(BZ38:BZ40) -> 1872.9064 | CA41: =SUM(CA38:CA40) -> 1932.8394 | CB41: =SUM(CB38:CB40) -> 1994.6902 | CC41: =SUM(CC38:CC40) -> 2058.5203 | CD41: =SUM(CD38:CD40) -> 2124.393 | CE41: =SUM(CE38:CE40) -> 2192.3735 | ... CX41: =SUM(CX38:CX40) -> 3988.6764
A42: Utilities | Q42: Utilities | AG42: Utilities | AU42: Utilities | BI42: Utilities | BW42: Utilities
A43: Utility Bill, Water, Sewer & Trash | B43: 12012 | C43: 10719 | D43: 10712 | E43: 11037 | F43: 11572 | G43: 11331 | H43: 12375 | I43: 12783 | J43: 12983 | K43: 13337 | L43: 13891 | M43: 12119 | N43: =SUM(B43:M43) -> 144871 | O43: 153395 | P43: =N43-O43 -> -8524 | Q43: Utility Bill, Water, Sewer & Trash | R43: 12159 | S43: 11243 | T43: =AE43/12 -> 12500 | U43: =T43 -> 12500 | V43: =U43 -> 12500 | W43: =V43 -> 12500 | X43: =W43 -> 12500 | Y43: =X43 -> 12500 | Z43: =Y43 -> 12500 | AA43: =Z43 -> 12500 | AB43: =AA43 -> 12500 | AC43: =AB43 -> 12500 | AD43: =SUM(R43:AC43) -> 148402 | AE43: 150000 | AF43: =AD43-AE43 -> -1598 | AG43: Utility Bill, Water, Sewer & Trash | AH43: =AC43*(1+(Inflation!$G$3)) -> 13125 | AI43: =AH43 -> 13125 | AJ43: =AI43 -> 13125 | AK43: =AJ43 -> 13125 | AL43: =AK43 -> 13125 | AM43: =AL43 -> 13125 | AN43: =AM43 -> 13125 | AO43: =AN43 -> 13125 | AP43: =AO43 -> 13125 | ... AS43: =AR43 -> 13125 | AT43: =SUM(AH43:AS43) -> 157500 | AU43: Utility Bill, Water, Sewer & Trash | AV43: =AS43*(1+(Inflation!$H$3)) -> 13781.25 | AW43: =AV43 -> 13781.25 | AX43: =AW43 -> 13781.25 | AY43: =AX43 -> 13781.25 | AZ43: =AY43 -> 13781.25 | BA43: =AZ43 -> 13781.25 | BB43: =BA43 -> 13781.25 | BC43: =BB43 -> 13781.25 | BD43: =BC43 -> 13781.25 | ... BG43: =BF43 -> 13781.25 | BH43: =SUM(AV43:BG43) -> 165375 | BI43: Utility Bill, Water, Sewer & Trash | BJ43: =BG43*(1+(Inflation!$I$3)) -> 14470.312 | BK43: =BJ43 -> 14470.312 | BL43: =BK43 -> 14470.312 | BM43: =BL43 -> 14470.312 | BN43: =BM43 -> 14470.312 | BO43: =BN43 -> 14470.312 | BP43: =BO43 -> 14470.312 | BQ43: =BP43 -> 14470.312 | BR43: =BQ43 -> 14470.312 | ... BU43: =BT43 -> 14470.312 | BV43: =SUM(BJ43:BU43) -> 173643.75 | BW43: Utility Bill, Water, Sewer & Trash | BX43: =BV43*(1+Inflation!$J$3) -> 182325.94 | BY43: =BX43*(1+Inflation!$J$4) -> 188160.37 | BZ43: =BY43*(1+Inflation!$J$4) -> 194181.5 | CA43: =BZ43*(1+Inflation!$J$4) -> 200395.31 | CB43: =CA43*(1+Inflation!$J$4) -> 206807.96 | CC43: =CB43*(1+Inflation!$J$4) -> 213425.81 | CD43: =CC43*(1+Inflation!$J$4) -> 220255.44 | CE43: =CD43*(1+Inflation!$J$4) -> 227303.61 | CF43: =CE43*(1+Inflation!$J$4) -> 234577.33 | ... CX43: =CW43*(1+Inflation!$J$4) -> 413542.92
A44: Telecomm Services | B44: 292 | C44: 326 | D44: 324 | E44: 321 | F44: 492 | G44: 321 | H44: 321 | I44: 375 | J44: 322 | K44: 375 | L44: 375 | M44: 375 | N44: =SUM(B44:M44) -> 4219 | O44: 4500 | P44: =N44-O44 -> -281 | Q44: Telecomm Services | R44: 354 | S44: 370 | T44: =AE44/12 -> 384.41667 | U44: =T44 -> 384.41667 | V44: =U44 -> 384.41667 | W44: =V44 -> 384.41667 | X44: =W44 -> 384.41667 | Y44: =X44 -> 384.41667 | Z44: =Y44 -> 384.41667 | AA44: =Z44 -> 384.41667 | AB44: =AA44 -> 384.41667 | AC44: =AB44 -> 384.41667 | AD44: =SUM(R44:AC44) -> 4568.1667 | AE44: 4613 | AF44: =AD44-AE44 -> -44.833333 | AG44: Telecomm Services | AH44: =AC44*(1+(Inflation!$G$6)) -> 394.02708 | AI44: =AH44 -> 394.02708 | AJ44: =AI44 -> 394.02708 | AK44: =AJ44 -> 394.02708 | AL44: =AK44 -> 394.02708 | AM44: =AL44 -> 394.02708 | AN44: =AM44 -> 394.02708 | AO44: =AN44 -> 394.02708 | AP44: =AO44 -> 394.02708 | ... AS44: =AR44 -> 394.02708 | AT44: =SUM(AH44:AS44) -> 4728.325 | AU44: Telecomm Services | AV44: =AS44*(1+(Inflation!$H$6)) -> 403.87776 | AW44: =AV44 -> 403.87776 | AX44: =AW44 -> 403.87776 | AY44: =AX44 -> 403.87776 | AZ44: =AY44 -> 403.87776 | BA44: =AZ44 -> 403.87776 | BB44: =BA44 -> 403.87776 | BC44: =BB44 -> 403.87776 | BD44: =BC44 -> 403.87776 | ... BG44: =BF44 -> 403.87776 | BH44: =SUM(AV44:BG44) -> 4846.5331 | BI44: Telecomm Services | BJ44: =BG44*(1+(Inflation!$I$6)) -> 413.9747 | BK44: =BJ44 -> 413.9747 | BL44: =BK44 -> 413.9747 | BM44: =BL44 -> 413.9747 | BN44: =BM44 -> 413.9747 | BO44: =BN44 -> 413.9747 | BP44: =BO44 -> 413.9747 | BQ44: =BP44 -> 413.9747 | BR44: =BQ44 -> 413.9747 | ... BU44: =BT44 -> 413.9747 | BV44: =SUM(BJ44:BU44) -> 4967.6965 | BW44: Telecomm Services | BX44: =BV44*(1+Inflation!$J$5) -> 5091.8889 | BY44: =BX44*(1+Inflation!$J$4) -> 5254.8293 | BZ44: =BY44*(1+Inflation!$J$4) -> 5422.9838 | CA44: =BZ44*(1+Inflation!$J$4) -> 5596.5193 | CB44: =CA44*(1+Inflation!$J$4) -> 5775.6079 | CC44: =CB44*(1+Inflation!$J$4) -> 5960.4274 | CD44: =CC44*(1+Inflation!$J$4) -> 6151.1611 | CE44: =CD44*(1+Inflation!$J$4) -> 6347.9982 | CF44: =CE44*(1+Inflation!$J$4) -> 6551.1342 | ... CX44: =CW44*(1+Inflation!$J$4) -> 11549.177
A45: Subtotal | B45: =SUM(B43:B44) -> 12304 | C45: =SUM(C43:C44) -> 11045 | D45: =SUM(D43:D44) -> 11036 | E45: =SUM(E43:E44) -> 11358 | F45: =SUM(F43:F44) -> 12064 | G45: =SUM(G43:G44) -> 11652 | H45: =SUM(H43:H44) -> 12696 | I45: =SUM(I43:I44) -> 13158 | ... M45: =SUM(M43:M44) -> 12494 | N45: =SUM(B45:M45) -> 149090 | O45: =SUM(O43:O44) -> 157895 | P45: =N45-O45 -> -8805 | Q45: Subtotal | R45: =SUM(R43:R44) -> 12513 | S45: =SUM(S43:S44) -> 11613 | T45: =SUM(T43:T44) -> 12884.417 | U45: =SUM(U43:U44) -> 12884.417 | V45: =SUM(V43:V44) -> 12884.417 | W45: =SUM(W43:W44) -> 12884.417 | X45: =SUM(X43:X44) -> 12884.417 | Y45: =SUM(Y43:Y44) -> 12884.417 | ... AC45: =SUM(AC43:AC44) -> 12884.417 | AD45: =SUM(R45:AC45) -> 152970.17 | AE45: =SUM(AE43:AE44) -> 154613 | AF45: =AD45-AE45 -> -1642.8333 | AG45: Subtotal | AH45: =SUM(AH43:AH44) -> 13519.027 | AI45: =SUM(AI43:AI44) -> 13519.027 | AJ45: =SUM(AJ43:AJ44) -> 13519.027 | AK45: =SUM(AK43:AK44) -> 13519.027 | AL45: =SUM(AL43:AL44) -> 13519.027 | AM45: =SUM(AM43:AM44) -> 13519.027 | AN45: =SUM(AN43:AN44) -> 13519.027 | AO45: =SUM(AO43:AO44) -> 13519.027 | ... AS45: =SUM(AS43:AS44) -> 13519.027 | AT45: =SUM(AH45:AS45) -> 162228.33 | AU45: Subtotal | AV45: =SUM(AV43:AV44) -> 14185.128 | AW45: =SUM(AW43:AW44) -> 14185.128 | AX45: =SUM(AX43:AX44) -> 14185.128 | AY45: =SUM(AY43:AY44) -> 14185.128 | AZ45: =SUM(AZ43:AZ44) -> 14185.128 | BA45: =SUM(BA43:BA44) -> 14185.128 | BB45: =SUM(BB43:BB44) -> 14185.128 | BC45: =SUM(BC43:BC44) -> 14185.128 | ... BG45: =SUM(BG43:BG44) -> 14185.128 | BH45: =SUM(AV45:BG45) -> 170221.53 | BI45: Subtotal | BJ45: =SUM(BJ43:BJ44) -> 14884.287 | BK45: =SUM(BK43:BK44) -> 14884.287 | BL45: =SUM(BL43:BL44) -> 14884.287 | BM45: =SUM(BM43:BM44) -> 14884.287 | BN45: =SUM(BN43:BN44) -> 14884.287 | BO45: =SUM(BO43:BO44) -> 14884.287 | BP45: =SUM(BP43:BP44) -> 14884.287 | BQ45: =SUM(BQ43:BQ44) -> 14884.287 | ... BU45: =SUM(BU43:BU44) -> 14884.287 | BV45: =SUM(BJ45:BU45) -> 178611.45 | BW45: Subtotal | BX45: =SUM(BX43:BX44) -> 187417.83 | BY45: =SUM(BY43:BY44) -> 193415.2 | BZ45: =SUM(BZ43:BZ44) -> 199604.48 | CA45: =SUM(CA43:CA44) -> 205991.83 | CB45: =SUM(CB43:CB44) -> 212583.57 | CC45: =SUM(CC43:CC44) -> 219386.24 | CD45: =SUM(CD43:CD44) -> 226406.6 | CE45: =SUM(CE43:CE44) -> 233651.61 | ... CX45: =SUM(CX43:CX44) -> 425092.09
A46: TOTAL CASH OUT | B46: =+B22+B31+B36+B41+B45 -> 74014 | C46: =+C22+C31+C36+C41+C45 -> 23946 | D46: =+D22+D31+D36+D41+D45 -> 72612.5 | E46: =+E22+E31+E36+E41+E45 -> 33124 | F46: =+F22+F31+F36+F41+F45 -> 24061 | G46: =+G22+G31+G36+G41+G45 -> 41783 | H46: =+H22+H31+H36+H41+H45 -> 227941 | I46: =+I22+I31+I36+I41+I45 -> 126441 | ... M46: =+M22+M31+M36+M41+M45 -> 172306.1 | N46: =SUM(B46:M46) -> 1108637.6 | O46: =O22+O31+O36+O41+O45 -> 1248700 | P46: =N46-O46 -> -140062.4 | Q46: TOTAL CASH OUT | R46: =+R22+R31+R36+R41+R45 -> 42550.675 | S46: =+S22+S31+S36+S41+S45 -> 41510.675 | T46: =+T22+T31+T36+T41+T45 -> 44603.342 | U46: =+U22+U31+U36+U41+U45 -> 37793.592 | V46: =+V22+V31+V36+V41+V45 -> 50006.092 | W46: =+W22+W31+W36+W41+W45 -> 231232.09 | X46: =+X22+X31+X36+X41+X45 -> 154989.73 | Y46: =+Y22+Y31+Y36+Y41+Y45 -> 112581.65 | ... AC46: =+AC22+AC31+AC36+AC41+AC45 -> 42603.342 | AD46: =SUM(R46:AC46) -> 1130991.8 | AE46: =+AE22+AE31+AE36+AE41+AE45 -> 1053547 | AF46: =AD46-AE46 -> 77444.767 | AG46: TOTAL CASH OUT | AH46: =+AH22+AH31+AH36+AH41+AH45 -> 44991.246 | AI46: =+AI22+AI31+AI36+AI41+AI45 -> 44071.196 | AJ46: =+AJ22+AJ31+AJ36+AJ41+AJ45 -> 46053.973 | AK46: =+AK22+AK31+AK36+AK41+AK45 -> 66895.708 | AL46: =+AL22+AL31+AL36+AL41+AL45 -> 74183.861 | AM46: =+AM22+AM31+AM36+AM41+AM45 -> 198124.25 | AN46: =+AN22+AN31+AN36+AN41+AN45 -> 89313.655 | AO46: =+AO22+AO31+AO36+AO41+AO45 -> 47313.655 | ... AS46: =+AS22+AS31+AS36+AS41+AS45 -> 44003.973 | AT46: =SUM(AH46:AS46) -> 777072.45 | AU46: TOTAL CASH OUT | AV46: =+AV22+AV31+AV36+AV41+AV45 -> 46786.45 | AW46: =+AW22+AW31+AW36+AW41+AW45 -> 45868.398 | AX46: =+AX22+AX31+AX36+AX41+AX45 -> 47900.745 | AY46: =+AY22+AY31+AY36+AY41+AY45 -> 56438.022 | AZ46: =+AZ22+AZ31+AZ36+AZ41+AZ45 -> 194831.51 | BA46: =+BA22+BA31+BA36+BA41+BA45 -> 42754.856 | BB46: =+BB22+BB31+BB36+BB41+BB45 -> 42754.856 | BC46: =+BC22+BC31+BC36+BC41+BC45 -> 43382.952 | ... BG46: =+BG22+BG31+BG36+BG41+BG45 -> 45799.495 | BH46: =SUM(AV46:BG46) -> 698421.25 | BI46: TOTAL CASH OUT | BJ46: =+BJ22+BJ31+BJ36+BJ41+BJ45 -> 48648.616 | BK46: =+BK22+BK31+BK36+BK41+BK45 -> 47732.614 | BL46: =+BL22+BL31+BL36+BL41+BL45 -> 49815.769 | BM46: =+BM22+BM31+BM36+BM41+BM45 -> 58382.947 | BN46: =+BN22+BN31+BN36+BN41+BN45 -> 44251.409 | BO46: =+BO22+BO31+BO36+BO41+BO45 -> 44251.409 | BP46: =+BP22+BP31+BP36+BP41+BP45 -> 44251.409 | BQ46: =+BQ22+BQ31+BQ36+BQ41+BQ45 -> 44902.035 | ... BU46: =+BU22+BU31+BU36+BU41+BU45 -> 47661.987 | BV46: =SUM(BJ46:BU46) -> 560808.26 | BW46: TOTAL CASH OUT | BX46: =+BX22+BX31+BX36+BX41+BX45 -> 580899.28 | BY46: =+BY22+BY31+BY36+BY41+BY45 -> 598620.58 | BZ46: =+BZ22+BZ31+BZ36+BZ41+BZ45 -> 739222.63 | CA46: =+CA22+CA31+CA36+CA41+CA45 -> 634840.68 | CB46: =+CB22+CB31+CB36+CB41+CB45 -> 653774.64 | CC46: =+CC22+CC31+CC36+CC41+CC45 -> 1226755.9 | CD46: =+CD22+CD31+CD36+CD41+CD45 -> 1229933.5 | CE46: =+CE22+CE31+CE36+CE41+CE45 -> 1158720.6 | ... CX46: =+CX22+CX31+CX36+CX41+CX45 -> 1251235.7
A47: Ending Cash Balance | B47: =B9+B16-B46 -> 543820 | C47: =C9+C16-C46 -> 618772 | D47: =D9+D16-D46 -> 649691.5 | E47: =E9+E16-E46 -> 711853 | F47: =F9+F16-F46 -> 773931.81 | G47: =G9+G16-G46 -> 825300.66 | H47: =H9+H16-H46 -> 824218 | I47: =I9+I16-I46 -> 670081.07 | ... M47: =M9+M16-M46 -> 528488.74 | Q47: Ending Balance (Operating + Reserve Cash) | R47: =R9+R16-R46 -> 646365.23 | S47: =S9+S16-S46 -> 687492.92 | T47: =T9+T16-T46 -> 707426.56 | U47: =U9+U16-U46 -> 731794.87 | V47: =V9+V16-V46 -> 772746.81 | W47: =W9+W16-W46 -> 600165.62 | X47: =X9+X16-X46 -> 503826.78 | Y47: =Y9+Y16-Y46 -> 449896.03 | ... AC47: =AC9+AC16-AC46 -> 268775.72 | AD47: =AC47 -> 268775.72 | AE47: 235497 | AF47: =AD47-AE47 -> 33278.717 | AG47: Ending Balance (Operating + Reserve Cash) | AH47: =AH9+AH16-AH46 -> 285176.35 | AI47: =AI9+AI16-AI46 -> 302497.02 | AJ47: =AJ9+AJ16-AJ46 -> 317834.93 | AK47: =AK9+AK16-AK46 -> 312331.09 | AL47: =AL9+AL16-AL46 -> 299539.11 | AM47: =AM9+AM16-AM46 -> 162806.73 | AN47: =AN9+AN16-AN46 -> 134884.95 | AO47: =AO9+AO16-AO46 -> 148963.17 | ... AS47: =AS9+AS16-AS46 -> 228405.76 | AT47: =AS47 -> 228405.76 | AU47: Ending Balance (Operating + Reserve Cash) | AV47: =AV9+AV16-AV46 -> 249979.74 | AW47: =AW9+AW16-AW46 -> 272471.76 | AX47: =AX9+AX16-AX46 -> 292931.44 | AY47: =AY9+AY16-AY46 -> 304853.84 | AZ47: =AZ9+AZ16-AZ46 -> 178382.75 | BA47: =BA9+BA16-BA46 -> 203988.31 | BB47: =BB9+BB16-BB46 -> 229593.88 | BC47: =BC9+BC16-BC46 -> 254571.35 | ... BG47: =BG9+BG16-BG46 -> 350309.58 | BH47: =BG47 -> 350309.58 | BI47: Ending Balance (Operating + Reserve Cash) | BJ47: =BJ9+BJ16-BJ46 -> 363191.65 | BK47: =BK9+BK16-BK46 -> 376989.72 | BL47: =BL9+BL16-BL46 -> 388704.63 | BM47: =BM9+BM16-BM46 -> 391852.36 | BN47: =BN9+BN16-BN46 -> 409131.64 | BO47: =BO9+BO16-BO46 -> 426410.91 | BP47: =BP9+BP16-BP46 -> 443690.18 | BQ47: =BQ9+BQ16-BQ46 -> 460318.83 | ... BU47: =BU9+BU16-BU46 -> 527869.51 | BV47: =BU47 -> 527869.51 | BW47: Ending Balance (Operating + Reserve Cash) | BX47: =BX9+BX16-BX46 -> 686202.63 | BY47: =BY9+BY16-BY46 -> 951900.25 | BZ47: =BZ9+BZ16-BZ46 -> 1077903.8 | CA47: =CA9+CA16-CA46 -> 1309219.9 | CB47: =CB9+CB16-CB46 -> 1522556 | CC47: =CC9+CC16-CC46 -> 1163888.6 | CD47: =CD9+CD16-CD46 -> 927245.83 | CE47: =CE9+CE16-CE46 -> 762843.22 | ... CX47: =CX9+CX16-CX46 -> 1884857.2
A48: Special Assessment | B48: 450 | C48: 450 | D48: 450 | E48: 450 | F48: 450 | G48: 450 | H48: 450 | I48: 450 | J48: 450 | K48: 450 | L48: 450 | M48: 450 | Q48: Special Assessments
A49: Monthly Assessment per Unit | B49: 350 | C49: 350 | D49: 350 | E49: 350 | F49: 350 | G49: 350 | H49: 350 | I49: 350 | J49: 350 | K49: 350 | L49: 350 | M49: 350 | Q49: Monthly Assessment per Unit | R49: 425 | S49: =R49 -> 425 | T49: =S49 -> 425 | U49: =T49 -> 425 | V49: =U49 -> 425 | W49: =V49 -> 425 | X49: =W49 -> 425 | Y49: =X49 -> 425 | Z49: =Y49 -> 425 | ... AE49: =AD49 -> 425 | AG49: Monthly Assessment per Unit | AH49: 425 | AI49: =AH49 -> 425 | AJ49: =AI49 -> 425 | AK49: =AJ49 -> 425 | AL49: =AK49 -> 425 | AM49: =AL49 -> 425 | AN49: =AM49 -> 425 | AO49: =AN49 -> 425 | AP49: =AO49 -> 425 | ... AT49: =AS49 -> 425 | AU49: Monthly Assessment per Unit | AV49: 475 | AW49: =AV49 -> 475 | AX49: =AW49 -> 475 | AY49: =AX49 -> 475 | AZ49: =AY49 -> 475 | BA49: =AZ49 -> 475 | BB49: =BA49 -> 475 | BC49: =BB49 -> 475 | BD49: =BC49 -> 475 | ... BH49: =BG49 -> 475 | BI49: Monthly Assessment per Unit | BJ49: 425 | BK49: =BJ49 -> 425 | BL49: =BK49 -> 425 | BM49: =BL49 -> 425 | BN49: =BM49 -> 425 | BO49: =BN49 -> 425 | BP49: =BO49 -> 425 | BQ49: =BP49 -> 425 | BR49: =BQ49 -> 425 | ... BV49: =BU49 -> 425 | BW49: Monthly Assessment per Unit | BX49: 425 | BY49: 500 | BZ49: 500 | CA49: 500 | CB49: 500 | CC49: 500 | CD49: 575 | CE49: 575 | CF49: 575 | CG49: 575 | CH49: 675 | CI49: 675 | CJ49: 675 | CK49: 675 | CL49: 650 | CM49: 650 | CN49: 650 | CO49: 650 | CP49: 650 | CQ49: 700 | CR49: 700 | CS49: 700 | CT49: 800 | CU49: 800 | CV49: 800 | CW49: 800 | CX49: 850
Q50: Line of Credit Payments (When Used) | R50: 0 | AG50: Loan Balance to Pay Off | AU50: Loan Balance to Pay Off | BI50: Loan Balance to Pay Off | BW50: Loan Balance to Pay Off
Q51: Loan Payments (When Used) | BW51: Minimum Year-End Reserve | BX51: =Reserves!G3 -> 515033.29 | BY51: =BX51*(1+Inflation!$J$13) -> 532710.18 | BZ51: =BY51*(1+Inflation!$J$13) -> 550993.77 | CA51: =BZ51*(1+Inflation!$J$13) -> 569904.89 | CB51: =CA51*(1+Inflation!$J$13) -> 589465.08 | CC51: =CB51*(1+Inflation!$J$13) -> 609696.61 | CD51: =CC51*(1+Inflation!$J$13) -> 630622.52 | CE51: =CD51*(1+Inflation!$J$13) -> 652266.64 | CF51: =CE51*(1+Inflation!$J$13) -> 674653.64 | ... CX51: =CW51*(1+Inflation!$J$13) -> 1238464
A52: Facilities Maintenance (Gantt Chart): | C52: Purple #'s are Maint Comm estimates and can shift in a row and auto-adjust for inflation. | Q52: Facilities Maintenance (Project Schedule): | AG52: Facilities Maintenance (Project Schedule): | AU52: Facilities Maintenance (Project Schedule): | BI52: Facilities Maintenance (Project Schedule): | BW52: Facilities Maintenance (Project Schedule):
P53: =N53-O53 -> 0 | Q53: Asphalt Cracks & Holes, Fill | X53: 48000 | AD53: =SUM(R53:AC53) -> 48000 | AE53: 48000 | AG53: Asphalt Cracks & Holes, Fill | AN53: 48000 | AT53: =SUM(AH53:AS53) -> 48000 | AU53: Asphalt Cracks & Holes, Fill | BH53: =SUM(AV53:BG53) -> 0 | BI53: Asphalt Cracks & Holes, Fill | BV53: =SUM(BJ53:BU53) -> 0 | BW53: Asphalt Cracks & Holes, Fill | BZ53: ='Project Costs'!$L$3*POWER(1+'Project Costs'!$J$1,Offset(BZ53,-50,0)-'Project Costs'!$I$1) -> 122761.16 | CM53: ='Project Costs'!$L$3*POWER(1+'Project Costs'!$J$1,Offset(CM53,-50,0)-'Project Costs'!$I$1) -> 194101.05
A54: Driveway pothole & crack repair | N54: =SUM(B54:M54) -> 0 | O54: 48000 | P54: =N54-O54 -> -48000 | AD54: =SUM(R54:AC54) -> 0 | AT54: =SUM(AH54:AS54) -> 0 | BH54: =SUM(AV54:BG54) -> 0 | BV54: =SUM(BJ54:BU54) -> 0 | BW54: Asphalt Milling and Overlay, then Replace | CI54: ='Project Costs'!M4/3 -> 347339.89 | CJ54: ='Project Costs'!M4/3 -> 347339.89 | CK54: ='Project Costs'!M4/3 -> 347339.89
A55: Landscaping Design Services | M55: 5000 | N55: =SUM(B55:M55) -> 5000 | P55: =N55-O55 -> 5000 | Q55: Landscaping, Wildfire Defensible Space | V55: 10000 | AD55: =SUM(R55:AC55) -> 10000 | AE55: 10000 | AG55: Landscaping | AM55: 10000 | AT55: =SUM(AH55:AS55) -> 10000 | AU55: Landscaping | BH55: =SUM(AV55:BG55) -> 0 | BI55: Landscaping | BV55: =SUM(BJ55:BU55) -> 0 | BW55: Landscaping | CN55: =('Project Costs'!$L$10*POWER(1+'Project Costs'!$J$1,Offset(CN55,-54,0)-'Project Costs'!$I$1))*25/76 -> 0 | CO55: =('Project Costs'!$L$10*POWER(1+'Project Costs'!$J$1,Offset(CO55,-54,0)-'Project Costs'!$I$1))*25/76 -> 0 | CQ55: =('Project Costs'!$L$10*POWER(1+'Project Costs'!$J$1,Offset(CQ55,-54,0)-'Project Costs'!$I$1))*26/76 -> 0
A56: Chimney Chase Flashing & Siding Repairs | M56: =(('Project Costs'!$L$9*POWER(1+'Project Costs'!$J$1,Offset(M56,-53,0)-'Project Costs'!$I$1))*8/76)+(('Project Costs'!$L$10*POWER(1+'Project Costs'!$J$1,Offset(I55,-54,0)-'Project Costs'!$I$1))*25/76) -> 6627.2665 | N56: =SUM(B56:M56) -> 6627.2665 | O56: 120000 | P56: =N56-O56 -> -113372.73 | Q56: Chimney Chase Flashing & Siding Repairs, 13 Bldgs | Y56: =$AE$56*(25/76) -> 17877.632 | Z56: =$AE$56*(25/76) -> 17877.632 | AA56: =$AE$56*(26/76) -> 18592.737 | AD56: =SUM(R56:AC56) -> 54348 | AE56: 54348 | AG56: Chimney Chase Flashing & Siding Repairs | AT56: =SUM(AH56:AS56) -> 0 | AU56: Chimney Chase Flashing & Siding Repairs | BH56: =SUM(AV56:BG56) -> 0 | BI56: Chimney Chase Flashing & Siding Repairs | BV56: =SUM(BJ56:BU56) -> 0 | BW56: Chimney Chase Flashing & Siding Repairs | CN56: =('Project Costs'!$L$9*POWER(1+'Project Costs'!$J$1,Offset(CN56,-53,0)-'Project Costs'!$I$1))*25/76 -> 43410.272 | CO56: =('Project Costs'!$L$9*POWER(1+'Project Costs'!$J$1,Offset(CO56,-53,0)-'Project Costs'!$I$1))*25/76 -> 44967.387 | CQ56: =('Project Costs'!$L$9*POWER(1+'Project Costs'!$J$1,Offset(CQ56,-53,0)-'Project Costs'!$I$1))*26/76 -> 50181.228
A57: Roof Flashing Repairs | M57: 0 | N57: =SUM(B57:M57) -> 0 | O57: 120000 | P57: =N57-O57 -> -120000 | Q57: Roof Flashing Repairs, 13 Buildings | Y57: =$AE57*(4/14) -> 18524.286 | Z57: =$AE57*(5/14) -> 23155.357 | AA57: =$AE57*(5/14) -> 23155.357 | AD57: =SUM(R57:AC57) -> 64835 | AE57: 64835 | AT57: =SUM(AH57:AS57) -> 0 | BH57: =SUM(AV57:BG57) -> 0 | BV57: =SUM(BJ57:BU57) -> 0 | BW57: Roof Flashing, Remove and Replace
A58: Flat Roof Replacement | B58: 27685 | D58: 25659.5 | H58: 155514 | I58: 54994 | N58: =236620+B58 -> 264305 | O58: 325000 | P58: =N58-O58 -> -60695 | Q58: Chimney Chase Covers, 76 Covers | X58: =$AE58*(3/14) -> 24363.643 | Y58: =$AE58*(3/14) -> 24363.643 | Z58: =$AE58*(4/14) -> 32484.857 | AA58: =$AE58*(4/14) -> 32484.857 | AD58: =SUM(R58:AC58) -> 113697 | AE58: 113697 | AG58: Chimney Chase Covers | AT58: =SUM(AH58:AS58) -> 0 | AU58: Chimney Chase Covers | BH58: =SUM(AV58:BG58) -> 0 | BV58: =SUM(BJ58:BU58) -> 0 | BW58: Garage, Replace Roof membrane, PVC | CR58: =(('Project Costs'!$L$11)*POWER(1+'Project Costs'!$J$1,Offset(CR58,-55,0)-'Project Costs'!$I$1))*(9/26) -> 192949.92 | CS58: =(('Project Costs'!$L$11)*POWER(1+'Project Costs'!$J$1,Offset(CS58,-55,0)-'Project Costs'!$I$1))*(9/26) -> 199870.98 | CT58: =(('Project Costs'!$L$11)*POWER(1+'Project Costs'!$J$1,Offset(CT58,-55,0)-'Project Costs'!$I$1))*(8/26) -> 184035.82
A59: Gutters, Clean and Repair | N59: =SUM(B59:M59) -> 0 | O59: 0 | P59: =N59-O59 -> 0 | Q59: Gutters, Clean and Repair | AD59: =SUM(R59:AC59) -> 0 | AG59: Gutters, Clean and Repair | AT59: =SUM(AH59:AS59) -> 0 | AU59: Gutters, Clean and Repair | BH59: =SUM(AV59:BG59) -> 0 | BI59: Gutters, Clean and Repair | BV59: =SUM(BJ59:BU59) -> 0 | BW59: Gutters, Clean and Repair | BY59: 0 | BZ59: 0 | CA59: 0 | CB59: 0 | CC59: 0 | CD59: 0 | CE59: 0 | CF59: 0 | CG59: 0 | CH59: 0 | CI59: 0 | CJ59: 0 | CK59: 0 | CL59: 0 | CM59: 0 | CN59: 0 | CO59: 0 | CP59: 0 | CQ59: 0 | CR59: 0 | CS59: 0 | CT59: 0 | CU59: 0 | CV59: 0 | CW59: 0 | CX59: 0
A60: Gutters & Guards, Install all buildings | L60: 137937 | N60: =SUM(B60:M60) -> 137937 | O60: 0 | P60: =N60-O60 -> 137937 | Q60: Gutter Guards, Install | AD60: =SUM(R60:AC60) -> 0 | AT60: =SUM(AH60:AS60) -> 0 | BH60: =SUM(AV60:BG60) -> 0 | BV60: =SUM(BJ60:BU60) -> 0 | BW60: Gutter Guards, Install | CS60: =('Project Costs'!$L$13*POWER(1+'Project Costs'!$J$1,Offset(CS60,-57,0)-'Project Costs'!$I$1))*(5/7) -> 151018.44 | CT60: =('Project Costs'!$L$13*POWER(1+'Project Costs'!$J$1,Offset(CT60,-57,0)-'Project Costs'!$I$1))*(5/7) -> 156435.43
P61: =N61-O61 -> 0 | Q61: Gutters, Install on all horizontal roof edges | AD61: =SUM(R61:AC61) -> 0 | AT61: =SUM(AH61:AS61) -> 0 | BH61: =SUM(AV61:BG61) -> 0 | BV61: =SUM(BJ61:BU61) -> 0 | BW61: Gutters, Install on all horizontal roof edges | CR61: =('Project Costs'!$L$14*POWER(1+'Project Costs'!$J$1,Offset(CR61,-58,0)-'Project Costs'!$I$1))*(4/14) -> 127653.5 | CS61: =('Project Costs'!$L$14*POWER(1+'Project Costs'!$J$1,Offset(CQ59,-56,0)-'Project Costs'!$I$1))*(5/14) -> 154041.44 | CT61: =('Project Costs'!$L$14*POWER(1+'Project Costs'!$J$1,Offset(CR59,-56,0)-'Project Costs'!$I$1))*(5/14) -> 159566.87
A62: Paint Building Wood Exteriors | K62: 18259 | M62: 18500 | N62: =SUM(B62:M62) -> 36759 | O62: 35000 | P62: =N62-O62 -> 1759 | Q62: Paint 4 Full Buildings and Trim on 2 Stucco Buildings | W62: 187035 | AD62: =SUM(R62:AC62) -> 187035 | AE62: 187035 | AG62: Paint 4 Building Exteriors | AM62: =(('Project Costs'!$L$15+'Project Costs'!$L$16)*POWER(1+'Project Costs'!$J$1,Offset(AM62,-59,0)-'Project Costs'!$I$1))*(4/12) -> 146810.6 | AT62: =SUM(AH62:AS62) -> 146810.6 | AU62: Paint 4 Building Exteriors | AZ62: =(('Project Costs'!$L$15+'Project Costs'!$L$16)*POWER(1+'Project Costs'!$J$1,Offset(AZ62,-59,0)-'Project Costs'!$I$1))*(4/12) -> 152076.66 | BH62: =SUM(AV62:BG62) -> 152076.66 | BI62: Paint for Building Exteriors | BV62: =SUM(BJ62:BU62) -> 0 | BW62: Paint for Building Exteriors | CG62: =(('Project Costs'!$L$15+'Project Costs'!$L$16)*POWER(1+'Project Costs'!$J$1,Offset(CG62,-59,0)-'Project Costs'!$I$1))*(4/14) -> 192075.67 | CH62: =(('Project Costs'!$L$15+'Project Costs'!$L$16)*POWER(1+'Project Costs'!$J$1,Offset(CH62,-59,0)-'Project Costs'!$I$1))*(4/14) -> 198965.38 | CI62: =(('Project Costs'!$L$15+'Project Costs'!$L$16)*POWER(1+'Project Costs'!$J$1,Offset(CI62,-59,0)-'Project Costs'!$I$1))*(4/14) -> 206102.21 | CJ62: =(('Project Costs'!$L$15+'Project Costs'!$L$16)*POWER(1+'Project Costs'!$J$1,Offset(CJ62,-59,0)-'Project Costs'!$I$1))*(1/14) -> 53373.762
P63: =N63-O63 -> 0 | Q63: Parking Lots, Restripe | AD63: =SUM(R63:AC63) -> 0 | AE63: 0 | AG63: Parking Lots, Restripe | AT63: =SUM(AH63:AS63) -> 0 | AU63: Parking Lots, Restripe | BD63: =('Project Costs'!$L$17*POWER(1+'Project Costs'!$J$1,Offset(BD63,-60,0)-'Project Costs'!$I$1)) -> 5471.9709 | BH63: =SUM(AV63:BG63) -> 5471.9709 | BI63: Parking Lots, Restripe | BV63: =SUM(BJ63:BU63) -> 0 | BW63: Parking Lots, Restripe | BX63: =('Project Costs'!$L$17*POWER(1+'Project Costs'!$J$1,Offset(BX63,-60,0)-'Project Costs'!$I$1)) -> 5871.5677 | BY63: =('Project Costs'!$L$17*POWER(1+'Project Costs'!$J$1,Offset(BY63,-60,0)-'Project Costs'!$I$1)) -> 6082.1793 | BZ63: =('Project Costs'!$L$17*POWER(1+'Project Costs'!$J$1,Offset(BZ63,-60,0)-'Project Costs'!$I$1)) -> 6300.3454 | CA63: =('Project Costs'!$L$17*POWER(1+'Project Costs'!$J$1,Offset(CA63,-60,0)-'Project Costs'!$I$1)) -> 6526.3372 | CB63: =('Project Costs'!$L$17*POWER(1+'Project Costs'!$J$1,Offset(CB63,-60,0)-'Project Costs'!$I$1)) -> 6760.4352 | CC63: =('Project Costs'!$L$17*POWER(1+'Project Costs'!$J$1,Offset(CC63,-60,0)-'Project Costs'!$I$1)) -> 7002.9302 | CD63: =('Project Costs'!$L$17*POWER(1+'Project Costs'!$J$1,Offset(CD63,-60,0)-'Project Costs'!$I$1)) -> 7254.1235 | CE63: =('Project Costs'!$L$17*POWER(1+'Project Costs'!$J$1,Offset(CE63,-60,0)-'Project Costs'!$I$1)) -> 7514.327 | ... CX63: =('Project Costs'!$L$17*POWER(1+'Project Costs'!$J$1,Offset(CX63,-60,0)-'Project Costs'!$I$1)) -> 14678.709
P64: =N64-O64 -> 0 | Q64: Guardrails on the patio area next to the pool | X64: 17620 | AD64: =SUM(R64:AC64) -> 17620 | AE64: 17620 | AT64: =SUM(AH64:AS64) -> 0 | BH64: =SUM(AV64:BG64) -> 0 | BV64: =SUM(BJ64:BU64) -> 0 | BW64: Pool Repair and Plaster Resurface | CK64: ='Project Costs'!$L$18*POWER(1+'Project Costs'!$J$1,Offset(CK64,-61,0)-'Project Costs'!$I$1) -> 42624.872
A65: Project Management Agent | H65: 594 | I65: 252 | K65: 2179 | N65: =SUM(B65:M65) -> 3025 | O65: 0 | P65: =N65-O65 -> 3025 | Q65: Replace/Repair Skylights | Y65: 5810 | AD65: =SUM(R65:AC65) -> 5810 | AE65: 5810 | AT65: =SUM(AH65:AS65) -> 0 | BH65: =SUM(AV65:BG65) -> 0 | BV65: =SUM(BJ65:BU65) -> 0
P66: =N66-O66 -> 0 | Q66: Repair retaining wall by building 4 | Z66: 10170 | AD66: =SUM(R66:AC66) -> 10170 | AE66: 10170 | AG66: Retaining Wall, Replace (Bldgs #1, & #7 west side, only) | AL66: =('Project Costs'!$L$19*POWER(1+'Project Costs'!$J$1,Offset(AL66,-63,0)-'Project Costs'!$I$1)) -> 24253.854 | AT66: =SUM(AH66:AS66) -> 24253.854 | BH66: =SUM(AV66:BG66) -> 0 | BV66: =SUM(BJ66:BU66) -> 0 | BW66: Retaining Wall, Replace
P67: =N67-O67 -> 0 | Q67: Townhouse Walls, Decks | AB67: 48000 | AD67: =SUM(R67:AC67) -> 48000 | AE67: 48000 | AG67: Retaining Wall, Repair (Bldgs#3,4,10) | AK67: =('Project Costs'!$L$20*POWER(1+'Project Costs'!$J$1,Offset(AK67,-64,0)-'Project Costs'!$I$1)) -> 12333.085 | AT67: =SUM(AH67:AS67) -> 12333.085 | BH67: =SUM(AV67:BG67) -> 0 | BV67: =SUM(BJ67:BU67) -> 0 | BW67: Retaining Wall, Repair
CY68: Metal Roofs
P69: =N69-O69 -> 0 | Q69: Roof, Install Fiberglass-reinforced asphalt shingles | AT69: =SUM(AH69:AS69) -> 0 | BH69: =SUM(AV69:BG69) -> 0 | BV69: =SUM(BJ69:BU69) -> 0 | BW69: Roof, Install Fiberglass-reinforced asphalt shingles | CC69: =('Project Costs'!$L$22*POWER(1+'Project Costs'!$J$1,Offset(CC69,-66,0)-'Project Costs'!$I$1))*(5/14) -> 517978.72 | CD69: =('Project Costs'!$L$22*POWER(1+'Project Costs'!$J$1,Offset(CD69,-66,0)-'Project Costs'!$I$1))*(5/14) -> 536558.48 | CE69: =('Project Costs'!$L$22*POWER(1+'Project Costs'!$J$1,Offset(CE69,-66,0)-'Project Costs'!$I$1))*(4/14) -> 444643.75 | CY69: https://www.homebuddy.com/costs/roofing/cost-of-metal-roof-vs-shingles?Source=Sad&mb=2681&utm_source=Sad&utm_campaign=23252167347_188513140253&utm_term=new%20roof%20cost%202026_e&utm_medium=2681&utm_content=783797253811-g&offer_id=2904&ad_id=Cj0KCQjwlLDQBhDjARIsAPlIefFmQr-q-M9xcyHobo6IJPSK381XCNe0G4kCBi7duZYDP2utt1PT3AUaAqqwEALw_wcB&gad_source=1&gad_campaignid=23252167347&gbraid=0AAAAADdiad_XrdcidX2bkpt0i9wlbfn6d&gclid=Cj0KCQjwlLDQBhDjARIsAPlIefFmQr-q-M9xcyHobo6IJPSK381XCNe0G4kCBi7duZYDP2utt1PT3AUaAqqwEALw_wcB | CZ69: https://www.homewyse.com/services/cost_to_install_seam_metal_roof.html | DA69: https://foxhavenroof.com/metal-roof-vs-shingles-cost-complete-2026-price-comparison/ | DB69: https://www.google.com/search?q=cost+comparison+of+metal+roofs+versus+shingles&sca_esv=c4a9854c715d4f5d&sxsrf=ANbL-n4KH-FVvsuTYnT2-GJdlg3TJLijfQ%3A1779229093585&ei=peEMaufAI53LkPIPreHwwQk&ved=0ahUKEwinp-PwsMaUAxWdJUQIHa0wPJgQ4dUDCBI&uact=5&oq=cost+comparison+of+metal+roofs+versus+shingles&gs_lp=Egxnd3Mtd2l6LXNlcnAiLmNvc3QgY29tcGFyaXNvbiBvZiBtZXRhbCByb29mcyB2ZXJzdXMgc2hpbmdsZXMyCBAAGIAEGKIEMgUQABjvBUjGKlD2CFjvI3ABeACQAQCYAeYBoAGlDKoBBjEuMTAuMbgBA8gBAPgBAZgCDKACpQzCAgoQABhHGNYEGLADwgIGEAAYHhgNwgILEAAYgAQYigUYhgPCAggQABiJBRiiBMICChAhGAoYoAEYwwSYAwCIBgGQBgiSBwQxLjExoAfONrIHBDAuMTG4B-4LwgcJMi03LjQuMC4xyAeMAYAIAQ&sclient=gws-wiz-serp#fpstate=ive&vld=cid:0a541bb1,vid:i6cysOpwpe0,st:0
A70: Annual Roof Inspection & Maint, All Bldgs | M70: 14575 | N70: =SUM(B70:M70) -> 14575 | O70: 15000 | P70: =N70-O70 -> -425 | Q70: Roof Inspection and Repair, All Bldgs | AA70: 15041 | AD70: =SUM(R70:AC70) -> 15041 | AE70: 15041 | AG70: Roof Inspection and Repair, All Bldgs | AK70: =AA70*(1+Inflation!$J$4) -> 15522.312 | AT70: =SUM(AH70:AS70) -> 15522.312 | AU70: Roof Inspection and Repair, All Bldgs | AY70: =AK70*(1+Inflation!$J$4) -> 16019.026 | BH70: =SUM(AV70:BG70) -> 16019.026 | BI70: Roof Inspection and Repair, All Bldgs | BM70: =AY70*(1+Inflation!$J$4) -> 16531.635 | BV70: =SUM(BJ70:BU70) -> 16531.635 | BW70: Roof Inspection and Repair, All Bldgs | BX70: =BV70*(1+Inflation!$J$4) -> 17060.647 | BY70: =BX70*(1+Inflation!$J$4) -> 17606.588 | BZ70: =BY70*(1+Inflation!$J$4) -> 18169.999 | CA70: =BZ70*(1+Inflation!$J$4) -> 18751.439 | CB70: =CA70*(1+Inflation!$J$4) -> 19351.485 | CC70: =CB70*(1+Inflation!$J$4) -> 19970.732 | CD70: =CC70*(1+Inflation!$J$4) -> 20609.796 | CE70: =CD70*(1+Inflation!$J$4) -> 21269.309 | CF70: =CE70*(1+Inflation!$J$4) -> 21949.927 | ... CX70: =CW70*(1+Inflation!$J$4) -> 38696.139
A71: Sidewalk repairs & replacement | I71: 7992 | N71: =SUM(B71:M71) -> 7992 | O71: 4000 | P71: =N71-O71 -> 3992 | Q71: Sidewalks, Replace Concrete | Y71: 6000 | AD71: =SUM(R71:AC71) -> 6000 | AE71: 6000 | AG71: Sidewalks, Replace Concrete | AO71: 6000 | AT71: =SUM(AH71:AS71) -> 6000 | AU71: Sidewalks, Replace Concrete | BC71: =('Project Costs'!$L$23*POWER(1+'Project Costs'!$J$1,Offset(BC71,-68,0)-'Project Costs'!$I$1)) -> 628.09583 | BH71: =SUM(AV71:BG71) -> 628.09583 | BI71: Sidewalks, Replace Concrete | BQ71: =('Project Costs'!$L$23*POWER(1+'Project Costs'!$J$1,Offset(BQ71,-68,0)-'Project Costs'!$I$1)) -> 650.62547 | BV71: =SUM(BJ71:BU71) -> 650.62547 | BW71: Sidewalks, Replace Concrete | BX71: =('Project Costs'!$L$23*POWER(1+'Project Costs'!$J$1,Offset(BX71,-68,0)-'Project Costs'!$I$1)) -> 673.96323 | BY71: =('Project Costs'!$L$23*POWER(1+'Project Costs'!$J$1,Offset(BY71,-68,0)-'Project Costs'!$I$1)) -> 698.13812 | BZ71: =('Project Costs'!$L$23*POWER(1+'Project Costs'!$J$1,Offset(BZ71,-68,0)-'Project Costs'!$I$1)) -> 723.18015 | CA71: =('Project Costs'!$L$23*POWER(1+'Project Costs'!$J$1,Offset(CA71,-68,0)-'Project Costs'!$I$1)) -> 749.12043 | CB71: =('Project Costs'!$L$23*POWER(1+'Project Costs'!$J$1,Offset(CB71,-68,0)-'Project Costs'!$I$1)) -> 775.99118 | CC71: =('Project Costs'!$L$23*POWER(1+'Project Costs'!$J$1,Offset(CC71,-68,0)-'Project Costs'!$I$1)) -> 803.82578 | CD71: =('Project Costs'!$L$23*POWER(1+'Project Costs'!$J$1,Offset(CD71,-68,0)-'Project Costs'!$I$1)) -> 832.6588 | CE71: =('Project Costs'!$L$23*POWER(1+'Project Costs'!$J$1,Offset(CE71,-68,0)-'Project Costs'!$I$1)) -> 862.52605 | ... CX71: =('Project Costs'!$L$23*POWER(1+'Project Costs'!$J$1,Offset(CX71,-68,0)-'Project Costs'!$I$1)) -> 1684.8839
P72: =N72-O72 -> 0 | Q72: Gutter work, Bldg 13 | X72: 25000 | AD72: =SUM(R72:AC72) -> 25000 | AE72: 25000 | AT72: =SUM(AH72:AS72) -> 0 | BH72: =SUM(AV72:BG72) -> 0 | BV72: =SUM(BJ72:BU72) -> 0
A73: Wood Siding Repairs | M73: 50000 | N73: =SUM(B73:M73) -> 50000 | O73: 50000 | P73: =N73-O73 -> 0 | Q73: Wood Siding Repairs | AG73: Wood Siding Repairs | AM73: =W73*(1+Inflation!$G$4) -> 0 | AT73: =SUM(AH73:AS73) -> 0 | AU73: Wood Siding Repairs | BA73: =AM73*(1+Inflation!$H$4) -> 0 | BH73: =SUM(AV73:BG73) -> 0 | BI73: Wood Siding Repairs | BO73: =BA73*(1+Inflation!$H$4) -> 0 | BV73: =SUM(BJ73:BU73) -> 0 | BW73: Wood Siding Repairs | BX73: =BV73*(1+Inflation!$J$4) -> 0
A74: Tree Removal | G74: 10000 | H74: 14000 | I74: 27008 | N74: =SUM(B74:M74) -> 51008 | O74: 50000 | P74: =N74-O74 -> 1008 | Q74: Tree Removal & Grind, 15 Small Trees | Z74: 15605 | AD74: =SUM(R74:AC74) -> 15605 | AE74: 15605 | AT74: =SUM(AH74:AS74) -> 0 | BH74: =SUM(AV74:BG74) -> 0 | BV74: =SUM(BJ74:BU74) -> 0 | BW74: Xeriscaping, Install
P75: =N75-O75 -> 0 | Q75: Stairwell Guardrail, Replace on Unit 420 | W75: 4191 | AD75: =SUM(R75:AC75) -> 4191 | AE75: 4191 | AT75: =SUM(AH75:AS75) -> 0 | BH75: =SUM(AV75:BG75) -> 0 | BV75: =SUM(BJ75:BU75) -> 0
A76: Balcony and Stairwell Repairs | M76: 25000 | N76: =SUM(B76:M76) -> 25000 | O76: 25000 | P76: =N76-O76 -> 0 | Q76: Balcony and Stairwell Repairs, 41 Treads | AA76: 23173 | AD76: =SUM(R76:AC76) -> 23173 | AE76: 23173 | AG76: Balcony and Stairwell Repairs | AQ76: 5000 | AT76: =SUM(AH76:AS76) -> 5000 | AU76: Balcony and Stairwell Repairs | BE76: =AQ76*(1+Inflation!$H$2) -> 5175 | BH76: =SUM(AV76:BG76) -> 5175 | BI76: Balcony and Stairwell Repairs | BS76: =BE76*(1+Inflation!$H$2) -> 5356.125 | BV76: =SUM(BJ76:BU76) -> 5356.125 | BW76: Balcony and Stairwell Repairs
A77: Board Maintenance Contingency | I77: 0 | J77: 0 | K77: 0 | N77: =SUM(B77:M77) -> 0 | O77: 165586 | P77: =N77-O77 -> -165586 | AD77: =SUM(R77:AC77) -> 0 | AT77: =SUM(AH77:AS77) -> 0 | BH77: =SUM(AV77:BG77) -> 0 | BV77: =SUM(BJ77:BU77) -> 0
A78: Breaker Maintenance | M78: 15000 | N78: =SUM(B78:M78) -> 15000 | O78: 15000 | P78: =N78-O78 -> 0 | Q78: Breaker Maintenance, Inspection | Z78: 0 | AD78: =SUM(R78:AC78) -> 0 | AG78: Breaker Maintenance | AT78: =SUM(AH78:AS78) -> 0 | AU78: Breaker Maintenance | BD78: 0 | BH78: =SUM(AV78:BG78) -> 0 | BI78: Breaker Maintenance | BV78: =SUM(BJ78:BU78) -> 0 | BW78: Breaker Maintenance | BX78: 0 | BY78: =(BD78*(1+Inflation!$J$4))*(1+Inflation!$J$4) -> 0 | BZ78: 0 | CA78: 0 | CB78: =(BY78*(1+Inflation!$J$4))*(1+Inflation!$J$4) -> 0 | CC78: 0 | CD78: 0 | CE78: =(CB78*(1+Inflation!$J$4))*(1+Inflation!$J$4) -> 0 | CF78: 0 | CG78: 0 | CH78: =(CE78*(1+Inflation!$J$4))*(1+Inflation!$J$4) -> 0 | CI78: 0 | CJ78: 0 | CK78: =(CH78*(1+Inflation!$J$4))*(1+Inflation!$J$4) -> 0 | CL78: 0 | CM78: 0 | CN78: =(CK78*(1+Inflation!$J$4))*(1+Inflation!$J$4) -> 0 | CO78: 0 | CP78: 0 | CQ78: =(CN78*(1+Inflation!$J$4))*(1+Inflation!$J$4) -> 0 | CR78: 0 | CS78: 0 | CT78: =(CQ78*(1+Inflation!$J$4))*(1+Inflation!$J$4) -> 0 | CU78: 0 | CV78: 0 | CW78: =(CT78*(1+Inflation!$J$4))*(1+Inflation!$J$4) -> 0 | CX78: 0
A79: Water Valve and Line Inspection | K79: 19808 | N79: =SUM(B79:M79) -> 19808 | O79: 0 | P79: =N79-O79 -> 19808 | Q79: Water Valve and Line Annual Inspection | AA79: 0 | AD79: =SUM(R79:AC79) -> 0 | AE79: 0 | AG79: Water Valve and Line Inspection | AQ79: =AA79*(1+Inflation!$G$4) -> 0 | AT79: =SUM(AH79:AS79) -> 0 | AU79: Water Valve and Line Inspection | BE79: =AQ79*(1+Inflation!$H$4) -> 0 | BH79: =SUM(AV79:BG79) -> 0 | BI79: Water Valve and Line Inspection | BS79: =BE79*(1+Inflation!$I$4) -> 0 | BV79: =SUM(BJ79:BU79) -> 0 | BW79: Water Valve and Line Inspection | BX79: =BS79*(1+Inflation!$J$4) -> 0 | BY79: =BX79*(1+Inflation!$J$4) -> 0 | BZ79: =BY79*(1+Inflation!$J$4) -> 0 | CA79: =BZ79*(1+Inflation!$J$4) -> 0 | CB79: =CA79*(1+Inflation!$J$4) -> 0 | CC79: =CB79*(1+Inflation!$J$4) -> 0 | CD79: =CC79*(1+Inflation!$J$4) -> 0 | CE79: =CD79*(1+Inflation!$J$4) -> 0 | CF79: =CE79*(1+Inflation!$J$4) -> 0 | ... CX79: =CW79*(1+Inflation!$J$4) -> 0
N80: =SUM(B80:M80) -> 0 | O80: 0 | P80: =N80-O80 -> 0 | Q80: Sewer Inspection, Bi-annual Inspection | U80: 0 | AD80: =SUM(R80:AC80) -> 0 | AE80: 0 | AG80: Sewer Inspection | AT80: =SUM(AH80:AS80) -> 0 | AU80: Sewer Inspection | AY80: =(U80*(1+Inflation!$F$4))*(1+Inflation!$G$4) -> 0 | BH80: =SUM(AV80:BG80) -> 0 | BI80: Sewer Inspection | BV80: =SUM(BJ80:BU80) -> 0 | BW80: Sewer Inspection | BX80: =(AY80*(1+Inflation!$H$4))*(1+Inflation!$I$4) -> 0 | BY80: 0 | BZ80: =(BX80*(1+Inflation!$J$4))*(1+Inflation!$J$4) -> 0 | CA80: 0 | CB80: =(BZ80*(1+Inflation!$J$4))*(1+Inflation!$J$4) -> 0 | CC80: 0 | CD80: =(CB80*(1+Inflation!$J$4))*(1+Inflation!$J$4) -> 0 | CE80: 0 | CF80: =(CD80*(1+Inflation!$J$4))*(1+Inflation!$J$4) -> 0 | CG80: 0 | CH80: =(CF80*(1+Inflation!$J$4))*(1+Inflation!$J$4) -> 0 | CI80: 0 | CJ80: =(CH80*(1+Inflation!$J$4))*(1+Inflation!$J$4) -> 0 | CK80: 0 | CL80: =(CJ80*(1+Inflation!$J$4))*(1+Inflation!$J$4) -> 0 | CM80: 0 | CN80: =(CL80*(1+Inflation!$J$4))*(1+Inflation!$J$4) -> 0 | CO80: 0 | CP80: =(CN80*(1+Inflation!$J$4))*(1+Inflation!$J$4) -> 0 | CQ80: 0 | CR80: =(CP80*(1+Inflation!$J$4))*(1+Inflation!$J$4) -> 0 | CS80: 0 | CT80: =(CR80*(1+Inflation!$J$4))*(1+Inflation!$J$4) -> 0 | CU80: 0 | CV80: =(CT80*(1+Inflation!$J$4))*(1+Inflation!$J$4) -> 0 | CW80: 0 | CX80: =(CV80*(1+Inflation!$J$4))*(1+Inflation!$J$4) -> 0
A81: Raise or Replace 16 windows in Bldgs 5 & 8. | N81: =SUM(B81:M81) -> 0 | O81: 0 | P81: =N81-O81 -> 0 | Q81: Raise or Replace windows in Apt Bldgs. | V81: 0 | AD81: =SUM(R81:AC81) -> 0 | AE81: 0 | AG81: Raise or Replace windows in Apt Bldgs. | AL81: =('Project Costs'!L37+'Project Costs'!L38)*1/3 -> 8616.352 | AT81: =SUM(AH81:AS81) -> 8616.352 | BH81: =SUM(AV81:BG81) -> 0 | BV81: =SUM(BJ81:BU81) -> 0 | BW81: Raise or Replace windows in Apt Bldgs. | CC81: ='Project Costs'!M37+'Project Costs'!M38 -> 35496.946
A82: TOTAL | B82: =SUM(B53:B81) -> 27685 | C82: =SUM(C53:C81) -> 0 | D82: =SUM(D53:D81) -> 25659.5 | E82: =SUM(E53:E81) -> 0 | F82: =SUM(F53:F81) -> 0 | G82: =SUM(G53:G81) -> 10000 | H82: =SUM(H53:H81) -> 170108 | I82: =SUM(I53:I81) -> 90246 | ... M82: =SUM(M53:M81) -> 134702.27 | N82: =SUM(B82:M82) -> 636583.77 | O82: =SUM(O53:O78) -> 972586 | P82: =N82-O82 -> -336002.23 | Q82: TOTAL | R82: =SUM(R53:R81) -> 0 | S82: =SUM(S53:S81) -> 0 | T82: =SUM(T53:T81) -> 0 | U82: =SUM(U53:U81) -> 0 | V82: =SUM(V53:V81) -> 10000 | W82: =SUM(W53:W81) -> 191226 | X82: =SUM(X53:X81) -> 114983.64 | Y82: =SUM(Y53:Y81) -> 72575.56 | ... AC82: =SUM(AC53:AC81) -> 0 | AD82: =SUM(R82:AC82) -> 648525 | AE82: =SUM(AE53:AE81) -> 648525 | AG82: TOTAL | AH82: =SUM(AH53:AH81) -> 0 | AI82: =SUM(AI53:AI81) -> 0 | AJ82: =SUM(AJ53:AJ81) -> 0 | AK82: =SUM(AK53:AK81) -> 27855.397 | AL82: =SUM(AL53:AL81) -> 32870.206 | AM82: =SUM(AM53:AM81) -> 156810.6 | AN82: =SUM(AN53:AN81) -> 48000 | AO82: =SUM(AO53:AO81) -> 6000 | ... AS82: =SUM(AS53:AS81) -> 0 | AT82: =SUM(AH82:AS82) -> 276536.2 | AU82: TOTAL | AV82: =SUM(AV53:AV81) -> 0 | AW82: =SUM(AW53:AW81) -> 0 | AX82: =SUM(AX53:AX81) -> 0 | AY82: =SUM(AY53:AY81) -> 16019.026 | AZ82: =SUM(AZ53:AZ81) -> 152076.66 | BA82: =SUM(BA53:BA81) -> 0 | BB82: =SUM(BB53:BB81) -> 0 | BC82: =SUM(BC53:BC81) -> 628.09583 | ... BG82: =SUM(BG53:BG81) -> 0 | BH82: =SUM(AV82:BG82) -> 179370.75 | BI82: TOTAL | BJ82: =SUM(BJ53:BJ81) -> 0 | BK82: =SUM(BK53:BK81) -> 0 | BL82: =SUM(BL53:BL81) -> 0 | BM82: =SUM(BM53:BM81) -> 16531.635 | BN82: =SUM(BN53:BN81) -> 0 | BO82: =SUM(BO53:BO81) -> 0 | BP82: =SUM(BP53:BP81) -> 0 | BQ82: =SUM(BQ53:BQ81) -> 650.62547 | ... BU82: =SUM(BU53:BU81) -> 0 | BV82: =SUM(BJ82:BU82) -> 22538.385 | BW82: TOTAL | BX82: =SUM(BX53:BX81) -> 23606.178 | BY82: =SUM(BY53:BY81) -> 24386.905 | BZ82: =SUM(BZ53:BZ81) -> 147954.68 | CA82: =SUM(CA53:CA81) -> 26026.896 | CB82: =SUM(CB53:CB81) -> 26887.911 | CC82: =SUM(CC53:CC81) -> 581253.15 | CD82: =SUM(CD53:CD81) -> 565255.06 | CE82: =SUM(CE53:CE81) -> 474289.91 | ... CX82: =SUM(CX53:CX81) -> 55059.731
Q84: Project PRIORITIES for 2026 from 4-27-26 Workshop
Q85: #1 Paint four Buildings and trim: $187,035
Q86: #2 Asphalt cracks, potholes (prevent water intrusion): $48,000
Q87: #3 Replace Stairwell Guardrail on Unit 420: $4,191
Q88: #4 Replace 41 stairwell steps: $23,173
Q89: #5 Guardrails on the patio area next to the pool (already informed Samson and Joshua that they won’t fall off the cliff anymore on walks ;)) $17,620
Q90: #6 Landscaping, Wildfire Defensible Space. $10,000
Q91: #7 Chimney Chase Flashing & Siding Repairs. $54,348
Q92: #7 Roof Flashing Repairs, 13 Buildings. $64,835
Q93: #7 Chimney Chase Covers, all. $113,697
Q94: (NOTE: #7 likely have overlapping scope: waiting for new bid and information in coming week to establish scope)
Q95: #8 Replace/Repair Skylights. $5,810
... Q116: EXAMPLE MOVABLE FORMULA FOR PAINTING 1 BUILDING=(('Project Costs'!$L$15+'Project Costs'!$L$16)*POWER(1+'Project Costs'!$J$1,Offset(W62,-59,0)-'Project Costs'!$I$1))*(1/12)

Sheet Inflation
A1: Annual Inflation Rates: | B1: 2022 | C1: 2023 | D1: 2024 | E1: 2025 | F1: 2026 | G1: 2027 | H1: 2028 | I1: 2029 | J1: 2030 | K1: 2031 | L1: 2032 | M1: 2033 | N1: 2034 | O1: 2035 | P1: 2036 | Q1: 2037 | R1: 2038 | S1: 2039 | T1: 2040 | U1: 2041 | V1: 2042 | W1: 2043 | X1: 2044 | Y1: 2045 | Z1: 2046 | AA1: 2047 | AB1: 2048 | AC1: 2049 | AD1: 2050 | AE1: 2051 | AF1: 2052 | AG1: 2053 | AH1: 2054
A2: Annual Building Construction Inflation Rate | B2: 0.171 | C2: 0.1996 | D2: -0.00098 | E2: 0.0279 | F2: 0.037 | G2: 0.035 | H2: 0.035 | I2: 0.035 | J2: 0.035 | K2: https://fred.stlouisfed.org/series/PCU236223236223
A3: Annual Water Utility Inflation Rate | B3: 0.04 | C3: 0.04 | D3: 0.04 | E3: 0.049 | F3: 0.06 | G3: 0.05 | H3: 0.05 | I3: 0.05 | J3: 0.05 | K3: Los Alamos Department of Public Utilities. | L3: https://ladailypost.com/gibson-inflation-squeezes-utilities-too/
A4: Annual Building Maintenance/Repair Inflation Rate | B4: 0.118 | C4: 0.063 | D4: 0.0275 | E4: 0.047 | F4: 0.032 | G4: 0.032 | H4: 0.032 | I4: 0.032 | J4: 0.032 | K4: https://fred.stlouisfed.org/series/PCU2381MR2381MR
A5: Annual General Inflation Rate | B5: 0.068 | C5: 0.065 | D5: 0.025 | E5: 0.033 | F5: 0.025 | G5: 0.025 | H5: 0.025 | I5: 0.025 | J5: 0.025 | K5: https://www.usinflationcalculator.com/inflation/current-inflation-rates/#:~:text=The%20annual%20inflation%20rate%20for%20the%20United%20States,inflation%20over%20the%2012%20months%20ended%20October%202021.
A6: Annual Cost of Living Rate CPI (for salaries) | B6: 0.05 | C6: 0.04 | D6: 0.025 | E6: 0.025 | F6: 0.025 | G6: 0.025 | H6: 0.025 | I6: 0.025 | J6: 0.025 | K6: https://www.bls.gov/data/inflation_calculator.htm
A7: Number of Ridge Park Units | B7: 138 | C7: 138 | D7: 138 | E7: 138 | F7: 138 | G7: 138 | H7: 138 | I7: 138 | J7: 138
A8: Payroll Tax Rate | B8: 0.0866 | C8: 0.0866 | D8: 0.0866 | E8: 0.0866 | F8: 0.0866 | G8: 0.0866 | H8: 0.0866 | I8: 0.0866 | J8: 0.0866
A9: Reserve as % of Total Dues Collected | B9: 0.1 | C9: 0.1 | D9: 0.1 | E9: 0.1 | F9: 0.1 | G9: 0.1 | H9: 0.1 | I9: 0.1 | J9: 0.1
A11: Interest Income Rate on Reserve Account. | E11: 0.0225 | F11: 0.02 | G11: 0.02 | H11: 0.02 | I11: 0.02 | J11: 0.02
A13: Weighted Average Inflation Rate for Projects. | F13: =(F2*$C$16)+(F4*$C$17) -> 0.035869737 | G13: =(G2*$C$16)+(G4*$C$17) -> 0.034321842 | H13: =(H2*$C$16)+(H4*$C$17) -> 0.034321842 | I13: =(I2*$C$16)+(I4*$C$17) -> 0.034321842 | J13: =(J2*$C$16)+(J4*$C$17) -> 0.034321842
A15: Weighted Average Calculation: | B15: 2026 Budget | C15: % of Total
A16: Annual Building Construction | B16: ='30 Year'!AE27 -> 566158 | C16: =B16/B18 -> 0.7739474
A17: Annual Building Maintenance/Repair | B17: ='30 Year'!AE31-'30 Year'!AE27 -> 165362 | C17: =B17/B18 -> 0.2260526
A18: Total | B18: =SUM(B16:B17) -> 731520 | C18: =SUM(C16:C17) -> 1

Sheet 5 - Yr
A1: Ridge Park Luxury Condominiums, Inc., 5-Year Budget Projection
B3: ='30 Year'!AD3 -> 2026 | C3: ='30 Year'!AT3 -> 2027 | D3: ='30 Year'!BH3 -> 2028 | E3: ='30 Year'!BV3 -> 2029 | F3: ='30 Year'!BX3 -> 2030
A4: Starting Cash Balance | B4: 547842 | C4: ='30 Year'!AH9 -> 268775.72 | D4: ='30 Year'!AV9 -> 228405.76 | E4: ='30 Year'!BJ9 -> 350309.58 | F4: ='30 Year'!BX9 -> 527869.51
A5: CASH IN | B5: ='30 Year'!AD10 | C5: ='30 Year'!AT10 | D5: ='30 Year'!BH10 | E5: ='30 Year'!BV10 | F5: ='30 Year'!BX10
A6: Interest Income | B6: ='30 Year'!AE11 -> 5300 | C6: ='30 Year'!AT11 -> 2949.3167 | D6: ='30 Year'!BH11 -> 2577.6867 | E6: ='30 Year'!BV11 -> 3361.02 | F6: ='30 Year'!BX11 -> 334.25167
A7: Income from Owner Assessments | B7: ='30 Year'!AE12 -> 703800 | C7: ='30 Year'!AT12 -> 703800 | D7: ='30 Year'!BH12 -> 786600 | E7: ='30 Year'!BV12 -> 703800 | F7: ='30 Year'!BX12 -> 703800
A8: Other Income Apt Rent | B8: ='30 Year'!AE13 -> 30000 | C8: ='30 Year'!AT13 -> 30750 | D8: ='30 Year'!BH13 -> 31518.75 | E8: ='30 Year'!BV13 -> 32306.719 | F8: ='30 Year'!BX13 -> 33114.387
A9: RV Park Fees | B9: ='30 Year'!AE14 -> 2100 | C9: ='30 Year'!AT14 -> 2152.5 | D9: ='30 Year'!BH14 -> 2206.3125 | E9: ='30 Year'!BV14 -> 2261.4703 | F9: ='30 Year'!BX14 -> 2318.0071
A10: Late Fees, Resale Certificates | B10: ='30 Year'!AE15 -> 0 | C10: ='30 Year'!AT15 -> 0 | D10: ='30 Year'!BH15 -> 0 | E10: ='30 Year'!BV15 -> 0 | F10: ='30 Year'!BX15 -> 0
A11: TOTAL CASH IN | B11: ='30 Year'!AE16 -> 741200 | C11: ='30 Year'!AT16 -> 736702.5 | D11: ='30 Year'!BH16 -> 820325.06 | E11: ='30 Year'!BV16 -> 738368.19 | F11: ='30 Year'!BX16 -> 739232.39
A12: CASH OUT | B12: ='30 Year'!AE17 | C12: ='30 Year'!AT17 | D12: ='30 Year'!BH17 | E12: ='30 Year'!BV17 | F12: ='30 Year'!BX17
A13: Financial Management | B13: ='30 Year'!AE18 | C13: ='30 Year'!AT18 | D13: ='30 Year'!BH18 | E13: ='30 Year'!BV18 | F13: ='30 Year'!BX18
A14: Accounting | B14: ='30 Year'!AE19 -> 6824 | C14: ='30 Year'!AT19 -> 5824.05 | D14: ='30 Year'!BH19 -> 5969.6512 | E14: ='30 Year'!BV19 -> 6118.8925 | F14: ='30 Year'!BX19 -> 6271.8648
A15: Insurance | B15: ='30 Year'!AE20 -> 95097 | C15: ='30 Year'!AT20 -> 93783.4 | D15: ='30 Year'!BH20 -> 96127.985 | E15: ='30 Year'!BV20 -> 98531.185 | F15: ='30 Year'!BX20 -> 100994.46
A16: Legal/Professional Services | B16: ='30 Year'!AE21 -> 10295 | C16: ='30 Year'!AT21 -> 10552.478 | D16: ='30 Year'!BH21 -> 10816.289 | E16: ='30 Year'!BV21 -> 11086.697 | F16: ='30 Year'!BX21 -> 11363.864
A17: Subtotal | B17: ='30 Year'!AE22 -> 112216 | C17: ='30 Year'!AT22 -> 110159.93 | D17: ='30 Year'!BH22 -> 112913.93 | E17: ='30 Year'!BV22 -> 115736.77 | F17: ='30 Year'!BX22 -> 118630.19
... A42: Ending Cash Balance | B42: ='30 Year'!AE47 -> 235497 | C42: ='30 Year'!AT47 -> 228405.76 | D42: ='30 Year'!BH47 -> 350309.58 | E42: ='30 Year'!BV47 -> 527869.51 | F42: ='30 Year'!BX47 -> 686202.63
B43: ='30 Year'!AE48 | C43: ='30 Year'!AT48 | D43: ='30 Year'!BH48 | E43: ='30 Year'!BV48 | F43: ='30 Year'!BX48
A44: Monthly Assessment per Unit | B44: ='30 Year'!AE49 -> 425 | C44: ='30 Year'!AT49 -> 425 | D44: ='30 Year'!BH49 -> 475 | E44: ='30 Year'!BV49 -> 425 | F44: ='30 Year'!BX49 -> 425

Sheet 5-Yr Projects
A1: Ridge Park Luxury Condominiums, Inc., 5-Year Project Cost Projection
A3: Planned Expenditures (Projects) | B3: 2026 | C3: 2027 | D3: 2028 | E3: 2029 | F3: 2030
A4: ='30 Year'!Q53 -> Asphalt Cracks & Holes, Fill | B4: ='30 Year'!AD53 -> 48000 | C4: ='30 Year'!AT53 -> 48000 | F4: ='30 Year'!BX53
F5: ='30 Year'!BX54
F6: =#REF! -> #REF!
A7: ='30 Year'!Q56 -> Chimney Chase Flashing & Siding Repairs, 13 Bldgs | B7: ='30 Year'!AD56 -> 54348
A8: ='30 Year'!Q55 -> Landscaping, Wildfire Defensible Space | B8: ='30 Year'!AD55 -> 10000 | C8: ='30 Year'!AT55 -> 10000
A9: ='30 Year'!Q58 -> Chimney Chase Covers, 76 Covers | B9: ='30 Year'!AD58 -> 113697
A10: ='30 Year'!Q59 -> Gutters, Clean and Repair | F10: ='30 Year'!BX59
A13: ='30 Year'!Q62 -> Paint 4 Full Buildings and Trim on 2 Stucco Buildings | B13: ='30 Year'!AD62 -> 187035 | C13: ='30 Year'!AT62 -> 146810.6 | D13: ='30 Year'!BH62 -> 152076.66 | E13: ='30 Year'!BV62 -> 0
A14: ='30 Year'!Q63 -> Parking Lots, Restripe | B14: ='30 Year'!AD63 -> 0 | D14: ='30 Year'!BH63 -> 5471.9709 | F14: ='30 Year'!BX63 -> 5871.5677
A17: ='30 Year'!Q66 -> Repair retaining wall by building 4 | C17: ='30 Year'!AT66 -> 24253.854
A18: ='30 Year'!Q67 -> Townhouse Walls, Decks | C18: ='30 Year'!AT67 -> 12333.085
A19: ='30 Year'!Q57 -> Roof Flashing Repairs, 13 Buildings | B19: ='30 Year'!AD57 -> 64835
A21: ='30 Year'!Q70 -> Roof Inspection and Repair, All Bldgs | B21: ='30 Year'!AD70 -> 15041 | C21: ='30 Year'!AT70 -> 15522.312 | D21: ='30 Year'!BH70 -> 16019.026 | E21: ='30 Year'!BV70 -> 16531.635 | F21: ='30 Year'!BX70 -> 17060.647
A22: ='30 Year'!Q71 -> Sidewalks, Replace Concrete | B22: ='30 Year'!AD71 -> 6000 | C22: ='30 Year'!AT71 -> 6000 | D22: ='30 Year'!BH71 -> 628.09583 | E22: ='30 Year'!BV71 -> 650.62547 | F22: ='30 Year'!BX71 -> 673.96323
F23: ='30 Year'!BX72
A25: ='30 Year'!Q74 -> Tree Removal & Grind, 15 Small Trees | B25: ='30 Year'!AD74 -> 15605
F26: ='30 Year'!BX75
A27: ='30 Year'!Q76 -> Balcony and Stairwell Repairs, 41 Treads | B27: ='30 Year'!AD76 -> 23173 | C27: ='30 Year'!AT76 -> 5000 | E27: ='30 Year'!BV76 -> 5356.125
A29: ='30 Year'!Q78 -> Breaker Maintenance, Inspection | C29: ='30 Year'!AT78 -> 0 | E29: ='30 Year'!BV78 -> 0
A30: ='30 Year'!Q79 -> Water Valve and Line Annual Inspection | B30: ='30 Year'!AD79 -> 0 | C30: ='30 Year'!AT79 -> 0 | D30: ='30 Year'!BH79 -> 0 | E30: ='30 Year'!BV79 -> 0 | F30: ='30 Year'!BX79 -> 0
A31: ='30 Year'!Q80 -> Sewer Inspection, Bi-annual Inspection | B31: ='30 Year'!AD80 -> 0 | D31: ='30 Year'!BH80 -> 0 | F31: ='30 Year'!BX80 -> 0
A32: ='30 Year'!Q81 -> Raise or Replace windows in Apt Bldgs. | B32: ='30 Year'!AD81 -> 0 | C32: ='30 Year'!AT81 -> 8616.352 | F32: ='30 Year'!BX81
A33: ='30 Year'!Q82 -> TOTAL | B33: ='30 Year'!AD82 -> 648525 | C33: ='30 Year'!AT82 -> 276536.2 | D33: ='30 Year'!BH82 -> 179370.75 | E33: ='30 Year'!BV82 -> 22538.385 | F33: ='30 Year'!BX82 -> 23606.178
A35: ='30 Year'!Q49 -> Monthly Assessment per Unit | B35: ='30 Year'!R49 -> 425 | C35: ='30 Year'!AH49 -> 425 | D35: ='30 Year'!AV49 -> 475 | E35: ='30 Year'!BJ49 -> 425 | F35: ='30 Year'!BX49 -> 425

Sheet Project Costs
A1: Project Cost Estimates as of Oct 10, 2024 | D1: Add Cost Contingency | E1: 0.1 | H1: Current Year is | I1: 2026 | J1: =Inflation!F13 -> 0.035869737 | K1: 0.0707 | N1: https://edzarenski.com/category/inflation-indexing/#:~:text=Current%20and%20predicted%20Inflation%20rates%20updated%209%2D19%2D22%3A&text=Infra%20Avg%20%2D0.3%25-,2021%20Rsdn%20Inflation%2013.4%25%2C%20Nonres%20Bldgs%206.8%25%2C%20Non,Non%2Dbldg%20Infra%20Avg%2012.0%25 | P1: https://smartasset.com/investing/inflation-calculator#PvB6ecvWDI
A2: Project Descriptions (Yellow for 2026) | B2: PRIORITY | C2: Year Done | D2: Lifespan in Years | E2: Year Due | F2: Total Ridge Park Square Feet | G2: Total Ridge Park Linear Feet | H2: Online Estimate (Current Year) | I2: Actual Cost or Contractor Quote | J2: Add Cost Contingency | K2: NM Gross Receipts Tax | L2: TOTAL Estimated Current COST | M2: TOTAL Estimated Future COST | N2: Estimate Sources | O2: Lifespan Sources | P2: Other Cost Sources
A3: Asphalt Cracks, Fill | C3: 2010 | D3: 8 | E3: 2032 | G3: 12591 | I3: =48295*power(1+$J$1,$I$1-$C$3) -> 84875.92 | J3: =SUM(H3:I3)*$E$1 -> 8487.592 | K3: =(H3+I3)*$K$1 -> 6000.7276 | L3: =SUM(H3:K3) -> 99364.24 | M3: =L3*((1+$J$1)^(E3-$I$1)) -> 122761.16 | N3: https://www.homewyse.com/services/cost_to_apply_slurry_seal.html | O3: https://www.bobvila.com/articles/best-asphalt-driveway-crack-filler/ | P3: Check Registers | Q3: Stuart Bowling paid Danny Romero $48,295 in 2010 to do all.
A4: Asphalt Milling and Overlay | D4: 15 | E4: 2041 | F4: ='Cost Data'!Q18 -> 104926 | H4: 524630 | J4: =SUM(H4:I4)*$E$1 -> 52463 | K4: =(H4+I4)*$K$1 -> 37091.341 | L4: =SUM(H4:K4) -> 614184.34 | M4: =L4*((1+$J$1)^(E4-$I$1)) -> 1042019.7 | N4: https://texpaveexperts.com/blog/how-much-does-an-asphalt-overlay-cost/ | O4: https://www.michiganpaving.com/blog/asphalt-milling-and-overlay-cost/
A5: Asphalt, Replace | C5: 1984 | D5: 25 | E5: 2053 | F5: ='Cost Data'!Q18 -> 104926 | H5: 944334 | J5: =SUM(H5:I5)*$E$1 -> 94433.4 | K5: =(H5+I5)*$K$1 -> 66764.414 | L5: =SUM(H5:K5) -> 1105531.8 | M5: =L5*((1+$J$1)^(E5-$I$1)) -> 2862926.3 | N5: https://texpaveexperts.com/blog/how-much-does-an-asphalt-overlay-cost/ | O5: https://www.homewyse.com/services/cost_to_install_asphaltic_concrete_driveway.html
A6: Bldg 2 Remove Metal & Paint | D6: 8 | E6: 2026 | F6: 9030 | H6: 32580 | J6: =SUM(H6:I6)*$E$1 -> 3258 | K6: =(H6+I6)*$K$1 -> 2303.406 | L6: =SUM(H6:K6) -> 38141.406 | M6: =L6*((1+$J$1)^(E6-$I$1)) -> 38141.406 | N6: https://www.homewyse.com/services/cost_to_paint_house_exterior.html
A7: Bldg 4 Paint Wood Panels and Trim, Buy paint | C7: 2015 | D7: 15 | E7: 2026 | F7: 7029 | H7: 21885 | J7: =SUM(H7:I7)*$E$1 -> 2188.5 | K7: =(H7+I7)*$K$1 -> 1547.2695 | L7: =SUM(H7:K7) -> 25620.769 | M7: =L7*((1+$J$1)^(E7-$I$1)) -> 25620.769 | N7: https://www.homewyse.com/services/cost_to_paint_house_exterior.html
A8: Bldg 5 Repair Ground Level Wiring | E8: 2024 | J8: =SUM(H8:I8)*$E$1 -> 0 | K8: =(H8+I8)*$K$1 -> 0 | L8: =SUM(H8:K8) -> 0 | M8: =L8*power(1+$J$1,E8-$I$1) -> 0 | N8: Connie Reynolds
A9: Chimney Chases, Remove and Replace Flashing | D9: 20 | E9: 2026 | G9: 1892 | H9: 55708 | J9: =SUM(H9:I9)*$E$1 -> 5570.8 | K9: =(H9+I9)*$K$1 -> 3938.5556 | L9: =SUM(H9:K9) -> 65217.356 | M9: =L9*((1+$J$1)^(E9-$I$1)) -> 65217.356 | N9: https://www.angi.com/articles/how-much-should-it-cost-replace-flashing-around-chimney.htm | P9: https://www.homewyse.com/services/cost_to_install_shingle_roof.html | Q9: https://www.angi.com/articles/what-is-chimney-flashing.htm | R9: Maint Comm Est $733 each for 76 chases.
A10: Chimney Chases, Repair Wood Siding and Paint Touch-up | D10: 20 | E10: 2026 | F10: 12768 | H10: 20400 | J10: =SUM(H10:I10)*$E$1 -> 2040 | K10: =(H10+I10)*$K$1 -> 1442.28 | L10: =SUM(H10:K10) -> 23882.28 | M10: =L10*((1+$J$1)^(E10-$I$1)) -> 23882.28 | N10: https://www.homewyse.com/maintenance_costs/cost_to_repair_board_siding.html | P10: https://homeguide.com/costs/chimney-repair-cost#:~:text=Chimney%20flashing%20repair%20costs%20%24200,chimney%20meet%20to%20prevent%20leaking.
A11: Garage, Replace Flat Roof membrane, PVC | C11: 2025 | D11: 25 | E11: 2050 | F11: ='Cost Data'!X18+'Cost Data'!Y18 -> 11180 | H11: 235144 | I11: 239250 | K11: 0 | L11: =SUM(I11:K11) -> 239250 | M11: =L11*((1+$J$1)^(E11-$I$1)) -> 557410.87 | N11: https://www.roofcalc.org/flat-roof-calculator/ | O11: https://roofslope.com/average-flat-roof-membrane-life-span/ | P11: https://www.roofcalc.org/pvc-roofing/ | Q11: https://www.homewyse.com/services/cost_to_install_membrane_roofing_system.html
A12: Gutters, Clean and Repair | D12: 1 | E12: 2026 | I12: 6000 | L12: =SUM(H12:K12) -> 6000 | M12: =L12*((1+$J$1)^(E12-$I$1)) -> 6000 | N12: Connie Reynolds. $6,000 bid from Manny Jaquez.
A13: Gutter Guards, Install | C13: 2025 | D13: 25 | E13: 2050 | G13: 4036 | I13: 79641 | J13: =SUM(H13:I13)*$E$1 -> 7964.1 | K13: 0 | L13: =SUM(H13:K13) -> 87605.1 | M13: =L13*((1+$J$1)^(E13-$I$1)) -> 204104.64 | N13: https://www.thisoldhouse.com/gutters/22454418/gutter-guard-installation-cost | O13: https://www.homewyse.com/services/cost_to_install_rain_gutter_cover.html
A14: Gutters, Install on horizontal roof edges | C14: 2025 | D14: 25 | E14: 2050 | G14: 4036 | I14: 174335 | J14: =SUM(H14:I14)*$E$1 -> 17433.5 | K14: 0 | L14: =SUM(H14:K14) -> 191768.5 | M14: =L14*((1+$J$1)^(E14-$I$1)) -> 446787.24 | N14: https://www.costimates.com/calculators/seamless-gutter-cost-calculator/ | O14: https://www.barrybest.com/blog/seamless-gutters/when-will-you-need-to-replace-your-gutters/ | P14: https://www.homewyse.com/services/cost_to_install_metal_gutters.html#google_vignette
A15: Paint for Building Exteriors | C15: 2015 | D15: 15 | E15: 2026 | F15: ='Cost Data'!C18 -> 145273 | H15: 0 | J15: =SUM(H15:I15)*$E$1 -> 0 | K15: =(H15+I15)*$K$1 -> 0 | L15: =SUM(H15:K15) -> 0 | M15: =L15*power(1+$J$1,E15-$I$1) -> 0 | N15: https://www.homewyse.com/services/cost_to_paint_house_exterior.html | O15: https://www.paintzen.com/blog/how-long-should-an-exterior-paint-job-last#:~:text=A%3A%20Typically%205%2D10%20years,a%20contractor%20and%20quality%20products. | P15: Check Registers | Q15: Stuart Bowling negotiated a "deal" with Sherwin Williams in Santa Fe in 2014.
A16: Paint Building Wood Exteriors, includes paint | C16: 2015 | D16: 10 | E16: 2026 | F16: ='Cost Data'!C18 -> 145273 | I16: 363185 | J16: =SUM(H16:I16)*$E$1 -> 36318.5 | K16: =(H16+I16)*$K$1 -> 25677.179 | L16: =SUM(H16:K16) -> 425180.68 | M16: =L16*((1+$J$1)^(E16-$I$1)) -> 425180.68 | N16: https://www.homewyse.com/services/cost_to_paint_two_story_house.html | O16: Check Registers | P16: https://www.westernwalls.com/house-painting-cost-calculator/ | Q16: https://www.behr.com/consumer/how-to/exterior/how-much-exterior-paint-to-buy | R16: https://home.howstuffworks.com/home-improvement/home-diy/painting/estimating-exterior-paint.htm
A17: Parking Lots, Restripe | C17: 2024 | D17: 3 | E17: 2027 | G17: 4356 | H17: =G17*1 -> 4356 | J17: =SUM(H17:I17)*$E$1 -> 435.6 | K17: =(H17+I17)*$K$1 -> 307.9692 | L17: =SUM(H17:K17) -> 5099.5692 | M17: =L17*((1+$J$1)^(E17-$I$1)) -> 5282.4894 | N17: Check Registers | O17: https://alphapavingtexas.com/how-long-does-parking-lot-paint-take-to-dry/ | P17: https://www.homeadvisor.com/cost/outdoor-living/parking-lot-striping/
A18: Pool Repair and Plaster Resurface | C18: 2022 | D18: 20 | E18: 2042 | F18: 720 | I18: 20000 | J18: =SUM(H18:I18)*$E$1 -> 2000 | K18: =(H18+I18)*$K$1 -> 1414 | L18: =SUM(H18:K18) -> 23414 | M18: =L18*((1+$J$1)^(E18-$I$1)) -> 41148.872 | N18: Contractor Estimate | P18: https://www.homewyse.com/services/cost_to_replaster_pool.html
A19: Retaining Wall, Replace (Bldgs #1, & #7 west side, only) | C19: 2023 | D19: 50 | E19: 2073 | F19: 112.5 | I19: 20000 | J19: =SUM(H19:I19)*$E$1 -> 2000 | K19: =(H19+I19)*$K$1 -> 1414 | L19: =SUM(H19:K19) -> 23414 | M19: =L19*((1+$J$1)^(E19-$I$1)) -> 122692.34 | N19: RP Files | O19: https://eaquinn.com/causes-retaining-wall-collapse/ | P19: https://homeguide.com/costs/retaining-wall-cost
A20: Retaining Wall, Repair (Bldgs#4) | D20: 50 | E20: 2026 | I20: 10170 | J20: =SUM(H20:I20)*$E$1 -> 1017 | K20: =(H20+I20)*$K$1 -> 719.019 | L20: =SUM(H20:K20) -> 11906.019 | M20: =L20*((1+$J$1)^(E20-$I$1)) -> 11906.019 | N20: Connie Reynolds | P20: https://homeguide.com/costs/retaining-wall-cost
A21: Roof Flashing, Remove and Replace | D21: 20 | E21: 2025 | G21: =SUM('Cost Data'!M18:O18) -> 9771 | I21: 158779 | J21: =SUM(H21:I21)*$E$1 -> 15877.9 | K21: =(H21+I21)*$K$1 -> 11225.675 | L21: =SUM(H21:K21) -> 185882.58 | M21: =L21*((1+$J$1)^(E21-$I$1)) -> 179445.9 | N21: https://litespeedconstruction.com/how-much-does-it-cost-to-replace-wall-flashings/ | O21: https://www.angi.com/articles/roof-flashing-types.htm | P21: https://www.angi.com/articles/how-much-should-it-cost-replace-flashing-around-chimney.htm | R21: https://www.iko.com/blog/what-is-roof-flashing-how-to-install-it/
A22: Roof, Install Fiberglass-reinforced asphalt shingles | C22: 2011 | D22: 25 | E22: 2036 | F22: ='Cost Data'!I18 -> 122484.18 | H22: 896733 | J22: =SUM(H22:I22)*$E$1 -> 89673.3 | K22: =(H22+I22+J22)*$K$1 -> 69738.925 | L22: =SUM(H22:K22) -> 1056145.2 | M22: =L22*((1+$J$1)^(E22-$I$1)) -> 1502363.7 | N22: https://www.homewyse.com/services/cost_to_install_asphalt_shingle_roof.html | O22: https://www.inchcalculator.com/roof-replacement-cost/ | P22: Stuart Bowling said the cost of the roof replacement in 2009-2010 was $650,000. The online calculator high estimate for 122,484 square feet is $896,733 as of March, 2026. | Q22: https://smartasset.com/investing/inflation-calculator#UmpNAXEirk | R22: https://www.calculator.net/future-value-calculator.html?cyearsv=15&cstartingprinciplev=237%2C000&cinterestratev=3&ccontributeamountv=60%2C000&ciadditionat1=end&printit=0&x=Calculate#calresult | S22: https://www.taylormaderoofingllc.com/life-expectancy-of-fiberglass-shingles/#:~:text=With%20proper%20maintenance%2C%20you%20can,outshine%20many%20other%20roofing%20materials%3F | T22: https://www.homewyse.com/services/cost_to_install_seam_metal_roof.html | U22: https://roofingcalculator.com/
A23: Sidewalks, Replace Concrete | D23: 25 | E23: 2026 | F23: 100 | H23: 500 | J23: =SUM(H23:I23)*$E$1 -> 50 | K23: =(H23+I23)*$K$1 -> 35.35 | L23: =SUM(H23:K23) -> 585.35 | M23: =L23*((1+$J$1)^(E23-$I$1)) -> 585.35 | O23: https://aaaconcreteraising.com/how-often-should-you-replace-your-sidewalk/ | P23: https://www.remodelingexpense.com/costs/cost-of-concrete-sidewalk/
A24: Sprinkling System, Repair along Oppenheimer Dr. | J24: =SUM(H24:I24)*$E$1 -> 0 | L24: =SUM(H24:K24) -> 0 | M24: =L24*power(1+$J$1,E24-$I$1) -> 0 | N24: 2023 Bid from Victor's Landscaping
A25: Stucco, Bldgs 2 & 4, Paint & Labor | C25: 2021 | D25: 10 | E25: 2031 | F25: ='Cost Data'!D18 -> 12510 | H25: 66803 | J25: =SUM(H25:I25)*$E$1 -> 6680.3 | K25: =(H25+I25)*$K$1 -> 4722.9721 | L25: =SUM(H25:K25) -> 78206.272 | M25: =L25*((1+$J$1)^(E25-$I$1)) -> 93275.441 | O25: https://www.paintzen.com/blog/how-long-should-an-exterior-paint-job-last#:~:text=A%3A%20Typically%205%2D10%20years,a%20contractor%20and%20quality%20products. | P25: https://www.homewyse.com/services/cost_to_paint_house_exterior.html
A26: Townhouse Balconies, facing street | C26: 2014 | D26: 100 | E26: 2114 | I26: 96000 | J26: =SUM(H26:I26)*$E$1 -> 9600 | K26: =(H26+I26)*$K$1 -> 6787.2 | L26: =SUM(H26:K26) -> 112387.2 | M26: =L26*((1+$J$1)^(E26-$I$1)) -> 2497868.9 | N26: All balconies were replaced in 2014 for $96,000 per Stuart Bowling.
A27: Trees, Remove, 50-Foot Pines, others | C27: 2024 | E27: 2024 | I27: 48178 | K27: 0 | L27: =SUM(H27:K27) -> 48178 | M27: =L27*((1+$J$1)^(E27-$I$1)) -> 44899.187 | N27: Victor's Landscaping quote for 20 trees in 2025.
A28: Tree Stump, Remove each | E28: 2024 | J28: =SUM(H28:I28)*$E$1 -> 0 | L28: =SUM(H28:K28) -> 0 | M28: =L28*power(1+$J$1,E28-$I$1) -> 0 | N28: Victor's Landscaping estimate in 2023.
A29: Landscaping, Wildfire Defensible Space | D29: 25 | E29: 2026 | F29: 1650 | H29: 33000 | J29: =SUM(H29:I29)*$E$1 -> 3300 | K29: =(H29+I29)*$K$1 -> 2333.1 | L29: =SUM(H29:K29) -> 38633.1 | M29: =L29*((1+$J$1)^(E29-$I$1)) -> 38633.1 | N29: https://www.homeserve.com/en-us/blog/cost-guide/xeriscape/
A30: Balcony and Stairwell Repairs | L30: 25000 | N30: RP Board estimate
A31: Water Valve and Line Inspection | E31: 2026 | I31: 1500 | J31: =SUM(H31:I31)*$E$1 -> 150 | K31: =(H31+I31)*$K$1 -> 106.05 | L31: =SUM(H31:K31) -> 1756.05 | M31: =L31*((1+$J$1)^(E31-$I$1)) -> 1756.05 | N31: https://mainstreamhomeservices.com/faq/how-much-will-a-plumbing-inspection-cost/ | O31: https://www.salisburyut.com/the-importance-of-regular-maintenance-for-your-water-main/#:~:text=When%20to%20schedule%20maintenance,safe%20water%20efficiently%20and%20reliably.
A32: Sewer Inspection, Every 2 Years | E32: 2026 | I32: 3500 | J32: =SUM(H32:I32)*$E$1 -> 350 | K32: =(H32+I32)*$K$1 -> 247.45 | L32: =SUM(H32:K32) -> 4097.45 | M32: =L32*((1+$J$1)^(E32-$I$1)) -> 4097.45 | N32: https://www.balkanplumbing.com/sewer-scope-inspection-cost/ | O32: https://plumbers.promatcher.com/cost/los-alamos-nm-plumbers-costs-prices.aspx
A33: Electrical Breaker Inspection | E33: 2026 | H33: 14000 | K33: =(H33+I33)*$K$1 -> 989.8 | L33: =SUM(H33:K33) -> 14989.8 | M33: =L33*((1+$J$1)^(E33-$I$1)) -> 14989.8
A34: Roof Inspection | E34: 2026 | I34: 15000 | K34: =(H34+I34)*$K$1 -> 1060.5 | L34: =SUM(H34:K34) -> 16060.5 | M34: =L34*((1+$J$1)^(E34-$I$1)) -> 16060.5
A35: Gas Valves (County responsibility) (check)
A36: Chimney Chase Covers, Stainless Steel | E36: 2026 | H36: 113696 | L36: =SUM(H36:K36) -> 113696 | N36: https://www.rockfordchimneysupply.com/products/stainless-steel-chase-covers?_pos=2&_sid=3bdf65c28&_ss=r | O36: https://gerriormasonry.com/chimney-chase-cover-replacement-cost/
A37: Raise or Replace in Apt. Bldgs. 24 windows in Blds 5,6 7, & 8 | E37: 2035 | H37: 16930 | J37: =SUM(H37:I37)*$E$1 -> 1693 | K37: =(H37+I37)*$K$1 -> 1196.951 | L37: =SUM(H37:K37) -> 19819.951 | M37: =L37*((1+$J$1)^(E37-$I$1)) -> 27217.541 | N37: https://www.homewyse.com/services/cost_to_install_replacement_windows.html | O37: RP Board's Estimate is 17,233
A38: Reframe 24 window openings in Bldgs 5,6 7, & 8 | E38: 2035 | H38: 5150 | J38: =SUM(H38:I38)*$E$1 -> 515 | K38: =(H38+I38)*$K$1 -> 364.105 | L38: =SUM(H38:K38) -> 6029.105 | M38: =L38*((1+$J$1)^(E38-$I$1)) -> 8279.4055 | N38: https://www.homewyse.com/services/cost_to_frame_window_opening.html
A39: Tree Removal & Grind, 15 Small Trees | L39: 15000 | N39: Maint Comm estimate for 15 small trees.
A40: Replace Exterior Stair Treads (Unit 420) | E40: 2025 | H40: 10500 | J40: =SUM(H40:I40)*$E$1 -> 1050 | K40: =(H40+I40)*$K$1 -> 742.35 | L40: =SUM(H40:K40) -> 12292.35 | M40: =L40*((1+$J$1)^(E40-$I$1)) -> 11866.695 | N40: https://www.lapeyrestair.com/blog/concrete-filled-metal-pan-stair-treads/?srsltid=AfmBOopSDMZ6p0DUb_L8CMqtQtduL17MnaNp_bx2_wZnRJMBI7PjY2Dp | O40: https://commercialconcreteproducts.com/stair-tread/ | P40: https://www.acisupply.com/proddetail.php?prod=AV12395TB | Q40: https://www.angi.com/articles/how-much-does-it-cost-install-concrete-steps.htm
A41: Structural Engineering Inspection Report | C41: 2025 | E41: 2029 | L41: 5000
A43: EXAMPLE MOVABLE FORMULA FOR PAINTING 1 BLDG=(('Project Costs'!$L$15+'Project Costs'!$L$16)*POWER(1+'Project Costs'!$J$1,Offset(W62,-59,0)-'Project Costs'!$I$1))*(1/12)
A45: OFFSET FORMULA:
A46: How to use the OFFSET function in Google Sheets - Sheetgo

Sheet Cost Data
A1: Estimated & Actual Dimensions and Areas | R1: 0.12
A2: Use these Estimates to check Contractor Estimates for reasonable costs.
A3: Bldg # | B3: Design Type (I-VII) | C3: Siding & Paintable Wood Area Square Ft | D3: Stucco Area Square Ft | E3: Building Stories | F3: Chimney Chases | G3: Chimney Chase Cover Dimensions | H3: Chimney Chase Flashing Linear Feet | I3: Roof Area Square Ft | J3: Building Footprint Square Ft | K3: Gutter Linear Ft 2nd Story | L3: Gutter Linear Ft 3rd Story | M3: Gutter/Fascia/Flashing Linear Ft TOTAL | N3: Headwall Horizontal Flashing LF | O3: Sidewall Sloped Flashing LF | P3: Asphalt Area Location | Q3: Asphalt Area Square Feet | R3: Asphalt Cracks Linear Feet | S3: Parking Spaces | T3: Handicap Parking Spaces | U3: Parking Stripe Linear Feet 18 ft ea | V3: Flat Garage Roof per Building | W3: Garage Roof Area SF | X3: Total Garage Roof Area SF | Y3: Garage Parapet Linear Feet Per Pair | Z3: Retaining Wall Length | AA3: Retaining Wall Height | AB3: Stairways | AC3: Water Supply Valves | AD3: Electrical Breaker Boxes | AE3: Sewer Clean-outs | AF3: Gas Valves | AG3: Cantilevered Balconies
A4: 1 | B4: III | C4: 11539 | E4: 3 | F4: 4 | G4: 5"10" x 4'4" | H4: =20.26*F4 -> 81.04 | I4: 6905.7356 | J4: =I4*0.94 -> 6491.3915 | K4: 0 | L4: 184 | M4: =K4+L4 -> 184 | N4: 0 | O4: 222 | P4: N & W of Bldg 1 | Q4: 17648 | R4: 2118 | S4: 49 | T4: 1 | U4: =(S4+T4)*18 -> 900 | AB4: 4 | AC4: 1 | AD4: 1 | AE4: 2 | AF4: 1
A5: 2 | B5: III | C5: 7029 | D5: 4510 | E5: 3 | F5: 4 | G5: 5"10" x 4'4" | H5: =20.26*F5 -> 81.04 | I5: 6905.7356 | J5: =I5*0.94 -> 6491.3915 | K5: 0 | L5: 184 | M5: =K5+L5 -> 184 | N5: 0 | O5: 222 | P5: NE of Bldg 2 | Q5: 9306 | R5: 1117 | S5: 30 | U5: =(S5+T5)*18 -> 540 | AB5: 4 | AC5: 2 | AD5: 1 | AE5: 1 | AF5: 1
A6: 3 | B6: II | C6: 11213 | E6: 3 | F6: 8 | G6: 5"10" x 4'4" | H6: =20.26*F6 -> 162.08 | I6: 12788.399 | J6: =I6*0.94 -> 12021.095 | K6: 156 | L6: 144 | M6: =K6+L6 -> 300 | N6: 0 | O6: 444 | P6: NW of Bldg 3 | Q6: 6489 | R6: 779 | S6: 24 | T6: 2 | U6: =(S6+T6)*18 -> 468 | AB6: 8 | AC6: 4 | AD6: 1 | AE6: 2 | AF6: 1
A7: 4 | B7: I | C7: 7029 | D7: 8000 | E7: 3 | F7: 8 | G7: 5"10" x 4'4" | H7: =20.26*F7 -> 162.08 | I7: 16402.616 | J7: =I7*0.94 -> 15418.459 | K7: 208 | L7: 188 | M7: =K7+L7 -> 396 | N7: 0 | O7: 554 | P7: W of Bldg 4 | Q7: 13152 | R7: 1578 | S7: 25 | T7: 2 | U7: =(S7+T7)*18 -> 486 | AB7: 8 | AC7: 2 | AD7: 1 | AE7: 1 | AF7: 1
A8: 5 | B8: IV | C8: 14409 | E8: 3 | F8: 8 | G8: 5"10" x 4'4" | H8: =20.26*F8 -> 162.08 | I8: 12668.881 | J8: =I8*0.94 -> 11908.749 | K8: 300 | L8: 284 | M8: =K8+L8 -> 584 | N8: 267 | O8: 686 | P8: E of Bldg 5 | Q8: 4268 | R8: 512 | S8: 4 | T8: 1 | U8: =(S8+T8)*18 -> 90 | AB8: 8 | AC8: 4 | AD8: 1 | AE8: 1 | AF8: 2
A9: 6 | B9: V | C9: 11948 | E9: 3 | F9: 4 | G9: 5"10" x 4'4" | H9: =20.26*F9 -> 81.04 | I9: 7993.3471 | J9: =I9*0.94 -> 7513.7463 | K9: 184 | L9: 104 | M9: =K9+L9 -> 288 | N9: 108 | O9: 256 | R9: 0 | U9: =(S9+T9)*18 -> 0 | AB9: 4 | AC9: 2 | AD9: 1 | AE9: 1 | AF9: 1
A10: 7 | B10: V | C10: 11948 | E10: 3 | F10: 4 | G10: 5"10" x 4'4" | H10: =20.26*F10 -> 81.04 | I10: 7993.3471 | J10: =I10*0.94 -> 7513.7463 | K10: 184 | L10: 104 | M10: =K10+L10 -> 288 | N10: 108 | O10: 256 | P10: E of Bldg 7 | Q10: 9263 | R10: 1112 | S10: 29 | T10: 3 | U10: =(S10+T10)*18 -> 576 | AB10: 4 | AC10: 2 | AD10: 1 | AE10: 1 | AF10: 2
A11: 8 | B11: IV | C11: 14409 | E11: 3 | F11: 8 | G11: 5"10" x 4'4" | H11: =20.26*F11 -> 162.08 | I11: 12668.881 | J11: =I11*0.94 -> 11908.749 | K11: 300 | L11: 284 | M11: =K11+L11 -> 584 | N11: 267 | O11: 686 | P11: N of Bldg 8 | Q11: 9570 | R11: 1148 | S11: 15 | T11: 1 | U11: =(S11+T11)*18 -> 288 | AB11: 8 | AC11: 2 | AD11: 1 | AE11: 2 | AF11: 1
A12: 9 | B12: VII | C12: 7886 | E12: 2 | F12: 6 | G12: 5'4" x 2'4" | H12: =20.26*F12 -> 121.56 | I12: 7572.6446 | J12: =I12*0.94 -> 7118.286 | K12: 174 | L12: 96 | M12: =K12+L12 -> 270 | N12: 144 | O12: 210 | P12: N of Bldgs 9 & 10 | Q12: 11040 | R12: 1325 | S12: 18 | T12: 1 | U12: =(S12+T12)*18 -> 342 | V12: 6 | W12: 380 | X12: =V12*W12 -> 2280 | Y12: =(V12/2)*100 -> 300 | AC12: 2 | AD12: 6 | AE12: 2 | AF12: 1 | AG12: 6
A13: 10 | B13: VI | C13: 11799 | E13: 3 | F13: 4 | G13: 5'4" x 2'4" | H13: =20.26*F13 -> 81.04 | I13: 5199.0221 | J13: =I13*0.94 -> 4887.0808 | K13: 106 | L13: 64 | M13: =K13+L13 -> 170 | N13: 119 | O13: 142 | R13: 0 | U13: =(S13+T13)*18 -> 0 | V13: 4 | W13: 380 | X13: =V13*W13 -> 1520 | Y13: =(V13/2)*100 -> 200 | AC13: 2 | AD13: 4 | AE13: 3 | AF13: 1 | AG13: 4
A14: 11 | B14: VII | C14: 7886 | E14: 2 | F14: 6 | G14: 5'4" x 2'4" | H14: =20.26*F14 -> 121.56 | I14: 7572.6446 | J14: =I14*0.94 -> 7118.286 | K14: 174 | L14: 96 | M14: =K14+L14 -> 270 | N14: 144 | O14: 210 | P14: E of Bldgs 11 & 12 | Q14: 12480 | R14: 1498 | S14: 23 | T14: 1 | U14: =(S14+T14)*18 -> 432 | V14: 6 | W14: 380 | X14: =V14*W14 -> 2280 | Y14: =(V14/2)*100 -> 300 | AC14: 2 | AD14: 6 | AE14: 3 | AF14: 1 | AG14: 6
A15: 12 | B15: VI | C15: 11799 | E15: 3 | F15: 4 | G15: 5'4" x 2'4" | H15: =20.26*F15 -> 81.04 | I15: 6382.2478 | J15: =I15*0.94 -> 5999.313 | K15: 106 | L15: 64 | M15: =K15+L15 -> 170 | N15: 119 | O15: 142 | R15: 0 | U15: =(S15+T15)*18 -> 0 | V15: 4 | W15: 380 | X15: =V15*W15 -> 1520 | Y15: =(V15/2)*100 -> 200 | AC15: 2 | AD15: 4 | AE15: 2 | AF15: 1 | AG15: 4
A16: 13 | B16: VI | C16: 11799 | E16: 3 | F16: 6 | G16: 5'4" x 2'4" | H16: =20.26*F16 -> 121.56 | I16: 6408.5418 | J16: =I16*0.94 -> 6024.0292 | K16: 106 | L16: 64 | M16: =K16+L16 -> 170 | N16: 119 | O16: 142 | P16: E of Bldg 13 | Q16: 4230 | R16: 508 | S16: 0 | T16: 0 | U16: =(S16+T16)*18 -> 0 | V16: 6 | W16: 380 | X16: =V16*W16 -> 2280 | Y16: =(V16/2)*100 -> 300 | AC16: 2 | AD16: 6 | AE16: 3 | AF16: 1 | AG16: 6
A17: 505 | B17: Rec | C17: 4580 | E17: 2 | F17: 2 | G17: 4' x 12' | H17: =20.26*F17 -> 40.52 | I17: 5022.1359 | J17: =I17*0.94 -> 4720.8077 | K17: 178 | L17: 0 | M17: =K17+L17 -> 178 | N17: 80 | O17: 88 | P17: SW of Bldg 505 | Q17: 7480 | R17: 898 | S17: 12 | T17: 1 | U17: =(S17+T17)*18 -> 234 | AC17: 2 | AD17: 1 | AE17: 2 | AF17: 1
C18: =SUM(C4:C17) -> 145273 | D18: =SUM(D4:D17) -> 12510 | F18: =SUM(F4:F17) -> 76 | H18: =SUM(H4:H17) -> 1539.76 | I18: =SUM(I4:I17) -> 122484.18 | J18: =SUM(J4:J17) -> 115135.13 | K18: =SUM(K4:K17) -> 2176 | L18: =SUM(L4:L17) -> 1860 | M18: =SUM(M4:M17) -> 4036 | N18: =SUM(N4:N17) -> 1475 | O18: =SUM(O4:O17) -> 4260 | Q18: =SUM(Q4:Q17) -> 104926 | R18: =SUM(R4:R17) -> 12593 | S18: =SUM(S4:S17) -> 229 | T18: =SUM(T4:T17) -> 13 | U18: =SUM(U4:U17) -> 4356 | V18: =SUM(V4:V17) -> 26 | X18: =SUM(X4:X17) -> 9880 | Y18: =SUM(Y4:Y17) -> 1300 | AB18: =SUM(AB4:AB17) -> 48 | AC18: =SUM(AC4:AC17) -> 31 | AD18: =SUM(AD4:AD17) -> 35 | AE18: =SUM(AE4:AE17) -> 26 | AF18: =SUM(AF4:AF17) -> 16 | AG18: =SUM(AG4:AG17) -> 26
A20: Retaining Wall, RR Ties | I20: Measure | K20: N of Bldg 1 Parking
A21: Retaining Wall, Concrete Block | K21: NW of Bldg 2 Parking
A22: Retaining Wall, Concrete Block | K22: N of Bldg 8 Parking
A23: Retaining Wall, Concrete Block | K23: W of Bldg 13
A24: Retaining Wall, Concrete Block | K24: W of Bldg 12
A25: Retaining Wall, Concrete Block | K25: W of Bldg 11
A26: Retaining Wall, Concrete Block | K26: S of Bldg 10
A27: Retaining Wall, Concrete Block | K27: S of Bldg 10
A28: Retaining Wall, RR Ties | K28: SE of Bldg 5
K31: Asphalt Areas SF | P31: Park Spaces | Q31: Handicap
K32: 17648 | L32: N & W of Bldg 1 | P32: 49 | Q32: 1
K33: 9306 | L33: NE of Bdlg 2 | P33: 30
K34: 6489 | L34: NW of Bldg 3 | P34: 24 | Q34: 2
K35: 13152 | L35: W of Bldg 4 | P35: 25 | Q35: 2
K36: 4268 | L36: E of Bldg 5 | P36: 4 | Q36: 1
K38: 9263 | L38: E of Bldg 7 | P38: 29 | Q38: 3
K39: 9570 | L39: N of Bldg 8 | P39: 15 | Q39: 1
K40: 11040 | L40: N of Bldgs 9 & 10 | P40: 18 | Q40: 1
K42: 12480 | L42: E of Bldgs 11 & 12 | P42: 23 | Q42: 1
K44: 4230 | L44: E of Bldg 13 | P44: 0 | Q44: 0
K45: 7480 | L45: SW of Bldg 505 | P45: 12 | Q45: 1
K46: 99302 | L46: Total | P46: 229 | Q46: 13

Sheet TREAS RPT
A2: 2026 Budget BLUE = Budget Number/Averages & Estimates BLACK = Formula Results/Projected | B2: 2026 Actual to-date Total | C2: 2026 Budgeted Total | D2: Percent of Budgeted Amount | E2: Line Items Under Budget (Projected) | F2: Line Items Over Budget (Projected) | G2: Previous Whole Month Balances
B3: 2026 | C3: 2026 | G3: 4 | H3: Enter Previous Month # (1 - 12)
A4: Operating Account (checking) | G4: =HLOOKUP($G$3,'30 Year'!$R$1:$AC$8,4,false) -> 161117.56
A5: Reserves Account (savings) | G5: =HLOOKUP($G$3,'30 Year'!$R$1:$AC$8,7,false) -> 421309
A6: Investment Account (CD) | G6: =HLOOKUP($G$3,'30 Year'!$R$1:$AC$8,8,false) -> 128511 | H6: Includes CD interest on $125,000
A7: Starting Cash Balance (Current Month) | G7: =SUM(G4:G6) -> 710937.56
A8: CASH IN
A9: Interest Income | B9: =SUMIF('30 Year'!$R$1:$AC$1,"<="&$G$3,'30 Year'!$R11:$AC11) -> 5739.03 | C9: ='30 Year'!AE11 -> 5300 | D9: =$B9/$C9 -> 1.0828358 | E9: =if('30 Year'!$AF11<0,'30 Year'!$AF11," ") | F9: =if('30 Year'!$AF11<=0," ",'30 Year'!$AF11) -> 4887.8967 | H9: Includes 1-yr interest from CD.
A10: Income from Owner Assessments | B10: =SUMIF('30 Year'!$R$1:$AC$1,"<="&$G$3,'30 Year'!$R12:$AC12) -> 177667.8 | C10: ='30 Year'!AE12 -> 703800 | D10: =$B10/$C10 -> 0.25244075 | E10: =if('30 Year'!$AF12<0,'30 Year'!$AF12," ") | F10: =if('30 Year'!$AF12<=0," ",'30 Year'!$AF12) -> 1.1641532e-10
A11: Other Income Apt Rent | B11: =SUMIF('30 Year'!$R$1:$AC$1,"<="&$G$3,'30 Year'!$R13:$AC13) -> 7500 | C11: ='30 Year'!AE13 -> 30000 | D11: =$B11/$C11 -> 0.25 | E11: =if('30 Year'!$AF13<0,'30 Year'!$AF13," ") | F11: =if('30 Year'!$AF13<=0," ",'30 Year'!$AF13)
A12: RV Park Fees | B12: ='30 Year'!N14 -> 0 | C12: ='30 Year'!AE14 -> 2100 | D12: =$B12/$C12 -> 0 | F12: =if('30 Year'!$AF14<=0," ",'30 Year'!$AF14)
A13: Late Fees, Resale Certificates | B13: 0 | C13: 0 | E13: =if('30 Year'!$AF15<0,'30 Year'!$AF15," ")
A14: TOTAL CASH IN | B14: ='30 Year'!N16 -> 1269822.9 | C14: =SUM(C9:C13) -> 741200 | D14: =$B14/$C14 -> 1.7131987 | E14: =SUM(E8:E13) -> 0 | F14: =SUM(F9:F13) -> 4887.8967
A15: CASH OUT
A16: Financial Management
A17: Accounting | B17: =SUMIF('30 Year'!$R$1:$AC$1,"<="&$G$3,'30 Year'!$R19:$AC19) -> 1250 | C17: ='30 Year'!AE19 -> 6824 | D17: =$B17/$C17 -> 0.18317702 | E17: =if('30 Year'!$AF19<0,'30 Year'!$AF19," ") -> -1142 | F17: =if('30 Year'!$AF19<=0," ",'30 Year'!$AF19) | G17: Need Check Register/Payee Info
A18: Insurance | B18: =SUMIF('30 Year'!$R$1:$AC$1,"<="&$G$3,'30 Year'!$R20:$AC20) -> 24374 | C18: ='30 Year'!AE20 -> 95097 | D18: =$B18/$C18 -> 0.25630672 | E18: =if('30 Year'!$AF20<0,'30 Year'!$AF20," ") -> -3601 | F18: =if('30 Year'!$AF20<=0," ",'30 Year'!$AF20)
A19: Legal/Professional Services | B19: =SUMIF('30 Year'!$R$1:$AC$1,"<="&$G$3,'30 Year'!$R21:$AC21) -> 2573.775 | C19: ='30 Year'!AE21 -> 10295 | D19: =$B19/$C19 -> 0.25000243 | E19: =if('30 Year'!$AF21<0,'30 Year'!$AF21," ") | F19: =if('30 Year'!$AF21<=0," ",'30 Year'!$AF21) -> 0.1 | G19: Need Check Register/Payee Info
A20: Subtotal | B20: =SUMIF('30 Year'!$R$1:$AC$1,"<="&$G$3,'30 Year'!$R22:$AC22) -> 28197.775 | C20: =SUM(C17:C19) -> 112216 | D20: =$B20/$C20 -> 0.25128123
A21: Maintenance and Repairs
A22: Equipment Repairs | B22: =SUMIF('30 Year'!$R$1:$AC$1,"<="&$G$3,'30 Year'!$R24:$AC24) -> 492.25 | C22: ='30 Year'!AE24 -> 1969 | D22: =$B22/$C22 -> 0.25 | E22: =if('30 Year'!$AF24<0,'30 Year'!$AF24," ") -> 0 | F22: =if('30 Year'!$AF24<=0," ",'30 Year'!$AF24) | G22: Need Check Register/Payee Info
A23: Grounds Maintenance | B23: =SUMIF('30 Year'!$R$1:$AC$1,"<="&$G$3,'30 Year'!$R25:$AC25) -> 15468.5 | C23: ='30 Year'!AE25 -> 61874 | D23: =$B23/$C23 -> 0.25 | E23: =if('30 Year'!$AF25<0,'30 Year'!$AF25," ") -> 0 | F23: =if('30 Year'!$AF25<=0," ",'30 Year'!$AF25) | G23: Need Check Register/Payee Info
A24: Facility Maintenance (Misc Repairs) | B24: =SUMIF('30 Year'!$R$1:$AC$1,"<="&$G$3,'30 Year'!$R26:$AC26) -> 17973 | C24: ='30 Year'!AE26 -> 71892 | D24: =$B24/$C24 -> 0.25 | E24: =if('30 Year'!$AF26<0,'30 Year'!$AF26," ") | F24: =if('30 Year'!$AF26<=0," ",'30 Year'!$AF26) | G24: Need Check Register/Payee Info
A25: Facilities Maintenance (Projects) | B25: =SUMIF('30 Year'!$R$1:$AC$1,"<="&$G$3,'30 Year'!$R27:$AC27) -> 0 | C25: ='30 Year'!AD82 -> 648525 | D25: =$B25/$C25 -> 0 | E25: =if('30 Year'!$AF27<0,'30 Year'!$AF27," ") | F25: =if('30 Year'!$AF27<=0," ",'30 Year'!$AF27) -> 82367
A26: Pool Maintenance | B26: =SUMIF('30 Year'!$R$1:$AC$1,"<="&$G$3,'30 Year'!$R28:$AC28) -> 0 | C26: ='30 Year'!AE28 -> 8850 | D26: =$B26/$C26 -> 0 | E26: =if('30 Year'!$AF28<0,'30 Year'!$AF28," ") | F26: =if('30 Year'!$AF28<=0," ",'30 Year'!$AF28)
A27: Rental Unit Maintenance | B27: =SUMIF('30 Year'!$R$1:$AC$1,"<="&$G$3,'30 Year'!$R29:$AC29) -> 384.5 | C27: ='30 Year'!AE29 -> 1538 | D27: =$B27/$C27 -> 0.25 | E27: =if('30 Year'!$AF29<0,'30 Year'!$AF29," ") | F27: =if('30 Year'!$AF29<=0," ",'30 Year'!$AF29) -> 0 | G27: Need Check Register/Payee Info
A28: Snow Removal & Purchase Snow-Melt | B28: =SUMIF('30 Year'!$R$1:$AC$1,"<="&$G$3,'30 Year'!$R30:$AC30) -> 9619.5 | C28: ='30 Year'!AE30 -> 19239 | D28: =$B28/$C28 -> 0.5 | E28: =if('30 Year'!$AF30<0,'30 Year'!$AF30," ") | F28: =if('30 Year'!$AF30<=0," ",'30 Year'!$AF30) | G28: Need Check Register/Payee Info
A29: Subtotal | B29: =SUMIF('30 Year'!$R$1:$AC$1,"<="&$G$3,'30 Year'!$R31:$AC31) -> 43937.75 | C29: =SUM(C22:C28) -> 813887 | D29: =$B29/$C29 -> 0.053985074
A30: Office Salary Expenses | B30: ='30 Year'!N32
A31: Business Office Salary | B31: =SUMIF('30 Year'!$R$1:$AC$1,"<="&$G$3,'30 Year'!$L33:$R33) -> 78744 | C31: ='30 Year'!AE33 -> 49400 | D31: =$B31/$C31 -> 1.5940081 | E31: =if('30 Year'!$AF33<0,'30 Year'!$AF33," ") -> 0 | F31: =if('30 Year'!$AF33<=0," ",'30 Year'!$AF33) | G31: Need Check Register/Payee Info
A32: Unallocated expenses | B32: =SUMIF('30 Year'!$R$1:$AC$1,"<="&$G$3,'30 Year'!$R34:$AC34) -> 0 | E32: =if('30 Year'!$AF34<0,'30 Year'!$AF34," ") | F32: =if('30 Year'!$AF34<=0," ",'30 Year'!$AF34) | G32: Unexplained Expenses
A33: Payroll Taxes & other taxes | B33: =SUMIF('30 Year'!$R$1:$AC$1,"<="&$G$3,'30 Year'!$R35:$AC35) -> 1589.6667 | C33: ='30 Year'!AE35 -> 4258 | D33: =$B33/$C33 -> 0.37333646 | E33: =if('30 Year'!$AF35<0,'30 Year'!$AF35," ") | F33: =if('30 Year'!$AF35<=0," ",'30 Year'!$AF35) -> 1410.3333 | G33: Need Check Register/Payee Info
A34: Subtotal | B34: =SUMIF('30 Year'!$R$1:$AC$1,"<="&$G$3,'30 Year'!$R36:$AC36) -> 13939.667 | C34: =SUM(C31:C33) -> 53658 | D34: =$B34/$C34 -> 0.25978729
A35: Office Expenses | B35: ='30 Year'!N37
A36: Supplies | B36: =SUMIF('30 Year'!$R$1:$AC$1,"<="&$G$3,'30 Year'!$R38:$AC38) -> 326.5 | C36: ='30 Year'!AE38 -> 1306 | D36: =$B36/$C36 -> 0.25 | E36: =if('30 Year'!$AF38<0,'30 Year'!$AF38," ") | F36: =if('30 Year'!$AF38<=0," ",'30 Year'!$AF38) | G36: Need Check Register/Payee Info
A37: Postage and Freight | B37: =SUMIF('30 Year'!$R$1:$AC$1,"<="&$G$3,'30 Year'!$R39:$AC39) -> 102.83333 | C37: ='30 Year'!AE39 -> 149 | D37: =$B37/$C37 -> 0.6901566 | E37: =if('30 Year'!$AF39<0,'30 Year'!$AF39," ") | F37: =if('30 Year'!$AF39<=0," ",'30 Year'!$AF39) -> 53.166667
A38: Travel/Mileage Reimbursement | B38: =SUMIF('30 Year'!$R$1:$AC$1,"<="&$G$3,'30 Year'!$R40:$AC40) -> 21.25 | C38: ='30 Year'!AE40 -> 85 | D38: =$B38/$C38 -> 0.25 | E38: =if('30 Year'!$AF40<0,'30 Year'!$AF40," ") | F38: =if('30 Year'!$AF40<=0," ",'30 Year'!$AF40) | G38: Need Check Register/Payee Info
A39: Subtotal | B39: =SUMIF('30 Year'!$R$1:$AC$1,"<="&$G$3,'30 Year'!$R41:$AC41) -> 450.58333 | C39: =SUM(C36:C38) -> 1540 | D39: =$B39/$C39 -> 0.29258658
A40: Utilities | B40: ='30 Year'!N42
A41: Utility Bill, Water, Sewer & Trash | B41: =SUMIF('30 Year'!$R$1:$AC$1,"<="&$G$3,'30 Year'!$R43:$AC43) -> 36243 | C41: ='30 Year'!AE43 -> 150000 | D41: =$B41/$C41 -> 0.24162 | E41: =if('30 Year'!$AF43<0,'30 Year'!$AF43," ") -> -1598 | F41: =if('30 Year'!$AF43<=0," ",'30 Year'!$AF43)
A42: Telecomm Services | B42: =SUMIF('30 Year'!$R$1:$AC$1,"<="&$G$3,'30 Year'!$R44:$AC44) -> 1138.8333 | C42: ='30 Year'!AE44 -> 4613 | D42: =$B42/$C42 -> 0.24687477 | E42: =if('30 Year'!$AF44<0,'30 Year'!$AF44," ") -> -44.833333 | F42: =if('30 Year'!$AF44<=0," ",'30 Year'!$AF44)
A43: Subtotal | B43: =SUMIF('30 Year'!$R$1:$AC$1,"<="&$G$3,'30 Year'!$R45:$AC45) -> 37381.833 | C43: =SUM(C41:C42) -> 154613 | D43: =$B43/$C43 -> 0.24177678
A44: TOTAL CASH OUT | B44: =SUMIF('30 Year'!$B$1:$M$1,"<="&$G$3,'30 Year'!$B46:$M46) -> 203696.5 | C44: =C20+C29+C34+C39+C43 -> 1135914 | D44: =$B44/$C44 -> 0.17932387 | E44: =SUM(E15:E43) -> -6385.8333 | F44: =SUM(F15:F43) -> 83830.6
A45: Ending Cash Balance | G45: =HLOOKUP($G$3,'30 Year'!$R$1:$AC$47,47,false) -> 731794.87 | H45: Projected
A48: PROJECTS
A49: ='30 Year'!Q53 -> Asphalt Cracks & Holes, Fill | B49: =SUMIF('30 Year'!$R$1:$AC$1,"<="&$G$3,'30 Year'!$R$53:$AC$53) -> 0 | C49: ='30 Year'!AE53 -> 48000 | D49: =$B49/$C49 -> 0 | E49: =if('30 Year'!$AF53<0,'30 Year'!$AF53," ") | F49: =if('30 Year'!$AF53<=0," ",'30 Year'!$AF53)
A50: ='30 Year'!Q55 -> Landscaping, Wildfire Defensible Space | B50: =SUMIF('30 Year'!$R$1:$AC$1,"<="&$G$3,'30 Year'!$R$53:$AC$53) -> 0 | C50: ='30 Year'!AE55 -> 10000 | D50: =$B50/$C50 -> 0 | E50: =if('30 Year'!$AF55<0,'30 Year'!$AF55," ") | F50: =if('30 Year'!$AF55<=0," ",'30 Year'!$AF55)
A51: ='30 Year'!Q56 -> Chimney Chase Flashing & Siding Repairs, 13 Bldgs | B51: =SUMIF('30 Year'!$R$1:$AC$1,"<="&$G$3,'30 Year'!$R$53:$AC$53) -> 0 | C51: ='30 Year'!AE56 -> 54348 | D51: =$B51/$C51 -> 0 | E51: =if('30 Year'!$AF56<0,'30 Year'!$AF56," ") | F51: =if('30 Year'!$AF56<=0," ",'30 Year'!$AF56)
A52: ='30 Year'!Q57 -> Roof Flashing Repairs, 13 Buildings | B52: =SUMIF('30 Year'!$R$1:$AC$1,"<="&$G$3,'30 Year'!$R$53:$AC$53) -> 0 | C52: ='30 Year'!AE57 -> 64835 | D52: =$B52/$C52 -> 0 | E52: =if('30 Year'!$AF57<0,'30 Year'!$AF57," ") | F52: =if('30 Year'!$AF57<=0," ",'30 Year'!$AF57)
A53: ='30 Year'!Q58 -> Chimney Chase Covers, 76 Covers | B53: =SUMIF('30 Year'!$R$1:$AC$1,"<="&$G$3,'30 Year'!$R$53:$AC$53) -> 0 | C53: ='30 Year'!AE58 -> 113697 | D53: =$B53/$C53 -> 0 | E53: =if('30 Year'!$AF58<0,'30 Year'!$AF58," ") | F53: =if('30 Year'!$AF58<=0," ",'30 Year'!$AF58)
A54: ='30 Year'!Q62 -> Paint 4 Full Buildings and Trim on 2 Stucco Buildings | B54: =SUMIF('30 Year'!$R$1:$AC$1,"<="&$G$3,'30 Year'!$R$53:$AC$53) -> 0 | C54: ='30 Year'!AE62 -> 187035 | D54: =$B54/$C54 -> 0 | E54: =if('30 Year'!$AF62<0,'30 Year'!$AF62," ") | F54: =if('30 Year'!$AF62<=0," ",'30 Year'!$AF62)
A55: ='30 Year'!Q64 -> Guardrails on the patio area next to the pool | B55: =SUMIF('30 Year'!$R$1:$AC$1,"<="&$G$3,'30 Year'!$R$53:$AC$53) -> 0 | C55: ='30 Year'!AE64 -> 17620 | D55: =$B55/$C55 -> 0 | E55: =if('30 Year'!$AF64<0,'30 Year'!$AF64," ") | F55: =if('30 Year'!$AF64<=0," ",'30 Year'!$AF64)
A56: ='30 Year'!Q65 -> Replace/Repair Skylights | B56: =SUMIF('30 Year'!$R$1:$AC$1,"<="&$G$3,'30 Year'!$R$53:$AC$53) -> 0 | C56: ='30 Year'!AE65 -> 5810 | D56: =$B56/$C56 -> 0 | E56: =if('30 Year'!$AF65<0,'30 Year'!$AF65," ") | F56: =if('30 Year'!$AF65<=0," ",'30 Year'!$AF65)
A57: ='30 Year'!Q66 -> Repair retaining wall by building 4 | B57: =SUMIF('30 Year'!$R$1:$AC$1,"<="&$G$3,'30 Year'!$R$53:$AC$53) -> 0 | C57: ='30 Year'!AE66 -> 10170 | D57: =$B57/$C57 -> 0 | E57: =if('30 Year'!$AF66<0,'30 Year'!$AF66," ") | F57: =if('30 Year'!$AF66<=0," ",'30 Year'!$AF66)
A58: ='30 Year'!Q67 -> Townhouse Walls, Decks | B58: =SUMIF('30 Year'!$R$1:$AC$1,"<="&$G$3,'30 Year'!$R$53:$AC$53) -> 0 | C58: ='30 Year'!AE67 -> 48000 | D58: =$B58/$C58 -> 0 | E58: =if('30 Year'!$AF67<0,'30 Year'!$AF67," ") | F58: =if('30 Year'!$AF67<=0," ",'30 Year'!$AF67)
A59: ='30 Year'!Q70 -> Roof Inspection and Repair, All Bldgs | B59: =SUMIF('30 Year'!$R$1:$AC$1,"<="&$G$3,'30 Year'!$R$53:$AC$53) -> 0 | C59: ='30 Year'!AE70 -> 15041 | D59: =$B59/$C59 -> 0 | E59: =if('30 Year'!$AF70<0,'30 Year'!$AF70," ") | F59: =if('30 Year'!$AF70<=0," ",'30 Year'!$AF70)
A60: ='30 Year'!Q71 -> Sidewalks, Replace Concrete | B60: =SUMIF('30 Year'!$R$1:$AC$1,"<="&$G$3,'30 Year'!$R$53:$AC$53) -> 0 | C60: ='30 Year'!AE71 -> 6000 | D60: =$B60/$C60 -> 0 | E60: =if('30 Year'!$AF71<0,'30 Year'!$AF71," ") | F60: =if('30 Year'!$AF71<=0," ",'30 Year'!$AF71)
A61: ='30 Year'!Q72 -> Gutter work, Bldg 13 | B61: =SUMIF('30 Year'!$R$1:$AC$1,"<="&$G$3,'30 Year'!$R$53:$AC$53) -> 0 | C61: ='30 Year'!AE72 -> 25000 | D61: =$B61/$C61 -> 0 | E61: =if('30 Year'!$AF72<0,'30 Year'!$AF72," ") | F61: =if('30 Year'!$AF72<=0," ",'30 Year'!$AF72)
A62: ='30 Year'!Q74 -> Tree Removal & Grind, 15 Small Trees | B62: =SUMIF('30 Year'!$R$1:$AC$1,"<="&$G$3,'30 Year'!$R$53:$AC$53) -> 0 | C62: ='30 Year'!AE74 -> 15605 | D62: =$B62/$C62 -> 0 | E62: =if('30 Year'!$AF74<0,'30 Year'!$AF74," ") | F62: =if('30 Year'!$AF74<=0," ",'30 Year'!$AF74)
A63: ='30 Year'!Q75 -> Stairwell Guardrail, Replace on Unit 420 | B63: =SUMIF('30 Year'!$R$1:$AC$1,"<="&$G$3,'30 Year'!$R$53:$AC$53) -> 0 | C63: ='30 Year'!AE75 -> 4191 | D63: =$B63/$C63 -> 0 | E63: =if('30 Year'!$AF75<0,'30 Year'!$AF75," ") | F63: =if('30 Year'!$AF75<=0," ",'30 Year'!$AF75)
A64: ='30 Year'!Q76 -> Balcony and Stairwell Repairs, 41 Treads | B64: =SUMIF('30 Year'!$R$1:$AC$1,"<="&$G$3,'30 Year'!$R$53:$AC$53) -> 0 | C64: ='30 Year'!AE76 -> 23173 | D64: =$B64/$C64 -> 0 | E64: =if('30 Year'!$AF76<0,'30 Year'!$AF76," ") | F64: =if('30 Year'!$AF76<=0," ",'30 Year'!$AF76)
A65: TOTAL | B65: =SUM(B49:B64) -> 0 | C65: =SUM(C49:C64) -> 648525 | D65: =SUM(D49:D64) -> 0 | E65: =SUM(E49:E64) -> 0 | F65: =SUM(F49:F64) -> 0

Sheet 26 Budget
A1: Ridge Park Luxury Condominiums 2026 Adopted Budget
A3: CASH BALANCE Jan 1, 2026 | C3: ='30 Year'!$R$9 -> 607915.91
A6: CASH IN
A7: Income from General Assessment for Common Expenses | C7: =138*'30 Year'!$R$49*12 -> 703800
A8: Income from HOA Owned Unit | C8: ='30 Year'!AE13 -> 30000
A9: Income from Reserve Funds Interest | C9: ='30 Year'!AE11 -> 5300
A10: Income From RV Parking Fees | C10: ='30 Year'!$AE$14 -> 2100
A11: Income from Late Fees, Resale Certificates | C11: ='30 Year'!AE15 -> 0
A12: Income from Reserve Assessment for Inadequate Reserves | C12: =138*'30 Year'!AE48*12 -> 0
A13: TOTAL CASH IN | C13: =SUM(C7:C12) -> 741200
A15: CASH OUT
A16: Financial Management | C16: =SUM(B17:B19) -> 112216
A17: Accounting | B17: ='30 Year'!AE19 -> 6824
A18: Insurance | B18: ='30 Year'!AE20 -> 95097
A19: Legal/Professional Services | B19: ='30 Year'!AE21 -> 10295
A20: Maintenance and Repairs | C20: =SUM(B21:B26) -> 165362
A21: Equipment Repairs | B21: ='30 Year'!AE24 -> 1969
A22: Grounds Maintenance | B22: ='30 Year'!AE25 -> 61874
A23: Facility Maintenance (Misc Repairs) | B23: ='30 Year'!AE26 -> 71892
A24: Pool Maintenance/Start-up | B24: ='30 Year'!AE28 -> 8850
A25: Rental Unit Maintenance | B25: ='30 Year'!AE29 -> 1538
A26: Snow Removal | B26: ='30 Year'!AE30 -> 19239
A27: Salary Expenses | C27: =SUM(B28:B29) -> 53658
A28: Business Office Salaries | B28: ='30 Year'!AE33 -> 49400
A29: Payroll Taxes | B29: ='30 Year'!AE35 -> 4258
A30: Office Expenses | C30: =SUM(B31:B33) -> 1540
A31: Office Supplies | B31: ='30 Year'!AE38 -> 1306
A32: Postage and Freight | B32: ='30 Year'!AE39 -> 149
A33: Travel/Mileage Reimbursement | B33: ='30 Year'!AE40 -> 85
A34: Utilities | C34: =SUM(B35:B36) -> 154613
A35: Water, Sewer, Electrical & Trash | B35: ='30 Year'!AE43 -> 150000
A36: Telecom/Internet Services | B36: ='30 Year'!AE44 -> 4613
A37: Facilities Maintenance PROJECTS | C37: ='30 Year'!AD27 -> 648525
A38: TOTAL CASH OUT | C38: =SUM(C16:C37) -> 1135914
A41: CASH BALANCE Dec 31, 2026 | C41: ='30 Year'!AE47 -> 235497
A44: TOTAL MONTHLY ASSESSMENT | C44: =SUM(B45:B46) -> 425
A45: Monthly General Assessment for Common Expenses | B45: ='30 Year'!$R$49 -> 425
A46: Monthly Reserve Assessment for Inadequate Reserves | B46: ='30 Year'!R50 -> 0

Sheet 26 Projects
A1: Ridge Park Luxury Condominiums 2026 Facilities Maintenance Projects
A3: PRIORITY # | B3: Planned Expenditures (revised 4/27/26 Workshop) | D3: =SUM(C4:C19) -> 648525 | E3: 4/27/26 Workshop Attendees
A4: 1 | B4: ='30 Year'!$Q62 -> Paint 4 Full Buildings and Trim on 2 Stucco Buildings | C4: ='30 Year'!$AD62 -> 187035
A5: 2 | B5: ='30 Year'!$Q53 -> Asphalt Cracks & Holes, Fill | C5: ='30 Year'!$AD53 -> 48000 | E5: Which areas?
A6: 3 | B6: ='30 Year'!$Q75 -> Stairwell Guardrail, Replace on Unit 420 | C6: ='30 Year'!$AD75 -> 4191
A7: 4 | B7: ='30 Year'!$Q76 -> Balcony and Stairwell Repairs, 41 Treads | C7: ='30 Year'!$AD76 -> 23173
A8: 5 | B8: ='30 Year'!$Q64 -> Guardrails on the patio area next to the pool | C8: ='30 Year'!$AD64 -> 17620
A9: 6 | B9: ='30 Year'!$Q55 -> Landscaping, Wildfire Defensible Space | C9: ='30 Year'!$AD55 -> 10000
A10: 7 | B10: ='30 Year'!$Q56 -> Chimney Chase Flashing & Siding Repairs, 13 Bldgs | C10: ='30 Year'!$AD56 -> 54348
A11: 7 | B11: ='30 Year'!$Q57 -> Roof Flashing Repairs, 13 Buildings | C11: ='30 Year'!$AD57 -> 64835
A12: 7 | B12: ='30 Year'!$Q58 -> Chimney Chase Covers, 76 Covers | C12: ='30 Year'!$AD58 -> 113697 | E12: Need to identify Chases that need new covers.
A13: 8 | B13: ='30 Year'!$Q65 -> Replace/Repair Skylights | C13: ='30 Year'!$AD65 -> 5810
A14: 9 | B14: ='30 Year'!$Q66 -> Repair retaining wall by building 4 | C14: ='30 Year'!$AD66 -> 10170
A15: 10 | B15: ='30 Year'!$Q67 -> Townhouse Walls, Decks | C15: ='30 Year'!$AD67 -> 48000
A16: 11 | B16: ='30 Year'!$Q72 -> Gutter work, Bldg 13 | C16: ='30 Year'!$AD72 -> 25000
A17: 12 | B17: ='30 Year'!$Q71 -> Sidewalks, Replace Concrete | C17: ='30 Year'!$AD71 -> 6000
A18: 13 | B18: ='30 Year'!$Q74 -> Tree Removal & Grind, 15 Small Trees | C18: ='30 Year'!$AD74 -> 15605
A19: 14 | B19: ='30 Year'!$Q70 -> Roof Inspection and Repair, All Bldgs | C19: ='30 Year'!$AD70 -> 15041

Sheet Policy
C1: RP Financing Policy (Proposed)
A3: "Investigate all Financing Options before assessing more money from owners."
C6: Financing Options in Order of Investigation Priority:
B7: Priority
B8: 1 | C8: Spread Project Costs/Multi-year
B9: 2 | C9: Delay a Project 1 or more years
B10: 3 | C10: Accept Contractor Financing
B11: 4 | C11: Obtain Line of Credit
B12: 5 | C12: Obtain Loan
B13: 6 | C13: Sell HOA Asset
B14: 7 | C14: Assess Owners

Sheet Insurance Data
B1: Ridge Park
A2: Estimated Dimensions and Areas
A4: Bldg # | B4: Building Stories | C4: Building Footprint Square Ft
A5: 1 | B5: 3 | C5: 6491.3915
A6: 2 | B6: 3 | C6: 6491.3915
A7: 3 | B7: 3 | C7: 12021.095
A8: 4 | B8: 3 | C8: 15418.459
A9: 5 | B9: 3 | C9: 11908.749
A10: 6 | B10: 3 | C10: 7513.7463
A11: 7 | B11: 3 | C11: 7513.7463
A12: 8 | B12: 3 | C12: 11908.749
A13: 9 | B13: 2 | C13: 7118.286
A14: 10 | B14: 3 | C14: 4887.0808
A15: 11 | B15: 2 | C15: 7118.286
A16: 12 | B16: 3 | C16: 5999.313
A17: 13 | B17: 3 | C17: 6024.0292
A18: 505 Club | B18: 2 | C18: 4720.8077
C19: 115135.13

Sheet 2024 Projects
A1: Job | B1: $ | C1: Urgency | D1: Comment | E1: Source
A2: Install Gutters (4.5 Bldgs) | B2: 88300 | C2: Low | D2: ABC Roofing can spread over 3 years plus extra for set-up (assume 20% extra). $220,748 for all w/ Leaf Guards. $166,367 for all w/o Leaf Guards. Manny replaced gutters on north side of Building 1 for $5,174.80 in 2022.
A3: Paint stairs Safety Yellow | B3: 35 | C3: High | D3: Insurance Survey Observation. 1 gallon.
A4: Paint Parking Spaces | B4: 155 | C4: High | D4: Insurance Survey Observation. 5 gallons.
A5: Paint Handicap Parking Spaces | B5: 35 | C5: High | D5: Insurance Survey Observation. 1 gallon.
A6: Remove 5 Tree Stumps along Oppenheimer Dr. | B6: 1500 | C6: Low | D6: Victors Landscaping. $300 each. Would simplify some landscaping work.
A7: Clean All Gutters | B7: 6000 | C7: High | D7: Insurance Survey Observation. Estimate from Manny Jaquez. Doing now?
A8: Remove Snow | B8: 20000 | C8: High | D8: Variable cost. Last year $14,035 was budgeted for 2024.
A9: Remove Pine cones | C9: Medium | D9: Insurance Survey Observation. Part of Maintenance Contract Fixed Fee.
A10: Fill Asphalt cracks and potholes (test) | B10: 10000 | C10: Medium | D10: Insurance Survey Observation. Assess after initial payment. $65,584 etsimated for all asphalt.
A11: Remove 5 Selected Large Trees. | B11: 12500 | C11: High | D11: Insurance Survey Observation. Removed 3 dying trees and 3 problematic trees in 2023 for $12,863. Assume $2,500 average for large trees. Manny can remove the tree in front of Clubhouse that is heaving the sidewalk. | E11: Broadleaf trees are less flamable than pine.
A12: Repair Sprinkling System along Oppenheimer | B12: 6000 | C12: High | D12: Bid from Victor's Landscaping. Do it before growing season.Prerequisit for other landscaping projects.
A13: Remove grass and Install gravel in selected areas, Bldgs 5 & 14. | B13: 1000 | C13: Low | D13: Landscape Committee. 13 tons of gravel. Does not include grass removal, plastic sheeting, etc.
A14: Emergency Repairs | B14: 50000 | C14: High | D14: Based on 2023 experience. Variable. Too high?
A15: Repair 6 Potholes | B15: 400 | C15: High | D15: Insurance Survey Observation. Manny can do. | E15: https://sealmaster.net/faq/much-cost-fix-pothole/#:~:text=Typical%20cost%20to%20repair%20potholes,also%20affect%20the%20repair%20cost.
A16: Repair damaged window and door trim, and loose siding. | B16: 19010 | C16: High | D16: Do those likely to leak first.
A17: Seal likely leaks on roofs and flashing around all 57chimneys. | B17: 57000 | C17: High | D17: Some chimney chases are worse than others. Assume $1,000 per chase. Some of the 57 chimneys need repair. | E17: https://www.angi.com/articles/how-much-should-it-cost-replace-flashing-around-chimney.htm
A18: Seal all 24 flat roofs on Townhouse garages (2 done in 2023). | B18: 76800 | C18: Medium | D18: Single-Ply membranes cover garage roofs now. They can be repaired for about $4-8 per square foot. Assume $3,872 for each 22x22 foot area. Manny resealed two garage roofs for $6,312. Do as needed. | E18: https://www.fixr.com/costs/flat-roof-repair
A19: Inspect electrical boxes/breaker panels in 2024, clean and repair, if necessary | B19: 2000 | C19: High | D19: Insurance Survey Observation. Depends on inspection results. Assume estimate of $600 per panel. Inspector and Contractor should be two different companies. | E19: https://www.homewyse.com/maintenance_costs/cost_to_repair_electric_panel.html
A20: Maintain landscape sprinklers, borders, plants, etc., except mowing. | B20: 21094 | C20: Low | D20: Landscape Committee may do some. Must repair sprinkliers first. Paid Victors Landscaping $5,544 per month for 3 months in 2021 for grounds maintenance including mowing. Mowing may cost $1,000, but not weekly.
A21: Install Safety signs. | B21: 1500 | C21: High | D21: Insurance Survey Observation. Handicap Parking, other safety signs.
A22: From Pete Carson:
A23: Electrical box inspection and maintenance $10K | B23: 10000 | D23: Inspection may cost $2,000. Results would identify additional repairs.
A24: Flat roof sealing $26K | B24: 26000 | D24: Manny said that he can repair membrane on garage roofs and do not need replacement for years.
A25: Roof and flashing sealing $30K | B25: 30000 | D25: Manny could identify immediate needs.
A26: Part time office assistant $22K (1000 hr.@$22.00/he.) | B26: 22000 | D26: Job Description? Who will supervise?
A27: Tree removal $25K | B27: 25000 | D27: $2,500 to remove one 60-FT (Large) tree. 10 large trees over the next two years seems reseaonable.
A28: Landscaping $15K | B28: 15000 | D28: Must fix Sprinklers first. Victors Landscaping estimated $6,000 for area along Oppenheimer.
A29: T&M snow removal $8K | B29: 8000 | D29: Last year $14,035 was budgeted for 2024.
A30: T&M yard maintenance $8K | B30: 8000 | D30: Last year $21,094 was budgeted for landscape, mowing, and removal of 5 large 60-FT trees.
A31: T&M misc. $10K | B31: 10000 | D31: The Operating budget or Emergency Repairs line can probably absorb this.
